Workbook

Sheet Cash Flow
A1: CASH FLOW STATEMENT
A2: 2018–2025 history · 2026–2032 forecasts
A4: PERIOD | B4: 2018A | C4: 2019A | D4: 2020A | E4: 2021A | F4: 2022A | G4: 2023A | H4: 2024A | I4: 2025A | J4: 2026E (9A+3F) | K4: 2027F | L4: 2028F | M4: 2029F | N4: 2030F | O4: 2031F | P4: 2032F
A5: FISCAL YEAR | B5: 2018 | C5: 2019 | D5: 2020 | E5: 2021 | F5: 2022 | G5: 2023 | H5: 2024 | I5: 2025 | J5: 2026 | K5: 2027 | L5: 2028 | M5: 2029 | N5: 2030 | O5: 2031 | P5: 2032
A7: CASH FROM OPERATING ACTIVITIES
A8: Net income / (loss) | B8: ='Income Statement'!B36 -> -1920000 | C8: ='Income Statement'!C36 -> -2650000 | D8: ='Income Statement'!D36 -> -4300000 | E8: ='Income Statement'!E36 -> -5682000 | F8: ='Income Statement'!F36 -> -21085000 | G8: ='Income Statement'!G36 -> -40000000 | H8: ='Income Statement'!H36 -> -62437500 | I8: ='Income Statement'!I36 -> -90065000 | ... P8: ='Income Statement'!P36 -> -104128599
A9: Add: depreciation and amortization | B9: ='Income Statement'!B27 -> 30000 | C9: ='Income Statement'!C27 -> 120000 | D9: ='Income Statement'!D27 -> 240000 | E9: ='Income Statement'!E27 -> 450000 | F9: ='Income Statement'!F27 -> 1100000 | G9: ='Income Statement'!G27 -> 3000000 | H9: ='Income Statement'!H27 -> 5000000 | I9: ='Income Statement'!I27 -> 7000000 | ... P9: ='Income Statement'!P27 -> 55062814
A10: Add: noncash stock-based compensation | B10: ='Income Statement'!B26 -> 40000 | C10: ='Income Statement'!C26 -> 100000 | D10: ='Income Statement'!D26 -> 240000 | E10: ='Income Statement'!E26 -> 450000 | F10: ='Income Statement'!F26 -> 750000 | G10: ='Income Statement'!G26 -> 2000000 | H10: ='Income Statement'!H26 -> 4000000 | I10: ='Income Statement'!I26 -> 7000000 | ... P10: ='Income Statement'!P26 -> 36669490
A11: Change in accounts receivable | B11: =-('Balance Sheet'!B9-0) -> 0 | C11: =-('Balance Sheet'!C9-'Balance Sheet'!B9) -> -43836 | D11: =-('Balance Sheet'!D9-'Balance Sheet'!C9) -> -98630 | E11: =-('Balance Sheet'!E9-'Balance Sheet'!D9) -> -202739 | F11: =-('Balance Sheet'!F9-'Balance Sheet'!E9) -> -394521 | G11: =-('Balance Sheet'!G9-'Balance Sheet'!F9) -> -1495890 | H11: =-('Balance Sheet'!H9-'Balance Sheet'!G9) -> -4745206 | I11: =-('Balance Sheet'!I9-'Balance Sheet'!H9) -> -7441096 | J11: =-('Balance Sheet'!J9-'Balance Sheet'!I9) -> -5872874 | ... P11: =-('Balance Sheet'!P9-'Balance Sheet'!O9) -> -9095031
A12: Change in inventory | B12: =-('Balance Sheet'!B10-0) -> 0 | C12: =-('Balance Sheet'!C10-'Balance Sheet'!B10) -> 0 | D12: =-('Balance Sheet'!D10-'Balance Sheet'!C10) -> 0 | E12: =-('Balance Sheet'!E10-'Balance Sheet'!D10) -> 0 | F12: =-('Balance Sheet'!F10-'Balance Sheet'!E10) -> 0 | G12: =-('Balance Sheet'!G10-'Balance Sheet'!F10) -> 0 | H12: =-('Balance Sheet'!H10-'Balance Sheet'!G10) -> -2591600 | I12: =-('Balance Sheet'!I10-'Balance Sheet'!H10) -> -3648400 | J12: =-('Balance Sheet'!J10-'Balance Sheet'!I10) -> -2572626 | ... P12: =-('Balance Sheet'!P10-'Balance Sheet'!O10) -> -6561095
A13: Change in prepaid expenses | B13: =-('Balance Sheet'!B11-0) -> 0 | C13: =-('Balance Sheet'!C11-'Balance Sheet'!B11) -> -20000 | D13: =-('Balance Sheet'!D11-'Balance Sheet'!C11) -> -45000 | E13: =-('Balance Sheet'!E11-'Balance Sheet'!D11) -> -85000 | F13: =-('Balance Sheet'!F11-'Balance Sheet'!E11) -> -210000 | G13: =-('Balance Sheet'!G11-'Balance Sheet'!F11) -> -660000 | H13: =-('Balance Sheet'!H11-'Balance Sheet'!G11) -> -1920000 | I13: =-('Balance Sheet'!I11-'Balance Sheet'!H11) -> -2700000 | J13: =-('Balance Sheet'!J11-'Balance Sheet'!I11) -> -2296713 | ... P13: =-('Balance Sheet'!P11-'Balance Sheet'!O11) -> -1110672
A14: Change in accounts payable | B14: ='Balance Sheet'!B17-0 -> 9452 | C14: ='Balance Sheet'!C17-'Balance Sheet'!B17 -> 26747 | D14: ='Balance Sheet'!D17-'Balance Sheet'!C17 -> 75582 | E14: ='Balance Sheet'!E17-'Balance Sheet'!D17 -> 98411 | F14: ='Balance Sheet'!F17-'Balance Sheet'!E17 -> 535698 | G14: ='Balance Sheet'!G17-'Balance Sheet'!F17 -> 601644 | H14: ='Balance Sheet'!H17-'Balance Sheet'!G17 -> 2178110 | I14: ='Balance Sheet'!I17-'Balance Sheet'!H17 -> 2657808 | J14: ='Balance Sheet'!J17-'Balance Sheet'!I17 -> 2860156 | ... P14: ='Balance Sheet'!P17-'Balance Sheet'!O17 -> 3413623
A15: Change in accrued expenses | B15: ='Balance Sheet'!B18-0 -> 92500 | C15: ='Balance Sheet'!C18-'Balance Sheet'!B18 -> 69500 | D15: ='Balance Sheet'!D18-'Balance Sheet'!C18 -> 163500 | E15: ='Balance Sheet'!E18-'Balance Sheet'!D18 -> 210500 | F15: ='Balance Sheet'!F18-'Balance Sheet'!E18 -> 1664000 | G15: ='Balance Sheet'!G18-'Balance Sheet'!F18 -> 2100000 | H15: ='Balance Sheet'!H18-'Balance Sheet'!G18 -> 4205000 | I15: ='Balance Sheet'!I18-'Balance Sheet'!H18 -> 6235000 | J15: ='Balance Sheet'!J18-'Balance Sheet'!I18 -> 5369630 | ... P15: ='Balance Sheet'!P18-'Balance Sheet'!O18 -> 5391922
A16: Change in deferred revenue | B16: ='Balance Sheet'!B19-0 -> 0 | C16: ='Balance Sheet'!C19-'Balance Sheet'!B19 -> 40000 | D16: ='Balance Sheet'!D19-'Balance Sheet'!C19 -> 116000 | E16: ='Balance Sheet'!E19-'Balance Sheet'!D19 -> 324000 | F16: ='Balance Sheet'!F19-'Balance Sheet'!E19 -> 840000 | G16: ='Balance Sheet'!G19-'Balance Sheet'!F19 -> 2420000 | H16: ='Balance Sheet'!H19-'Balance Sheet'!G19 -> 2200000 | I16: ='Balance Sheet'!I19-'Balance Sheet'!H19 -> 1020000 | J16: ='Balance Sheet'!J19-'Balance Sheet'!I19 -> 1566872 | ... P16: ='Balance Sheet'!P19-'Balance Sheet'!O19 -> 417833
A17: NET CASH FROM OPERATIONS | B17: =SUM(B8:B16) -> -1748048 | C17: =SUM(C8:C16) -> -2357589 | D17: =SUM(D8:D16) -> -3608548 | E17: =SUM(E8:E16) -> -4436828 | F17: =SUM(F8:F16) -> -16799823 | G17: =SUM(G8:G16) -> -32034246 | H17: =SUM(H8:H16) -> -54111196 | I17: =SUM(I8:I16) -> -79941688 | ... P17: =SUM(P8:P16) -> -19939715
A19: CASH FROM INVESTING ACTIVITIES
A20: Capital expenditures | B20: =-SUMIF('Monthly Data'!$B$2:$B1000,B$5,'Monthly Data'!$T$2:$T1000) -> -350000 | C20: =-SUMIF('Monthly Data'!$B$2:$B1000,C$5,'Monthly Data'!$T$2:$T1000) -> -750000 | D20: =-SUMIF('Monthly Data'!$B$2:$B1000,D$5,'Monthly Data'!$T$2:$T1000) -> -1250000 | E20: =-SUMIF('Monthly Data'!$B$2:$B1000,E$5,'Monthly Data'!$T$2:$T1000) -> -2500000 | F20: =-SUMIF('Monthly Data'!$B$2:$B1000,F$5,'Monthly Data'!$T$2:$T1000) -> -3000000 | G20: =-SUMIF('Monthly Data'!$B$2:$B1000,G$5,'Monthly Data'!$T$2:$T1000) -> -6000000 | H20: =-SUMIF('Monthly Data'!$B$2:$B1000,H$5,'Monthly Data'!$T$2:$T1000) -> -12000000 | I20: =-SUMIF('Monthly Data'!$B$2:$B1000,I$5,'Monthly Data'!$T$2:$T1000) -> -16000000 | ... P20: =-SUMIF('Monthly Data'!$B$2:$B1000,P$5,'Monthly Data'!$T$2:$T1000) -> -120279954
A21: NET CASH FROM INVESTING | B21: =B20 -> -350000 | C21: =C20 -> -750000 | D21: =D20 -> -1250000 | E21: =E20 -> -2500000 | F21: =F20 -> -3000000 | G21: =G20 -> -6000000 | H21: =H20 -> -12000000 | I21: =I20 -> -16000000 | ... P21: =P20 -> -120279954
A23: CASH FROM FINANCING ACTIVITIES
A24: Proceeds from equity financing | B24: =SUMIF('Monthly Data'!$B$2:$B1000,B$5,'Monthly Data'!$U$2:$U1000) -> 6000000 | C24: =SUMIF('Monthly Data'!$B$2:$B1000,C$5,'Monthly Data'!$U$2:$U1000) -> 0 | D24: =SUMIF('Monthly Data'!$B$2:$B1000,D$5,'Monthly Data'!$U$2:$U1000) -> 24000000 | E24: =SUMIF('Monthly Data'!$B$2:$B1000,E$5,'Monthly Data'!$U$2:$U1000) -> 0 | F24: =SUMIF('Monthly Data'!$B$2:$B1000,F$5,'Monthly Data'!$U$2:$U1000) -> 60000000 | G24: =SUMIF('Monthly Data'!$B$2:$B1000,G$5,'Monthly Data'!$U$2:$U1000) -> 0 | H24: =SUMIF('Monthly Data'!$B$2:$B1000,H$5,'Monthly Data'!$U$2:$U1000) -> 110000000 | I24: =SUMIF('Monthly Data'!$B$2:$B1000,I$5,'Monthly Data'!$U$2:$U1000) -> 0 | ... P24: =SUMIF('Monthly Data'!$B$2:$B1000,P$5,'Monthly Data'!$U$2:$U1000) -> 0
A25: Proceeds from venture debt | B25: =SUMIF('Monthly Data'!$B$2:$B1000,B$5,'Monthly Data'!$V$2:$V1000) -> 0 | C25: =SUMIF('Monthly Data'!$B$2:$B1000,C$5,'Monthly Data'!$V$2:$V1000) -> 0 | D25: =SUMIF('Monthly Data'!$B$2:$B1000,D$5,'Monthly Data'!$V$2:$V1000) -> 0 | E25: =SUMIF('Monthly Data'!$B$2:$B1000,E$5,'Monthly Data'!$V$2:$V1000) -> 0 | F25: =SUMIF('Monthly Data'!$B$2:$B1000,F$5,'Monthly Data'!$V$2:$V1000) -> 22000000 | G25: =SUMIF('Monthly Data'!$B$2:$B1000,G$5,'Monthly Data'!$V$2:$V1000) -> 40000000 | H25: =SUMIF('Monthly Data'!$B$2:$B1000,H$5,'Monthly Data'!$V$2:$V1000) -> 0 | I25: =SUMIF('Monthly Data'!$B$2:$B1000,I$5,'Monthly Data'!$V$2:$V1000) -> 40000000 | ... P25: =SUMIF('Monthly Data'!$B$2:$B1000,P$5,'Monthly Data'!$V$2:$V1000) -> 0
A26: Debt principal repayments | B26: =-SUMIF('Monthly Data'!$B$2:$B1000,B$5,'Monthly Data'!$W$2:$W1000) -> 0 | C26: =-SUMIF('Monthly Data'!$B$2:$B1000,C$5,'Monthly Data'!$W$2:$W1000) -> 0 | D26: =-SUMIF('Monthly Data'!$B$2:$B1000,D$5,'Monthly Data'!$W$2:$W1000) -> 0 | E26: =-SUMIF('Monthly Data'!$B$2:$B1000,E$5,'Monthly Data'!$W$2:$W1000) -> 0 | F26: =-SUMIF('Monthly Data'!$B$2:$B1000,F$5,'Monthly Data'!$W$2:$W1000) -> 0 | G26: =-SUMIF('Monthly Data'!$B$2:$B1000,G$5,'Monthly Data'!$W$2:$W1000) -> 0 | H26: =-SUMIF('Monthly Data'!$B$2:$B1000,H$5,'Monthly Data'!$W$2:$W1000) -> -5000000 | I26: =-SUMIF('Monthly Data'!$B$2:$B1000,I$5,'Monthly Data'!$W$2:$W1000) -> 0 | ... P26: =-SUMIF('Monthly Data'!$B$2:$B1000,P$5,'Monthly Data'!$W$2:$W1000) -> -15000000
A27: NET CASH FROM FINANCING | B27: =SUM(B24:B26) -> 6000000 | C27: =SUM(C24:C26) -> 0 | D27: =SUM(D24:D26) -> 24000000 | E27: =SUM(E24:E26) -> 0 | F27: =SUM(F24:F26) -> 82000000 | G27: =SUM(G24:G26) -> 40000000 | H27: =SUM(H24:H26) -> 105000000 | I27: =SUM(I24:I26) -> 40000000 | ... P27: =SUM(P24:P26) -> -15000000
A29: CASH RECONCILIATION
A30: NET CHANGE IN CASH | B30: =SUM(B17,B21,B27) -> 3901952 | C30: =SUM(C17,C21,C27) -> -3107589 | D30: =SUM(D17,D21,D27) -> 19141452 | E30: =SUM(E17,E21,E27) -> -6936828 | F30: =SUM(F17,F21,F27) -> 62200177 | G30: =SUM(G17,G21,G27) -> 1965754 | H30: =SUM(H17,H21,H27) -> 38888804 | I30: =SUM(I17,I21,I27) -> -55941688 | ... P30: =SUM(P17,P21,P27) -> -155219669
A31: Beginning cash and equivalents | B31: =0 -> 0 | C31: ='Balance Sheet'!B8 -> 3901952 | D31: ='Balance Sheet'!C8 -> 794363 | E31: ='Balance Sheet'!D8 -> 19935815 | F31: ='Balance Sheet'!E8 -> 12998987 | G31: ='Balance Sheet'!F8 -> 75199164 | H31: ='Balance Sheet'!G8 -> 77164918 | I31: ='Balance Sheet'!H8 -> 116053722 | J31: ='Balance Sheet'!I8 -> 60112034 | ... P31: ='Balance Sheet'!O8 -> -4125061
A32: ENDING CASH AND EQUIVALENTS | B32: =SUM(B30:B31) -> 3901952 | C32: =SUM(C30:C31) -> 794363 | D32: =SUM(D30:D31) -> 19935815 | E32: =SUM(E30:E31) -> 12998987 | F32: =SUM(F30:F31) -> 75199164 | G32: =SUM(G30:G31) -> 77164918 | H32: =SUM(H30:H31) -> 116053722 | I32: =SUM(I30:I31) -> 60112034 | ... P32: =SUM(P30:P31) -> -159344730
A33: Balance sheet ending cash (check) | B33: ='Balance Sheet'!B8 -> 3901952 | C33: ='Balance Sheet'!C8 -> 794363 | D33: ='Balance Sheet'!D8 -> 19935815 | E33: ='Balance Sheet'!E8 -> 12998987 | F33: ='Balance Sheet'!F8 -> 75199164 | G33: ='Balance Sheet'!G8 -> 77164918 | H33: ='Balance Sheet'!H8 -> 116053722 | I33: ='Balance Sheet'!I8 -> 60112034 | ... P33: ='Balance Sheet'!P8 -> -159344730
A34: Cash roll-forward difference (must = 0) | B34: =B32-B33 -> 0 | C34: =C32-C33 -> 0 | D34: =D32-D33 -> 0 | E34: =E32-E33 -> 0 | F34: =F32-F33 -> 0 | G34: =G32-G33 -> 0 | H34: =H32-H33 -> 0 | I34: =I32-I33 -> 0 | ... P34: =P32-P33 -> 0

Sheet Income Statement
A1: INCOME STATEMENT
A2: 2018–2025 synthetic history · 2026E (9 actual + 3 forecast) · 2027–2032 projections
A3: PERIOD | B3: 2018A | C3: 2019A | D3: 2020A | E3: 2021A | F3: 2022A | G3: 2023A | H3: 2024A | I3: 2025A | J3: 2026E (9A+3F) | K3: 2027F | L3: 2028F | M3: 2029F | N3: 2030F | O3: 2031F | P3: 2032F | Q3: Year | R3: Historical operating income ($) | S3: Forecast operating income ($) | T3: Operating break-even ($)
A4: FISCAL YEAR | B4: 2018 | C4: 2019 | D4: 2020 | E4: 2021 | F4: 2022 | G4: 2023 | H4: 2024 | I4: 2025 | J4: 2026 | K4: 2027 | L4: 2028 | M4: 2029 | N4: 2030 | O4: 2031 | P4: 2032 | Q4: =B4 -> 2018 | R4: =B29 -> -1920000 | S4: ="" | T4: 0
Q5: =C4 -> 2019 | R5: =C29 -> -2650000 | S5: ="" | T5: 0
A6: NET REVENUE | Q6: =D4 -> 2020 | R6: =D29 -> -4300000 | S6: ="" | T6: 0
A7: THX-101 licensed GLP-1 therapy | B7: =SUMIF('Monthly Data'!$B$2:$B1001,B$4,'Monthly Data'!$E$2:$E1001) -> 0 | C7: =SUMIF('Monthly Data'!$B$2:$B1001,C$4,'Monthly Data'!$E$2:$E1001) -> 0 | D7: =SUMIF('Monthly Data'!$B$2:$B1001,D$4,'Monthly Data'!$E$2:$E1001) -> 0 | E7: =SUMIF('Monthly Data'!$B$2:$B1001,E$4,'Monthly Data'!$E$2:$E1001) -> 0 | F7: =SUMIF('Monthly Data'!$B$2:$B1001,F$4,'Monthly Data'!$E$2:$E1001) -> 0 | G7: =SUMIF('Monthly Data'!$B$2:$B1001,G$4,'Monthly Data'!$E$2:$E1001) -> 0 | H7: =SUMIF('Monthly Data'!$B$2:$B1001,H$4,'Monthly Data'!$E$2:$E1001) -> 22000000 | I7: =SUMIF('Monthly Data'!$B$2:$B1001,I$4,'Monthly Data'!$E$2:$E1001) -> 65000000 | ... P7: =SUMIF('Monthly Data'!$B$2:$B1001,P$4,'Monthly Data'!$E$2:$E1001) -> 293464500 | Q7: =E4 -> 2021 | R7: =E29 -> -5682000 | S7: ="" | T7: 0
A8: THX-202 muscle treatment (scenario-dependent) | B8: =SUMIF('Monthly Data'!$B$2:$B1001,B$4,'Monthly Data'!$AI$2:$AI1001) -> 0 | C8: =SUMIF('Monthly Data'!$B$2:$B1001,C$4,'Monthly Data'!$AI$2:$AI1001) -> 0 | D8: =SUMIF('Monthly Data'!$B$2:$B1001,D$4,'Monthly Data'!$AI$2:$AI1001) -> 0 | E8: =SUMIF('Monthly Data'!$B$2:$B1001,E$4,'Monthly Data'!$AI$2:$AI1001) -> 0 | F8: =SUMIF('Monthly Data'!$B$2:$B1001,F$4,'Monthly Data'!$AI$2:$AI1001) -> 0 | G8: =SUMIF('Monthly Data'!$B$2:$B1001,G$4,'Monthly Data'!$AI$2:$AI1001) -> 0 | H8: =SUMIF('Monthly Data'!$B$2:$B1001,H$4,'Monthly Data'!$AI$2:$AI1001) -> 0 | I8: =SUMIF('Monthly Data'!$B$2:$B1001,I$4,'Monthly Data'!$AI$2:$AI1001) -> 0 | ... P8: =SUMIF('Monthly Data'!$B$2:$B1001,P$4,'Monthly Data'!$AI$2:$AI1001) -> 234454500 | Q8: =F4 -> 2022 | R8: =F29 -> -20150000 | S8: ="" | T8: 0
A9: Research services | B9: =SUMIF('Monthly Data'!$B$2:$B1001,B$4,'Monthly Data'!$F$2:$F1001) -> 0 | C9: =SUMIF('Monthly Data'!$B$2:$B1001,C$4,'Monthly Data'!$F$2:$F1001) -> 300000 | D9: =SUMIF('Monthly Data'!$B$2:$B1001,D$4,'Monthly Data'!$F$2:$F1001) -> 1000000 | E9: =SUMIF('Monthly Data'!$B$2:$B1001,E$4,'Monthly Data'!$F$2:$F1001) -> 2300000 | F9: =SUMIF('Monthly Data'!$B$2:$B1001,F$4,'Monthly Data'!$F$2:$F1001) -> 5000000 | G9: =SUMIF('Monthly Data'!$B$2:$B1001,G$4,'Monthly Data'!$F$2:$F1001) -> 11000000 | H9: =SUMIF('Monthly Data'!$B$2:$B1001,H$4,'Monthly Data'!$F$2:$F1001) -> 20000000 | I9: =SUMIF('Monthly Data'!$B$2:$B1001,I$4,'Monthly Data'!$F$2:$F1001) -> 22000000 | ... P9: =SUMIF('Monthly Data'!$B$2:$B1001,P$4,'Monthly Data'!$F$2:$F1001) -> 64616922 | Q9: =G4 -> 2023 | R9: =G29 -> -36430000 | S9: ="" | T9: 0
A10: Licensing / collaborations | B10: =SUMIF('Monthly Data'!$B$2:$B1001,B$4,'Monthly Data'!$G$2:$G1001) -> 0 | C10: =SUMIF('Monthly Data'!$B$2:$B1001,C$4,'Monthly Data'!$G$2:$G1001) -> 100000 | D10: =SUMIF('Monthly Data'!$B$2:$B1001,D$4,'Monthly Data'!$G$2:$G1001) -> 300000 | E10: =SUMIF('Monthly Data'!$B$2:$B1001,E$4,'Monthly Data'!$G$2:$G1001) -> 700000 | F10: =SUMIF('Monthly Data'!$B$2:$B1001,F$4,'Monthly Data'!$G$2:$G1001) -> 1000000 | G10: =SUMIF('Monthly Data'!$B$2:$B1001,G$4,'Monthly Data'!$G$2:$G1001) -> 6000000 | H10: =SUMIF('Monthly Data'!$B$2:$B1001,H$4,'Monthly Data'!$G$2:$G1001) -> 7000000 | I10: =SUMIF('Monthly Data'!$B$2:$B1001,I$4,'Monthly Data'!$G$2:$G1001) -> 7000000 | ... P10: =SUMIF('Monthly Data'!$B$2:$B1001,P$4,'Monthly Data'!$G$2:$G1001) -> 7000000 | Q10: =H4 -> 2024 | R10: =H29 -> -57380000 | S10: ="" | T10: 0
A11: TOTAL NET REVENUE | B11: =SUM(B7:B10) -> 0 | C11: =SUM(C7:C10) -> 400000 | D11: =SUM(D7:D10) -> 1300000 | E11: =SUM(E7:E10) -> 3000000 | F11: =SUM(F7:F10) -> 6000000 | G11: =SUM(G7:G10) -> 17000000 | H11: =SUM(H7:H10) -> 49000000 | I11: =SUM(I7:I10) -> 94000000 | ... P11: =SUM(P7:P10) -> 599535922 | Q11: =I4 -> 2025 | R11: =I29 -> -83520000 | S11: =I29 -> -83520000 | T11: 0
Q12: =J4 -> 2026 | R12: ="" | S12: =J29 -> -138167410 | T12: 0
A13: COST OF REVENUE | Q13: =K4 -> 2027 | R13: ="" | S13: =K29 -> -87732459 | T13: 0
A14: THX-101 manufacturing, royalty & distribution | B14: =SUMIF('Monthly Data'!$B$2:$B1001,B$4,'Monthly Data'!$H$2:$H1001)+SUMIF('Monthly Data'!$B$2:$B1001,B$4,'Monthly Data'!$I$2:$I1001) -> 0 | C14: =SUMIF('Monthly Data'!$B$2:$B1001,C$4,'Monthly Data'!$H$2:$H1001)+SUMIF('Monthly Data'!$B$2:$B1001,C$4,'Monthly Data'!$I$2:$I1001) -> 0 | D14: =SUMIF('Monthly Data'!$B$2:$B1001,D$4,'Monthly Data'!$H$2:$H1001)+SUMIF('Monthly Data'!$B$2:$B1001,D$4,'Monthly Data'!$I$2:$I1001) -> 0 | E14: =SUMIF('Monthly Data'!$B$2:$B1001,E$4,'Monthly Data'!$H$2:$H1001)+SUMIF('Monthly Data'!$B$2:$B1001,E$4,'Monthly Data'!$I$2:$I1001) -> 0 | F14: =SUMIF('Monthly Data'!$B$2:$B1001,F$4,'Monthly Data'!$H$2:$H1001)+SUMIF('Monthly Data'!$B$2:$B1001,F$4,'Monthly Data'!$I$2:$I1001) -> 0 | G14: =SUMIF('Monthly Data'!$B$2:$B1001,G$4,'Monthly Data'!$H$2:$H1001)+SUMIF('Monthly Data'!$B$2:$B1001,G$4,'Monthly Data'!$I$2:$I1001) -> 0 | H14: =SUMIF('Monthly Data'!$B$2:$B1001,H$4,'Monthly Data'!$H$2:$H1001)+SUMIF('Monthly Data'!$B$2:$B1001,H$4,'Monthly Data'!$I$2:$I1001) -> 6820000 | I14: =SUMIF('Monthly Data'!$B$2:$B1001,I$4,'Monthly Data'!$H$2:$H1001)+SUMIF('Monthly Data'!$B$2:$B1001,I$4,'Monthly Data'!$I$2:$I1001) -> 19500000 | ... P14: =SUMIF('Monthly Data'!$B$2:$B1001,P$4,'Monthly Data'!$H$2:$H1001)+SUMIF('Monthly Data'!$B$2:$B1001,P$4,'Monthly Data'!$I$2:$I1001) -> 80409545 | Q14: =L4 -> 2028 | R14: ="" | S14: =L29 -> -43855319 | T14: 0
A15: THX-202 manufacturing & distribution | B15: =SUMIF('Monthly Data'!$B$2:$B1001,B$4,'Monthly Data'!$AJ$2:$AJ1001) -> 0 | C15: =SUMIF('Monthly Data'!$B$2:$B1001,C$4,'Monthly Data'!$AJ$2:$AJ1001) -> 0 | D15: =SUMIF('Monthly Data'!$B$2:$B1001,D$4,'Monthly Data'!$AJ$2:$AJ1001) -> 0 | E15: =SUMIF('Monthly Data'!$B$2:$B1001,E$4,'Monthly Data'!$AJ$2:$AJ1001) -> 0 | F15: =SUMIF('Monthly Data'!$B$2:$B1001,F$4,'Monthly Data'!$AJ$2:$AJ1001) -> 0 | G15: =SUMIF('Monthly Data'!$B$2:$B1001,G$4,'Monthly Data'!$AJ$2:$AJ1001) -> 0 | H15: =SUMIF('Monthly Data'!$B$2:$B1001,H$4,'Monthly Data'!$AJ$2:$AJ1001) -> 0 | I15: =SUMIF('Monthly Data'!$B$2:$B1001,I$4,'Monthly Data'!$AJ$2:$AJ1001) -> 0 | ... P15: =SUMIF('Monthly Data'!$B$2:$B1001,P$4,'Monthly Data'!$AJ$2:$AJ1001) -> 78575900 | Q15: =M4 -> 2029 | R15: ="" | S15: =M29 -> -47073355 | T15: 0
A16: Research service delivery | B16: =SUMIF('Monthly Data'!$B$2:$B1001,B$4,'Monthly Data'!$J$2:$J1001) -> 0 | C16: =SUMIF('Monthly Data'!$B$2:$B1001,C$4,'Monthly Data'!$J$2:$J1001) -> 120000 | D16: =SUMIF('Monthly Data'!$B$2:$B1001,D$4,'Monthly Data'!$J$2:$J1001) -> 440000 | E16: =SUMIF('Monthly Data'!$B$2:$B1001,E$4,'Monthly Data'!$J$2:$J1001) -> 1012000 | F16: =SUMIF('Monthly Data'!$B$2:$B1001,F$4,'Monthly Data'!$J$2:$J1001) -> 2200000 | G16: =SUMIF('Monthly Data'!$B$2:$B1001,G$4,'Monthly Data'!$J$2:$J1001) -> 4950000 | H16: =SUMIF('Monthly Data'!$B$2:$B1001,H$4,'Monthly Data'!$J$2:$J1001) -> 9000000 | I16: =SUMIF('Monthly Data'!$B$2:$B1001,I$4,'Monthly Data'!$J$2:$J1001) -> 9460000 | ... P16: =SUMIF('Monthly Data'!$B$2:$B1001,P$4,'Monthly Data'!$J$2:$J1001) -> 28442804 | Q16: =N4 -> 2030 | R16: ="" | S16: =N29 -> -56815353
A17: Licensing delivery | B17: =SUMIF('Monthly Data'!$B$2:$B1001,B$4,'Monthly Data'!$K$2:$K1001) -> 0 | C17: =SUMIF('Monthly Data'!$B$2:$B1001,C$4,'Monthly Data'!$K$2:$K1001) -> 10000 | D17: =SUMIF('Monthly Data'!$B$2:$B1001,D$4,'Monthly Data'!$K$2:$K1001) -> 30000 | E17: =SUMIF('Monthly Data'!$B$2:$B1001,E$4,'Monthly Data'!$K$2:$K1001) -> 70000 | F17: =SUMIF('Monthly Data'!$B$2:$B1001,F$4,'Monthly Data'!$K$2:$K1001) -> 100000 | G17: =SUMIF('Monthly Data'!$B$2:$B1001,G$4,'Monthly Data'!$K$2:$K1001) -> 480000 | H17: =SUMIF('Monthly Data'!$B$2:$B1001,H$4,'Monthly Data'!$K$2:$K1001) -> 560000 | I17: =SUMIF('Monthly Data'!$B$2:$B1001,I$4,'Monthly Data'!$K$2:$K1001) -> 560000 | ... P17: =SUMIF('Monthly Data'!$B$2:$B1001,P$4,'Monthly Data'!$K$2:$K1001) -> 560003 | Q17: =O4 -> 2031 | R17: ="" | S17: =O29 -> -74480551
A18: TOTAL COST OF REVENUE | B18: =SUM(B14:B17) -> 0 | C18: =SUM(C14:C17) -> 130000 | D18: =SUM(D14:D17) -> 470000 | E18: =SUM(E14:E17) -> 1082000 | F18: =SUM(F14:F17) -> 2300000 | G18: =SUM(G14:G17) -> 5430000 | H18: =SUM(H14:H17) -> 16380000 | I18: =SUM(I14:I17) -> 29520000 | ... P18: =SUM(P14:P17) -> 187988252 | Q18: =P4 -> 2032 | R18: ="" | S18: =P29 -> -102364853
A19: GROSS PROFIT | B19: =B11-B18 -> 0 | C19: =C11-C18 -> 270000 | D19: =D11-D18 -> 830000 | E19: =E11-E18 -> 1918000 | F19: =F11-F18 -> 3700000 | G19: =G11-G18 -> 11570000 | H19: =H11-H18 -> 32620000 | I19: =I11-I18 -> 64480000 | ... P19: =P11-P18 -> 411547670
A20: Gross margin % | B20: =IFERROR(B19/B11,0) -> 0 | C20: =IFERROR(C19/C11,0) -> 0.675 | D20: =IFERROR(D19/D11,0) -> 0.63846154 | E20: =IFERROR(E19/E11,0) -> 0.63933333 | F20: =IFERROR(F19/F11,0) -> 0.61666667 | G20: =IFERROR(G19/G11,0) -> 0.68058824 | H20: =IFERROR(H19/H11,0) -> 0.66571429 | I20: =IFERROR(I19/I11,0) -> 0.68595745 | ... P20: =IFERROR(P19/P11,0) -> 0.68644372
A22: OPERATING EXPENSES
A23: Research & development | B23: =SUMIF('Monthly Data'!$B$2:$B1001,B$4,'Monthly Data'!$L$2:$L1001)+SUMIF('Monthly Data'!$B$2:$B1001,B$4,'Monthly Data'!$M$2:$M1001) -> 1150000 | C23: =SUMIF('Monthly Data'!$B$2:$B1001,C$4,'Monthly Data'!$L$2:$L1001)+SUMIF('Monthly Data'!$B$2:$B1001,C$4,'Monthly Data'!$M$2:$M1001) -> 1650000 | D23: =SUMIF('Monthly Data'!$B$2:$B1001,D$4,'Monthly Data'!$L$2:$L1001)+SUMIF('Monthly Data'!$B$2:$B1001,D$4,'Monthly Data'!$M$2:$M1001) -> 2750000 | E23: =SUMIF('Monthly Data'!$B$2:$B1001,E$4,'Monthly Data'!$L$2:$L1001)+SUMIF('Monthly Data'!$B$2:$B1001,E$4,'Monthly Data'!$M$2:$M1001) -> 3800000 | F23: =SUMIF('Monthly Data'!$B$2:$B1001,F$4,'Monthly Data'!$L$2:$L1001)+SUMIF('Monthly Data'!$B$2:$B1001,F$4,'Monthly Data'!$M$2:$M1001) -> 15000000 | G23: =SUMIF('Monthly Data'!$B$2:$B1001,G$4,'Monthly Data'!$L$2:$L1001)+SUMIF('Monthly Data'!$B$2:$B1001,G$4,'Monthly Data'!$M$2:$M1001) -> 22000000 | H23: =SUMIF('Monthly Data'!$B$2:$B1001,H$4,'Monthly Data'!$L$2:$L1001)+SUMIF('Monthly Data'!$B$2:$B1001,H$4,'Monthly Data'!$M$2:$M1001) -> 44000000 | I23: =SUMIF('Monthly Data'!$B$2:$B1001,I$4,'Monthly Data'!$L$2:$L1001)+SUMIF('Monthly Data'!$B$2:$B1001,I$4,'Monthly Data'!$M$2:$M1001) -> 70000000 | ... P23: =SUMIF('Monthly Data'!$B$2:$B1001,P$4,'Monthly Data'!$L$2:$L1001)+SUMIF('Monthly Data'!$B$2:$B1001,P$4,'Monthly Data'!$M$2:$M1001) -> 149600421
A24: Sales and marketing | B24: =SUMIF('Monthly Data'!$B$2:$B1001,B$4,'Monthly Data'!$N$2:$N1001) -> 100000 | C24: =SUMIF('Monthly Data'!$B$2:$B1001,C$4,'Monthly Data'!$N$2:$N1001) -> 200000 | D24: =SUMIF('Monthly Data'!$B$2:$B1001,D$4,'Monthly Data'!$N$2:$N1001) -> 400000 | E24: =SUMIF('Monthly Data'!$B$2:$B1001,E$4,'Monthly Data'!$N$2:$N1001) -> 650000 | F24: =SUMIF('Monthly Data'!$B$2:$B1001,F$4,'Monthly Data'!$N$2:$N1001) -> 2000000 | G24: =SUMIF('Monthly Data'!$B$2:$B1001,G$4,'Monthly Data'!$N$2:$N1001) -> 9000000 | H24: =SUMIF('Monthly Data'!$B$2:$B1001,H$4,'Monthly Data'!$N$2:$N1001) -> 18000000 | I24: =SUMIF('Monthly Data'!$B$2:$B1001,I$4,'Monthly Data'!$N$2:$N1001) -> 36000000 | ... P24: =SUMIF('Monthly Data'!$B$2:$B1001,P$4,'Monthly Data'!$N$2:$N1001) -> 202242301
A25: General and administration | B25: =SUMIF('Monthly Data'!$B$2:$B1001,B$4,'Monthly Data'!$O$2:$O1001) -> 600000 | C25: =SUMIF('Monthly Data'!$B$2:$B1001,C$4,'Monthly Data'!$O$2:$O1001) -> 850000 | D25: =SUMIF('Monthly Data'!$B$2:$B1001,D$4,'Monthly Data'!$O$2:$O1001) -> 1500000 | E25: =SUMIF('Monthly Data'!$B$2:$B1001,E$4,'Monthly Data'!$O$2:$O1001) -> 2250000 | F25: =SUMIF('Monthly Data'!$B$2:$B1001,F$4,'Monthly Data'!$O$2:$O1001) -> 5000000 | G25: =SUMIF('Monthly Data'!$B$2:$B1001,G$4,'Monthly Data'!$O$2:$O1001) -> 12000000 | H25: =SUMIF('Monthly Data'!$B$2:$B1001,H$4,'Monthly Data'!$O$2:$O1001) -> 19000000 | I25: =SUMIF('Monthly Data'!$B$2:$B1001,I$4,'Monthly Data'!$O$2:$O1001) -> 28000000 | ... P25: =SUMIF('Monthly Data'!$B$2:$B1001,P$4,'Monthly Data'!$O$2:$O1001) -> 70337497
A26: Noncash stock compensation | B26: =SUMIF('Monthly Data'!$B$2:$B1001,B$4,'Monthly Data'!$P$2:$P1001) -> 40000 | C26: =SUMIF('Monthly Data'!$B$2:$B1001,C$4,'Monthly Data'!$P$2:$P1001) -> 100000 | D26: =SUMIF('Monthly Data'!$B$2:$B1001,D$4,'Monthly Data'!$P$2:$P1001) -> 240000 | E26: =SUMIF('Monthly Data'!$B$2:$B1001,E$4,'Monthly Data'!$P$2:$P1001) -> 450000 | F26: =SUMIF('Monthly Data'!$B$2:$B1001,F$4,'Monthly Data'!$P$2:$P1001) -> 750000 | G26: =SUMIF('Monthly Data'!$B$2:$B1001,G$4,'Monthly Data'!$P$2:$P1001) -> 2000000 | H26: =SUMIF('Monthly Data'!$B$2:$B1001,H$4,'Monthly Data'!$P$2:$P1001) -> 4000000 | I26: =SUMIF('Monthly Data'!$B$2:$B1001,I$4,'Monthly Data'!$P$2:$P1001) -> 7000000 | ... P26: =SUMIF('Monthly Data'!$B$2:$B1001,P$4,'Monthly Data'!$P$2:$P1001) -> 36669490
A27: Depreciation and amortization | B27: =SUMIF('Monthly Data'!$B$2:$B1001,B$4,'Monthly Data'!$Q$2:$Q1001) -> 30000 | C27: =SUMIF('Monthly Data'!$B$2:$B1001,C$4,'Monthly Data'!$Q$2:$Q1001) -> 120000 | D27: =SUMIF('Monthly Data'!$B$2:$B1001,D$4,'Monthly Data'!$Q$2:$Q1001) -> 240000 | E27: =SUMIF('Monthly Data'!$B$2:$B1001,E$4,'Monthly Data'!$Q$2:$Q1001) -> 450000 | F27: =SUMIF('Monthly Data'!$B$2:$B1001,F$4,'Monthly Data'!$Q$2:$Q1001) -> 1100000 | G27: =SUMIF('Monthly Data'!$B$2:$B1001,G$4,'Monthly Data'!$Q$2:$Q1001) -> 3000000 | H27: =SUMIF('Monthly Data'!$B$2:$B1001,H$4,'Monthly Data'!$Q$2:$Q1001) -> 5000000 | I27: =SUMIF('Monthly Data'!$B$2:$B1001,I$4,'Monthly Data'!$Q$2:$Q1001) -> 7000000 | ... P27: =SUMIF('Monthly Data'!$B$2:$B1001,P$4,'Monthly Data'!$Q$2:$Q1001) -> 55062814
A28: TOTAL OPERATING EXPENSES | B28: =SUM(B23:B27) -> 1920000 | C28: =SUM(C23:C27) -> 2920000 | D28: =SUM(D23:D27) -> 5130000 | E28: =SUM(E23:E27) -> 7600000 | F28: =SUM(F23:F27) -> 23850000 | G28: =SUM(G23:G27) -> 48000000 | H28: =SUM(H23:H27) -> 90000000 | I28: =SUM(I23:I27) -> 148000000 | ... P28: =SUM(P23:P27) -> 513912523
A29: OPERATING INCOME / (LOSS) | B29: =B19-B28 -> -1920000 | C29: =C19-C28 -> -2650000 | D29: =D19-D28 -> -4300000 | E29: =E19-E28 -> -5682000 | F29: =F19-F28 -> -20150000 | G29: =G19-G28 -> -36430000 | H29: =H19-H28 -> -57380000 | I29: =I19-I28 -> -83520000 | ... P29: =P19-P28 -> -102364853
A30: Operating margin % | B30: =IFERROR(B29/B11,0) -> 0 | C30: =IFERROR(C29/C11,0) -> -6.625 | D30: =IFERROR(D29/D11,0) -> -3.3076923 | E30: =IFERROR(E29/E11,0) -> -1.894 | F30: =IFERROR(F29/F11,0) -> -3.3583333 | G30: =IFERROR(G29/G11,0) -> -2.1429412 | H30: =IFERROR(H29/H11,0) -> -1.1710204 | I30: =IFERROR(I29/I11,0) -> -0.88851064 | ... P30: =IFERROR(P29/P11,0) -> -0.17074015
A32: OTHER ITEMS
A33: Interest expense (venture debt) | B33: =SUMIF('Monthly Data'!$B$2:$B1001,B$4,'Monthly Data'!$R$2:$R1001) -> 0 | C33: =SUMIF('Monthly Data'!$B$2:$B1001,C$4,'Monthly Data'!$R$2:$R1001) -> 0 | D33: =SUMIF('Monthly Data'!$B$2:$B1001,D$4,'Monthly Data'!$R$2:$R1001) -> 0 | E33: =SUMIF('Monthly Data'!$B$2:$B1001,E$4,'Monthly Data'!$R$2:$R1001) -> 0 | F33: =SUMIF('Monthly Data'!$B$2:$B1001,F$4,'Monthly Data'!$R$2:$R1001) -> 935000 | G33: =SUMIF('Monthly Data'!$B$2:$B1001,G$4,'Monthly Data'!$R$2:$R1001) -> 3570000 | H33: =SUMIF('Monthly Data'!$B$2:$B1001,H$4,'Monthly Data'!$R$2:$R1001) -> 5057500 | I33: =SUMIF('Monthly Data'!$B$2:$B1001,I$4,'Monthly Data'!$R$2:$R1001) -> 6545000 | ... P33: =SUMIF('Monthly Data'!$B$2:$B1001,P$4,'Monthly Data'!$R$2:$R1001) -> 1763746
A34: INCOME / (LOSS) BEFORE TAX | B34: =B29-B33 -> -1920000 | C34: =C29-C33 -> -2650000 | D34: =D29-D33 -> -4300000 | E34: =E29-E33 -> -5682000 | F34: =F29-F33 -> -21085000 | G34: =G29-G33 -> -40000000 | H34: =H29-H33 -> -62437500 | I34: =I29-I33 -> -90065000 | ... P34: =P29-P33 -> -104128599
A35: Income taxes | B35: =SUMIF('Monthly Data'!$B$2:$B1001,B$4,'Monthly Data'!$S$2:$S1001) -> 0 | C35: =SUMIF('Monthly Data'!$B$2:$B1001,C$4,'Monthly Data'!$S$2:$S1001) -> 0 | D35: =SUMIF('Monthly Data'!$B$2:$B1001,D$4,'Monthly Data'!$S$2:$S1001) -> 0 | E35: =SUMIF('Monthly Data'!$B$2:$B1001,E$4,'Monthly Data'!$S$2:$S1001) -> 0 | F35: =SUMIF('Monthly Data'!$B$2:$B1001,F$4,'Monthly Data'!$S$2:$S1001) -> 0 | G35: =SUMIF('Monthly Data'!$B$2:$B1001,G$4,'Monthly Data'!$S$2:$S1001) -> 0 | H35: =SUMIF('Monthly Data'!$B$2:$B1001,H$4,'Monthly Data'!$S$2:$S1001) -> 0 | I35: =SUMIF('Monthly Data'!$B$2:$B1001,I$4,'Monthly Data'!$S$2:$S1001) -> 0 | ... P35: =SUMIF('Monthly Data'!$B$2:$B1001,P$4,'Monthly Data'!$S$2:$S1001) -> 0
A36: NET INCOME / (LOSS) | B36: =B34-B35 -> -1920000 | C36: =C34-C35 -> -2650000 | D36: =D34-D35 -> -4300000 | E36: =E34-E35 -> -5682000 | F36: =F34-F35 -> -21085000 | G36: =G34-G35 -> -40000000 | H36: =H34-H35 -> -62437500 | I36: =I34-I35 -> -90065000 | ... P36: =P34-P35 -> -104128599
A37: Net margin % | B37: =IFERROR(B36/B11,0) -> 0 | C37: =IFERROR(C36/C11,0) -> -6.625 | D37: =IFERROR(D36/D11,0) -> -3.3076923 | E37: =IFERROR(E36/E11,0) -> -1.894 | F37: =IFERROR(F36/F11,0) -> -3.5141667 | G37: =IFERROR(G36/G11,0) -> -2.3529412 | H37: =IFERROR(H36/H11,0) -> -1.2742347 | I37: =IFERROR(I36/I11,0) -> -0.9581383 | ... P37: =IFERROR(P36/P11,0) -> -0.173682
A38: R&D / total revenue | B38: =IFERROR(B23/B11,0) -> 0 | C38: =IFERROR(C23/C11,0) -> 4.125 | D38: =IFERROR(D23/D11,0) -> 2.1153846 | E38: =IFERROR(E23/E11,0) -> 1.2666667 | F38: =IFERROR(F23/F11,0) -> 2.5 | G38: =IFERROR(G23/G11,0) -> 1.2941176 | H38: =IFERROR(H23/H11,0) -> 0.89795918 | I38: =IFERROR(I23/I11,0) -> 0.74468085 | ... P38: =IFERROR(P23/P11,0) -> 0.24952704

Sheet Balance Sheet
A1: BALANCE SHEET
A2: 2018–2025 history · 2026–2032 forecasts
A4: PERIOD | B4: 2018A | C4: 2019A | D4: 2020A | E4: 2021A | F4: 2022A | G4: 2023A | H4: 2024A | I4: 2025A | J4: 2026E (9A+3F) | K4: 2027F | L4: 2028F | M4: 2029F | N4: 2030F | O4: 2031F | P4: 2032F
A5: FISCAL YEAR | B5: 2018 | C5: 2019 | D5: 2020 | E5: 2021 | F5: 2022 | G5: 2023 | H5: 2024 | I5: 2025 | J5: 2026 | K5: 2027 | L5: 2028 | M5: 2029 | N5: 2030 | O5: 2031 | P5: 2032
A7: ASSETS
A8: Cash and cash equivalents | B8: {=INDEX('Monthly Data'!$AF$2:$AF1001,MATCH(DATE(B$5,12,1),'Monthly Data'!$A$2:$A1001,0))} -> 3901952 | C8: {=INDEX('Monthly Data'!$AF$2:$AF1001,MATCH(DATE(C$5,12,1),'Monthly Data'!$A$2:$A1001,0))} -> 794363 | D8: {=INDEX('Monthly Data'!$AF$2:$AF1001,MATCH(DATE(D$5,12,1),'Monthly Data'!$A$2:$A1001,0))} -> 19935815 | E8: {=INDEX('Monthly Data'!$AF$2:$AF1001,MATCH(DATE(E$5,12,1),'Monthly Data'!$A$2:$A1001,0))} -> 12998987 | F8: {=INDEX('Monthly Data'!$AF$2:$AF1001,MATCH(DATE(F$5,12,1),'Monthly Data'!$A$2:$A1001,0))} -> 75199164 | G8: {=INDEX('Monthly Data'!$AF$2:$AF1001,MATCH(DATE(G$5,12,1),'Monthly Data'!$A$2:$A1001,0))} -> 77164918 | H8: {=INDEX('Monthly Data'!$AF$2:$AF1001,MATCH(DATE(H$5,12,1),'Monthly Data'!$A$2:$A1001,0))} -> 116053722 | I8: {=INDEX('Monthly Data'!$AF$2:$AF1001,MATCH(DATE(I$5,12,1),'Monthly Data'!$A$2:$A1001,0))} -> 60112034 | ... P8: {=INDEX('Monthly Data'!$AF$2:$AF1001,MATCH(DATE(P$5,12,1),'Monthly Data'!$A$2:$A1001,0))} -> -159344730
A9: Accounts receivable | B9: {=INDEX('Monthly Data'!$X$2:$X1001,MATCH(DATE(B$5,12,1),'Monthly Data'!$A$2:$A1001,0))} -> 0 | C9: {=INDEX('Monthly Data'!$X$2:$X1001,MATCH(DATE(C$5,12,1),'Monthly Data'!$A$2:$A1001,0))} -> 43836 | D9: {=INDEX('Monthly Data'!$X$2:$X1001,MATCH(DATE(D$5,12,1),'Monthly Data'!$A$2:$A1001,0))} -> 142466 | E9: {=INDEX('Monthly Data'!$X$2:$X1001,MATCH(DATE(E$5,12,1),'Monthly Data'!$A$2:$A1001,0))} -> 345205 | F9: {=INDEX('Monthly Data'!$X$2:$X1001,MATCH(DATE(F$5,12,1),'Monthly Data'!$A$2:$A1001,0))} -> 739726 | G9: {=INDEX('Monthly Data'!$X$2:$X1001,MATCH(DATE(G$5,12,1),'Monthly Data'!$A$2:$A1001,0))} -> 2235616 | H9: {=INDEX('Monthly Data'!$X$2:$X1001,MATCH(DATE(H$5,12,1),'Monthly Data'!$A$2:$A1001,0))} -> 6980822 | I9: {=INDEX('Monthly Data'!$X$2:$X1001,MATCH(DATE(I$5,12,1),'Monthly Data'!$A$2:$A1001,0))} -> 14421918 | ... P9: {=INDEX('Monthly Data'!$X$2:$X1001,MATCH(DATE(P$5,12,1),'Monthly Data'!$A$2:$A1001,0))} -> 73140999
A10: Inventory | B10: {=INDEX('Monthly Data'!$Y$2:$Y1001,MATCH(DATE(B$5,12,1),'Monthly Data'!$A$2:$A1001,0))} -> 0 | C10: {=INDEX('Monthly Data'!$Y$2:$Y1001,MATCH(DATE(C$5,12,1),'Monthly Data'!$A$2:$A1001,0))} -> 0 | D10: {=INDEX('Monthly Data'!$Y$2:$Y1001,MATCH(DATE(D$5,12,1),'Monthly Data'!$A$2:$A1001,0))} -> 0 | E10: {=INDEX('Monthly Data'!$Y$2:$Y1001,MATCH(DATE(E$5,12,1),'Monthly Data'!$A$2:$A1001,0))} -> 0 | F10: {=INDEX('Monthly Data'!$Y$2:$Y1001,MATCH(DATE(F$5,12,1),'Monthly Data'!$A$2:$A1001,0))} -> 0 | G10: {=INDEX('Monthly Data'!$Y$2:$Y1001,MATCH(DATE(G$5,12,1),'Monthly Data'!$A$2:$A1001,0))} -> 0 | H10: {=INDEX('Monthly Data'!$Y$2:$Y1001,MATCH(DATE(H$5,12,1),'Monthly Data'!$A$2:$A1001,0))} -> 2591600 | I10: {=INDEX('Monthly Data'!$Y$2:$Y1001,MATCH(DATE(I$5,12,1),'Monthly Data'!$A$2:$A1001,0))} -> 6240000 | ... P10: {=INDEX('Monthly Data'!$Y$2:$Y1001,MATCH(DATE(P$5,12,1),'Monthly Data'!$A$2:$A1001,0))} -> 41577135
A11: Prepaid expenses | B11: {=INDEX('Monthly Data'!$Z$2:$Z1001,MATCH(DATE(B$5,12,1),'Monthly Data'!$A$2:$A1001,0))} -> 0 | C11: {=INDEX('Monthly Data'!$Z$2:$Z1001,MATCH(DATE(C$5,12,1),'Monthly Data'!$A$2:$A1001,0))} -> 20000 | D11: {=INDEX('Monthly Data'!$Z$2:$Z1001,MATCH(DATE(D$5,12,1),'Monthly Data'!$A$2:$A1001,0))} -> 65000 | E11: {=INDEX('Monthly Data'!$Z$2:$Z1001,MATCH(DATE(E$5,12,1),'Monthly Data'!$A$2:$A1001,0))} -> 150000 | F11: {=INDEX('Monthly Data'!$Z$2:$Z1001,MATCH(DATE(F$5,12,1),'Monthly Data'!$A$2:$A1001,0))} -> 360000 | G11: {=INDEX('Monthly Data'!$Z$2:$Z1001,MATCH(DATE(G$5,12,1),'Monthly Data'!$A$2:$A1001,0))} -> 1020000 | H11: {=INDEX('Monthly Data'!$Z$2:$Z1001,MATCH(DATE(H$5,12,1),'Monthly Data'!$A$2:$A1001,0))} -> 2940000 | I11: {=INDEX('Monthly Data'!$Z$2:$Z1001,MATCH(DATE(I$5,12,1),'Monthly Data'!$A$2:$A1001,0))} -> 5640000 | ... P11: {=INDEX('Monthly Data'!$Z$2:$Z1001,MATCH(DATE(P$5,12,1),'Monthly Data'!$A$2:$A1001,0))} -> 17039082
A12: Property, plant and equipment (net) | B12: =0-'Cash Flow'!B20-'Income Statement'!B27 -> 320000 | C12: ='Balance Sheet'!B12-'Cash Flow'!C20-'Income Statement'!C27 -> 950000 | D12: ='Balance Sheet'!C12-'Cash Flow'!D20-'Income Statement'!D27 -> 1960000 | E12: ='Balance Sheet'!D12-'Cash Flow'!E20-'Income Statement'!E27 -> 4010000 | F12: ='Balance Sheet'!E12-'Cash Flow'!F20-'Income Statement'!F27 -> 5910000 | G12: ='Balance Sheet'!F12-'Cash Flow'!G20-'Income Statement'!G27 -> 8910000 | H12: ='Balance Sheet'!G12-'Cash Flow'!H20-'Income Statement'!H27 -> 15910000 | I12: ='Balance Sheet'!H12-'Cash Flow'!I20-'Income Statement'!I27 -> 24910000 | J12: ='Balance Sheet'!I12-'Cash Flow'!J20-'Income Statement'!J27 -> 36517249 | ... P12: ='Balance Sheet'!O12-'Cash Flow'!P20-'Income Statement'!P27 -> 250956802
A13: TOTAL CURRENT ASSETS | B13: =SUM(B8:B11) -> 3901952 | C13: =SUM(C8:C11) -> 858199 | D13: =SUM(D8:D11) -> 20143281 | E13: =SUM(E8:E11) -> 13494192 | F13: =SUM(F8:F11) -> 76298890 | G13: =SUM(G8:G11) -> 80420534 | H13: =SUM(H8:H11) -> 128566144 | I13: =SUM(I8:I11) -> 86413952 | ... P13: =SUM(P8:P11) -> -27587514
A14: TOTAL ASSETS | B14: =SUM(B12:B13) -> 4221952 | C14: =SUM(C12:C13) -> 1808199 | D14: =SUM(D12:D13) -> 22103281 | E14: =SUM(E12:E13) -> 17504192 | F14: =SUM(F12:F13) -> 82208890 | G14: =SUM(G12:G13) -> 89330534 | H14: =SUM(H12:H13) -> 144476144 | I14: =SUM(I12:I13) -> 111323952 | ... P14: =SUM(P12:P13) -> 223369288
A16: LIABILITIES
A17: Accounts payable | B17: {=INDEX('Monthly Data'!$AA$2:$AA1001,MATCH(DATE(B$5,12,1),'Monthly Data'!$A$2:$A1001,0))} -> 9452 | C17: {=INDEX('Monthly Data'!$AA$2:$AA1001,MATCH(DATE(C$5,12,1),'Monthly Data'!$A$2:$A1001,0))} -> 36199 | D17: {=INDEX('Monthly Data'!$AA$2:$AA1001,MATCH(DATE(D$5,12,1),'Monthly Data'!$A$2:$A1001,0))} -> 111781 | E17: {=INDEX('Monthly Data'!$AA$2:$AA1001,MATCH(DATE(E$5,12,1),'Monthly Data'!$A$2:$A1001,0))} -> 210192 | F17: {=INDEX('Monthly Data'!$AA$2:$AA1001,MATCH(DATE(F$5,12,1),'Monthly Data'!$A$2:$A1001,0))} -> 745890 | G17: {=INDEX('Monthly Data'!$AA$2:$AA1001,MATCH(DATE(G$5,12,1),'Monthly Data'!$A$2:$A1001,0))} -> 1347534 | H17: {=INDEX('Monthly Data'!$AA$2:$AA1001,MATCH(DATE(H$5,12,1),'Monthly Data'!$A$2:$A1001,0))} -> 3525644 | I17: {=INDEX('Monthly Data'!$AA$2:$AA1001,MATCH(DATE(I$5,12,1),'Monthly Data'!$A$2:$A1001,0))} -> 6183452 | ... P17: {=INDEX('Monthly Data'!$AA$2:$AA1001,MATCH(DATE(P$5,12,1),'Monthly Data'!$A$2:$A1001,0))} -> 26082819
A18: Accrued operating expenses | B18: {=INDEX('Monthly Data'!$AB$2:$AB1001,MATCH(DATE(B$5,12,1),'Monthly Data'!$A$2:$A1001,0))} -> 92500 | C18: {=INDEX('Monthly Data'!$AB$2:$AB1001,MATCH(DATE(C$5,12,1),'Monthly Data'!$A$2:$A1001,0))} -> 162000 | D18: {=INDEX('Monthly Data'!$AB$2:$AB1001,MATCH(DATE(D$5,12,1),'Monthly Data'!$A$2:$A1001,0))} -> 325500 | E18: {=INDEX('Monthly Data'!$AB$2:$AB1001,MATCH(DATE(E$5,12,1),'Monthly Data'!$A$2:$A1001,0))} -> 536000 | F18: {=INDEX('Monthly Data'!$AB$2:$AB1001,MATCH(DATE(F$5,12,1),'Monthly Data'!$A$2:$A1001,0))} -> 2200000 | G18: {=INDEX('Monthly Data'!$AB$2:$AB1001,MATCH(DATE(G$5,12,1),'Monthly Data'!$A$2:$A1001,0))} -> 4300000 | H18: {=INDEX('Monthly Data'!$AB$2:$AB1001,MATCH(DATE(H$5,12,1),'Monthly Data'!$A$2:$A1001,0))} -> 8505000 | I18: {=INDEX('Monthly Data'!$AB$2:$AB1001,MATCH(DATE(I$5,12,1),'Monthly Data'!$A$2:$A1001,0))} -> 14740000 | ... P18: {=INDEX('Monthly Data'!$AB$2:$AB1001,MATCH(DATE(P$5,12,1),'Monthly Data'!$A$2:$A1001,0))} -> 40411198
A19: Deferred contract revenue | B19: {=INDEX('Monthly Data'!$AC$2:$AC1001,MATCH(DATE(B$5,12,1),'Monthly Data'!$A$2:$A1001,0))} -> 0 | C19: {=INDEX('Monthly Data'!$AC$2:$AC1001,MATCH(DATE(C$5,12,1),'Monthly Data'!$A$2:$A1001,0))} -> 40000 | D19: {=INDEX('Monthly Data'!$AC$2:$AC1001,MATCH(DATE(D$5,12,1),'Monthly Data'!$A$2:$A1001,0))} -> 156000 | E19: {=INDEX('Monthly Data'!$AC$2:$AC1001,MATCH(DATE(E$5,12,1),'Monthly Data'!$A$2:$A1001,0))} -> 480000 | F19: {=INDEX('Monthly Data'!$AC$2:$AC1001,MATCH(DATE(F$5,12,1),'Monthly Data'!$A$2:$A1001,0))} -> 1320000 | G19: {=INDEX('Monthly Data'!$AC$2:$AC1001,MATCH(DATE(G$5,12,1),'Monthly Data'!$A$2:$A1001,0))} -> 3740000 | H19: {=INDEX('Monthly Data'!$AC$2:$AC1001,MATCH(DATE(H$5,12,1),'Monthly Data'!$A$2:$A1001,0))} -> 5940000 | I19: {=INDEX('Monthly Data'!$AC$2:$AC1001,MATCH(DATE(I$5,12,1),'Monthly Data'!$A$2:$A1001,0))} -> 6960000 | ... P19: {=INDEX('Monthly Data'!$AC$2:$AC1001,MATCH(DATE(P$5,12,1),'Monthly Data'!$A$2:$A1001,0))} -> 13262304
A20: Current portion of debt | B20: {=INDEX('Monthly Data'!$AD$2:$AD1001,MATCH(DATE(B$5,12,1),'Monthly Data'!$A$2:$A1001,0))} -> 0 | C20: {=INDEX('Monthly Data'!$AD$2:$AD1001,MATCH(DATE(C$5,12,1),'Monthly Data'!$A$2:$A1001,0))} -> 0 | D20: {=INDEX('Monthly Data'!$AD$2:$AD1001,MATCH(DATE(D$5,12,1),'Monthly Data'!$A$2:$A1001,0))} -> 0 | E20: {=INDEX('Monthly Data'!$AD$2:$AD1001,MATCH(DATE(E$5,12,1),'Monthly Data'!$A$2:$A1001,0))} -> 0 | F20: {=INDEX('Monthly Data'!$AD$2:$AD1001,MATCH(DATE(F$5,12,1),'Monthly Data'!$A$2:$A1001,0))} -> 0 | G20: {=INDEX('Monthly Data'!$AD$2:$AD1001,MATCH(DATE(G$5,12,1),'Monthly Data'!$A$2:$A1001,0))} -> 5000000 | H20: {=INDEX('Monthly Data'!$AD$2:$AD1001,MATCH(DATE(H$5,12,1),'Monthly Data'!$A$2:$A1001,0))} -> 0 | I20: {=INDEX('Monthly Data'!$AD$2:$AD1001,MATCH(DATE(I$5,12,1),'Monthly Data'!$A$2:$A1001,0))} -> 0 | ... P20: {=INDEX('Monthly Data'!$AD$2:$AD1001,MATCH(DATE(P$5,12,1),'Monthly Data'!$A$2:$A1001,0))} -> 7000000
A21: TOTAL CURRENT LIABILITIES | B21: =SUM(B17:B20) -> 101952 | C21: =SUM(C17:C20) -> 238199 | D21: =SUM(D17:D20) -> 593281 | E21: =SUM(E17:E20) -> 1226192 | F21: =SUM(F17:F20) -> 4265890 | G21: =SUM(G17:G20) -> 14387534 | H21: =SUM(H17:H20) -> 17970644 | I21: =SUM(I17:I20) -> 27883452 | ... P21: =SUM(P17:P20) -> 86756321
A22: Long-term venture debt | B22: =B32-B20 -> 0 | C22: =C32-C20 -> 0 | D22: =D32-D20 -> 0 | E22: =E32-E20 -> 0 | F22: =F32-F20 -> 22000000 | G22: =G32-G20 -> 57000000 | H22: =H32-H20 -> 57000000 | I22: =I32-I20 -> 97000000 | ... P22: =P32-P20 -> 0
A23: TOTAL LIABILITIES | B23: =SUM(B21:B22) -> 101952 | C23: =SUM(C21:C22) -> 238199 | D23: =SUM(D21:D22) -> 593281 | E23: =SUM(E21:E22) -> 1226192 | F23: =SUM(F21:F22) -> 26265890 | G23: =SUM(G21:G22) -> 71387534 | H23: =SUM(H21:H22) -> 74970644 | I23: =SUM(I21:I22) -> 124883452 | ... P23: =SUM(P21:P22) -> 86756321
A25: STOCKHOLDERS EQUITY
A26: Additional paid-in capital | B26: =0+'Cash Flow'!B24+'Income Statement'!B26 -> 6040000 | C26: ='Balance Sheet'!B26+'Cash Flow'!C24+'Income Statement'!C26 -> 6140000 | D26: ='Balance Sheet'!C26+'Cash Flow'!D24+'Income Statement'!D26 -> 30380000 | E26: ='Balance Sheet'!D26+'Cash Flow'!E24+'Income Statement'!E26 -> 30830000 | F26: ='Balance Sheet'!E26+'Cash Flow'!F24+'Income Statement'!F26 -> 91580000 | G26: ='Balance Sheet'!F26+'Cash Flow'!G24+'Income Statement'!G26 -> 93580000 | H26: ='Balance Sheet'!G26+'Cash Flow'!H24+'Income Statement'!H26 -> 207580000 | I26: ='Balance Sheet'!H26+'Cash Flow'!I24+'Income Statement'!I26 -> 214580000 | J26: ='Balance Sheet'!I26+'Cash Flow'!J24+'Income Statement'!J26 -> 381860536 | ... P26: ='Balance Sheet'!O26+'Cash Flow'!P24+'Income Statement'!P26 -> 953194239
A27: Accumulated deficit / retained earnings | B27: =0+'Income Statement'!B36 -> -1920000 | C27: ='Balance Sheet'!B27+'Income Statement'!C36 -> -4570000 | D27: ='Balance Sheet'!C27+'Income Statement'!D36 -> -8870000 | E27: ='Balance Sheet'!D27+'Income Statement'!E36 -> -14552000 | F27: ='Balance Sheet'!E27+'Income Statement'!F36 -> -35637000 | G27: ='Balance Sheet'!F27+'Income Statement'!G36 -> -75637000 | H27: ='Balance Sheet'!G27+'Income Statement'!H36 -> -138074500 | I27: ='Balance Sheet'!H27+'Income Statement'!I36 -> -228139500 | J27: ='Balance Sheet'!I27+'Income Statement'!J36 -> -374551906 | ... P27: ='Balance Sheet'!O27+'Income Statement'!P36 -> -816581272
A28: TOTAL STOCKHOLDERS EQUITY | B28: =SUM(B26:B27) -> 4120000 | C28: =SUM(C26:C27) -> 1570000 | D28: =SUM(D26:D27) -> 21510000 | E28: =SUM(E26:E27) -> 16278000 | F28: =SUM(F26:F27) -> 55943000 | G28: =SUM(G26:G27) -> 17943000 | H28: =SUM(H26:H27) -> 69505500 | I28: =SUM(I26:I27) -> -13559500 | ... P28: =SUM(P26:P27) -> 136612967
A30: TOTAL LIABILITIES AND EQUITY | B30: =B23+B28 -> 4221952 | C30: =C23+C28 -> 1808199 | D30: =D23+D28 -> 22103281 | E30: =E23+E28 -> 17504192 | F30: =F23+F28 -> 82208890 | G30: =G23+G28 -> 89330534 | H30: =H23+H28 -> 144476144 | I30: =I23+I28 -> 111323952 | ... P30: =P23+P28 -> 223369288
A31: Balance sheet difference (must = 0) | B31: =B14-B30 -> 0 | C31: =C14-C30 -> 0 | D31: =D14-D30 -> 0 | E31: =E14-E30 -> 0 | F31: =F14-F30 -> 0 | G31: =G14-G30 -> 0 | H31: =H14-H30 -> 0 | I31: =I14-I30 -> 0 | ... P31: =P14-P30 -> 0
A32: Total debt (for interest calculation) | B32: {=INDEX('Monthly Data'!$AE$2:$AE1001,MATCH(DATE(B$5,12,1),'Monthly Data'!$A$2:$A1001,0))} -> 0 | C32: {=INDEX('Monthly Data'!$AE$2:$AE1001,MATCH(DATE(C$5,12,1),'Monthly Data'!$A$2:$A1001,0))} -> 0 | D32: {=INDEX('Monthly Data'!$AE$2:$AE1001,MATCH(DATE(D$5,12,1),'Monthly Data'!$A$2:$A1001,0))} -> 0 | E32: {=INDEX('Monthly Data'!$AE$2:$AE1001,MATCH(DATE(E$5,12,1),'Monthly Data'!$A$2:$A1001,0))} -> 0 | F32: {=INDEX('Monthly Data'!$AE$2:$AE1001,MATCH(DATE(F$5,12,1),'Monthly Data'!$A$2:$A1001,0))} -> 22000000 | G32: {=INDEX('Monthly Data'!$AE$2:$AE1001,MATCH(DATE(G$5,12,1),'Monthly Data'!$A$2:$A1001,0))} -> 62000000 | H32: {=INDEX('Monthly Data'!$AE$2:$AE1001,MATCH(DATE(H$5,12,1),'Monthly Data'!$A$2:$A1001,0))} -> 57000000 | I32: {=INDEX('Monthly Data'!$AE$2:$AE1001,MATCH(DATE(I$5,12,1),'Monthly Data'!$A$2:$A1001,0))} -> 97000000 | ... P32: {=INDEX('Monthly Data'!$AE$2:$AE1001,MATCH(DATE(P$5,12,1),'Monthly Data'!$A$2:$A1001,0))} -> 7000000

Sheet Monthly Data
A1: Month | B1: Fiscal year | C1: THX-101 prescription fills | D1: Institutional research clients | E1: THX-101 licensed GLP-1 revenue ($) | F1: Research services revenue ($) | G1: Licensing/collaboration revenue ($) | H1: THX-101 manufacturing & distribution ($) | I1: THX-101 partner licensing royalty ($) | J1: Research service delivery costs ($) | K1: License service delivery costs ($) | L1: THX-202 muscle research & trials ($) | M1: THX-303 bone discovery R&D ($) | N1: Sales and marketing expense ($) | O1: General & administration expense ($) | P1: Noncash stock compensation ($) | Q1: Depreciation & amortization ($) | R1: Venture debt interest expense ($) | S1: Income tax expense ($) | T1: Equipment/facilities capex ($) | U1: Equity funding proceeds ($) | V1: New debt proceeds ($) | W1: Debt principal repayments ($) | X1: Accounts receivable, month-end ($) | Y1: Inventory, month-end ($) | Z1: Prepaids, month-end ($) | AA1: Accounts payable, month-end ($) | AB1: Accrued expenses, month-end ($) | AC1: Deferred contract revenue, month-end ($) | AD1: Current debt, month-end ($) | AE1: Total debt, month-end ($) | AF1: Cash, month-end ($) | AG1: Cash change before equity ($) | AH1: THX-202 active treated patients | AI1: THX-202 commercial revenue ($) | AJ1: THX-202 commercial delivery costs ($) | AL1: FY2026 methodology
A2: 43101 | B2: =YEAR(A2) -> 2018 | C2: ='Revenue & Demand'!C166 -> 0 | D2: ='Revenue & Demand'!F166 -> 0 | E2: ='Revenue & Demand'!E166 -> 0 | F2: ='Revenue & Demand'!H166 -> 0 | G2: ='Revenue & Demand'!J166 -> 0 | H2: ='Manufacturing & Production'!F206 -> 0 | I2: ='Manufacturing & Production'!G206 -> 0 | J2: ='Workforce & Expenses'!M258 -> 0 | K2: ='Manufacturing & Production'!K206 -> 0 | L2: ='Clinical Trials & R&D'!F206 -> 96895 | M2: ='Clinical Trials & R&D'!I206 -> 0 | N2: ='Workforce & Expenses'!P258 -> 3632 | O2: ='Workforce & Expenses'!S258 -> 49115 | P2: ='Funding & Cap'!F61 -> 3009 | Q2: ='Working Capital & Assets'!B5 -> 2500 | R2: ='Funding & Cap'!H61 -> 0 | S2: ='Working Capital & Assets'!C5 -> 0 | T2: ='Working Capital & Assets'!D5 -> 22183 | U2: ='Funding & Cap'!B61 -> 6000000 | V2: ='Funding & Cap'!C61 -> 0 | W2: ='Funding & Cap'!D61 -> 0 | X2: ='Working Capital & Assets'!E5 -> 0 | Y2: ='Working Capital & Assets'!F5 -> 0 | Z2: ='Working Capital & Assets'!G5 -> 0 | AA2: ='Working Capital & Assets'!H5 -> 873 | AB2: ='Working Capital & Assets'!I5 -> 8541 | AC2: ='Working Capital & Assets'!J5 -> 0 | AD2: =MIN(AE2,SUMIFS($W$2:$W$181,$A$2:$A$181,">"&A2,$A$2:$A$181,"<="&EDATE(A2,12))+IF(AND(DATE(2033,12,1)>A2,DATE(2033,12,1)<=EDATE(A2,12)),'Funding & Cap'!$B$200,0)) -> 0 | AE2: ='Funding & Cap'!Q61 -> 0 | AF2: =AG2+U2 -> 5837589 | AG2: =SUM(E2:G2)-SUM(H2:S2)+P2+Q2-X2-Y2-Z2+AA2+AB2+AC2-T2+V2-W2 -> -162411 | AH2: ='Revenue & Demand'!P166 -> 0 | AI2: ='Revenue & Demand'!Q166 -> 0 | AJ2: ='Manufacturing & Production'!J206 -> 0 | AL2: Jan–Sep 2026 are fixed synthetic actuals, entered on historical operating schedules.
A3: 43132 | B3: =YEAR(A3) -> 2018 | C3: ='Revenue & Demand'!C167 -> 0 | D3: ='Revenue & Demand'!F167 -> 0 | E3: ='Revenue & Demand'!E167 -> 0 | F3: ='Revenue & Demand'!H167 -> 0 | G3: ='Revenue & Demand'!J167 -> 0 | H3: ='Manufacturing & Production'!F207 -> 0 | I3: ='Manufacturing & Production'!G207 -> 0 | J3: ='Workforce & Expenses'!M259 -> 0 | K3: ='Manufacturing & Production'!K207 -> 0 | L3: ='Clinical Trials & R&D'!F207 -> 99034 | M3: ='Clinical Trials & R&D'!I207 -> 0 | N3: ='Workforce & Expenses'!P259 -> 4487 | O3: ='Workforce & Expenses'!S259 -> 50150 | P3: ='Funding & Cap'!F62 -> 3068 | Q3: ='Working Capital & Assets'!B6 -> 2500 | R3: ='Funding & Cap'!H62 -> 0 | S3: ='Working Capital & Assets'!C6 -> 0 | T3: ='Working Capital & Assets'!D6 -> 22457 | U3: ='Funding & Cap'!B62 -> 0 | V3: ='Funding & Cap'!C62 -> 0 | W3: ='Funding & Cap'!D62 -> 0 | X3: ='Working Capital & Assets'!E6 -> 0 | Y3: ='Working Capital & Assets'!F6 -> 0 | Z3: ='Working Capital & Assets'!G6 -> 0 | AA3: ='Working Capital & Assets'!H6 -> 1723 | AB3: ='Working Capital & Assets'!I6 -> 16859 | AC3: ='Working Capital & Assets'!J6 -> 0 | AD3: =MIN(AE3,SUMIFS($W$2:$W$181,$A$2:$A$181,">"&A3,$A$2:$A$181,"<="&EDATE(A3,12))+IF(AND(DATE(2033,12,1)>A3,DATE(2033,12,1)<=EDATE(A3,12)),'Funding & Cap'!$B$200,0)) -> 0 | AE3: ='Funding & Cap'!Q62 -> 0 | AF3: =AF2+AG3+U3 -> 5670629 | AG3: =SUM(E3:G3)-SUM(H3:S3)+P3+Q3-(X3-X2)-(Y3-Y2)-(Z3-Z2)+(AA3-AA2)+(AB3-AB2)+(AC3-AC2)-T3+V3-W3 -> -166960 | AH3: ='Revenue & Demand'!P167 -> 0 | AI3: ='Revenue & Demand'!Q167 -> 0 | AJ3: ='Manufacturing & Production'!J207 -> 0 | AL3: Oct–Dec 2026 remain projections, rebased to YTD operating performance.
A4: 43160 | B4: =YEAR(A4) -> 2018 | C4: ='Revenue & Demand'!C168 -> 0 | D4: ='Revenue & Demand'!F168 -> 0 | E4: ='Revenue & Demand'!E168 -> 0 | F4: ='Revenue & Demand'!H168 -> 0 | G4: ='Revenue & Demand'!J168 -> 0 | H4: ='Manufacturing & Production'!F208 -> 0 | I4: ='Manufacturing & Production'!G208 -> 0 | J4: ='Workforce & Expenses'!M260 -> 0 | K4: ='Manufacturing & Production'!K208 -> 0 | L4: ='Clinical Trials & R&D'!F208 -> 99028 | M4: ='Clinical Trials & R&D'!I208 -> 0 | N4: ='Workforce & Expenses'!P260 -> 5342 | O4: ='Workforce & Expenses'!S260 -> 50741 | P4: ='Funding & Cap'!F63 -> 3127 | Q4: ='Working Capital & Assets'!B7 -> 2500 | R4: ='Funding & Cap'!H63 -> 0 | S4: ='Working Capital & Assets'!C7 -> 0 | T4: ='Working Capital & Assets'!D7 -> 55595 | U4: ='Funding & Cap'!B63 -> 0 | V4: ='Funding & Cap'!C63 -> 0 | W4: ='Funding & Cap'!D63 -> 0 | X4: ='Working Capital & Assets'!E7 -> 0 | Y4: ='Working Capital & Assets'!F7 -> 0 | Z4: ='Working Capital & Assets'!G7 -> 0 | AA4: ='Working Capital & Assets'!H7 -> 2533 | AB4: ='Working Capital & Assets'!I7 -> 24790 | AC4: ='Working Capital & Assets'!J7 -> 0 | AD4: =MIN(AE4,SUMIFS($W$2:$W$181,$A$2:$A$181,">"&A4,$A$2:$A$181,"<="&EDATE(A4,12))+IF(AND(DATE(2033,12,1)>A4,DATE(2033,12,1)<=EDATE(A4,12)),'Funding & Cap'!$B$200,0)) -> 0 | AE4: ='Funding & Cap'!Q63 -> 0 | AF4: =AF3+AG4+U4 -> 5468664 | AG4: =SUM(E4:G4)-SUM(H4:S4)+P4+Q4-(X4-X3)-(Y4-Y3)-(Z4-Z3)+(AA4-AA3)+(AB4-AB3)+(AC4-AC3)-T4+V4-W4 -> -201965 | AH4: ='Revenue & Demand'!P168 -> 0 | AI4: ='Revenue & Demand'!Q168 -> 0 | AJ4: ='Manufacturing & Production'!J208 -> 0 | AL4: 2026 annual statements = nine completed months + three forecast months.
A5: 43191 | B5: =YEAR(A5) -> 2018 | C5: ='Revenue & Demand'!C169 -> 0 | D5: ='Revenue & Demand'!F169 -> 0 | E5: ='Revenue & Demand'!E169 -> 0 | F5: ='Revenue & Demand'!H169 -> 0 | G5: ='Revenue & Demand'!J169 -> 0 | H5: ='Manufacturing & Production'!F209 -> 0 | I5: ='Manufacturing & Production'!G209 -> 0 | J5: ='Workforce & Expenses'!M261 -> 0 | K5: ='Manufacturing & Production'!K209 -> 0 | L5: ='Clinical Trials & R&D'!F209 -> 97167 | M5: ='Clinical Trials & R&D'!I209 -> 0 | N5: ='Workforce & Expenses'!P261 -> 6197 | O5: ='Workforce & Expenses'!S261 -> 50820 | P5: ='Funding & Cap'!F64 -> 3186 | Q5: ='Working Capital & Assets'!B8 -> 2500 | R5: ='Funding & Cap'!H64 -> 0 | S5: ='Working Capital & Assets'!C8 -> 0 | T5: ='Working Capital & Assets'!D8 -> 23005 | U5: ='Funding & Cap'!B64 -> 0 | V5: ='Funding & Cap'!C64 -> 0 | W5: ='Funding & Cap'!D64 -> 0 | X5: ='Working Capital & Assets'!E8 -> 0 | Y5: ='Working Capital & Assets'!F8 -> 0 | Z5: ='Working Capital & Assets'!G8 -> 0 | AA5: ='Working Capital & Assets'!H8 -> 3298 | AB5: ='Working Capital & Assets'!I8 -> 32275 | AC5: ='Working Capital & Assets'!J8 -> 0 | AD5: =MIN(AE5,SUMIFS($W$2:$W$181,$A$2:$A$181,">"&A5,$A$2:$A$181,"<="&EDATE(A5,12))+IF(AND(DATE(2033,12,1)>A5,DATE(2033,12,1)<=EDATE(A5,12)),'Funding & Cap'!$B$200,0)) -> 0 | AE5: ='Funding & Cap'!Q64 -> 0 | AF5: =AF4+AG5+U5 -> 5299725 | AG5: =SUM(E5:G5)-SUM(H5:S5)+P5+Q5-(X5-X4)-(Y5-Y4)-(Z5-Z4)+(AA5-AA4)+(AB5-AB4)+(AC5-AC4)-T5+V5-W5 -> -168939 | AH5: ='Revenue & Demand'!P169 -> 0 | AI5: ='Revenue & Demand'!Q169 -> 0 | AJ5: ='Manufacturing & Production'!J209 -> 0
A6: 43221 | B6: =YEAR(A6) -> 2018 | C6: ='Revenue & Demand'!C170 -> 0 | D6: ='Revenue & Demand'!F170 -> 0 | E6: ='Revenue & Demand'!E170 -> 0 | F6: ='Revenue & Demand'!H170 -> 0 | G6: ='Revenue & Demand'!J170 -> 0 | H6: ='Manufacturing & Production'!F210 -> 0 | I6: ='Manufacturing & Production'!G210 -> 0 | J6: ='Workforce & Expenses'!M262 -> 0 | K6: ='Manufacturing & Production'!K210 -> 0 | L6: ='Clinical Trials & R&D'!F210 -> 94233 | M6: ='Clinical Trials & R&D'!I210 -> 0 | N6: ='Workforce & Expenses'!P262 -> 7051 | O6: ='Workforce & Expenses'!S262 -> 50454 | P6: ='Funding & Cap'!F65 -> 3245 | Q6: ='Working Capital & Assets'!B9 -> 2500 | R6: ='Funding & Cap'!H65 -> 0 | S6: ='Working Capital & Assets'!C9 -> 0 | T6: ='Working Capital & Assets'!D9 -> 23279 | U6: ='Funding & Cap'!B65 -> 0 | V6: ='Funding & Cap'!C65 -> 0 | W6: ='Funding & Cap'!D65 -> 0 | X6: ='Working Capital & Assets'!E9 -> 0 | Y6: ='Working Capital & Assets'!F9 -> 0 | Z6: ='Working Capital & Assets'!G9 -> 0 | AA6: ='Working Capital & Assets'!H9 -> 4023 | AB6: ='Working Capital & Assets'!I9 -> 39374 | AC6: ='Working Capital & Assets'!J9 -> 0 | AD6: =MIN(AE6,SUMIFS($W$2:$W$181,$A$2:$A$181,">"&A6,$A$2:$A$181,"<="&EDATE(A6,12))+IF(AND(DATE(2033,12,1)>A6,DATE(2033,12,1)<=EDATE(A6,12)),'Funding & Cap'!$B$200,0)) -> 0 | AE6: ='Funding & Cap'!Q65 -> 0 | AF6: =AF5+AG6+U6 -> 5132532 | AG6: =SUM(E6:G6)-SUM(H6:S6)+P6+Q6-(X6-X5)-(Y6-Y5)-(Z6-Z5)+(AA6-AA5)+(AB6-AB5)+(AC6-AC5)-T6+V6-W6 -> -167193 | AH6: ='Revenue & Demand'!P170 -> 0 | AI6: ='Revenue & Demand'!Q170 -> 0 | AJ6: ='Manufacturing & Production'!J210 -> 0
A7: 43252 | B7: =YEAR(A7) -> 2018 | C7: ='Revenue & Demand'!C171 -> 0 | D7: ='Revenue & Demand'!F171 -> 0 | E7: ='Revenue & Demand'!E171 -> 0 | F7: ='Revenue & Demand'!H171 -> 0 | G7: ='Revenue & Demand'!J171 -> 0 | H7: ='Manufacturing & Production'!F211 -> 0 | I7: ='Manufacturing & Production'!G211 -> 0 | J7: ='Workforce & Expenses'!M263 -> 0 | K7: ='Manufacturing & Production'!K211 -> 0 | L7: ='Clinical Trials & R&D'!F211 -> 91299 | M7: ='Clinical Trials & R&D'!I211 -> 0 | N7: ='Workforce & Expenses'!P263 -> 7906 | O7: ='Workforce & Expenses'!S263 -> 49833 | P7: ='Funding & Cap'!F66 -> 3304 | Q7: ='Working Capital & Assets'!B10 -> 2500 | R7: ='Funding & Cap'!H66 -> 0 | S7: ='Working Capital & Assets'!C10 -> 0 | T7: ='Working Capital & Assets'!D10 -> 23552 | U7: ='Funding & Cap'!B66 -> 0 | V7: ='Funding & Cap'!C66 -> 0 | W7: ='Funding & Cap'!D66 -> 0 | X7: ='Working Capital & Assets'!E10 -> 0 | Y7: ='Working Capital & Assets'!F10 -> 0 | Z7: ='Working Capital & Assets'!G10 -> 0 | AA7: ='Working Capital & Assets'!H10 -> 4726 | AB7: ='Working Capital & Assets'!I10 -> 46250 | AC7: ='Working Capital & Assets'!J10 -> 0 | AD7: =MIN(AE7,SUMIFS($W$2:$W$181,$A$2:$A$181,">"&A7,$A$2:$A$181,"<="&EDATE(A7,12))+IF(AND(DATE(2033,12,1)>A7,DATE(2033,12,1)<=EDATE(A7,12)),'Funding & Cap'!$B$200,0)) -> 0 | AE7: ='Funding & Cap'!Q66 -> 0 | AF7: =AF6+AG7+U7 -> 4967521 | AG7: =SUM(E7:G7)-SUM(H7:S7)+P7+Q7-(X7-X6)-(Y7-Y6)-(Z7-Z6)+(AA7-AA6)+(AB7-AB6)+(AC7-AC6)-T7+V7-W7 -> -165011 | AH7: ='Revenue & Demand'!P171 -> 0 | AI7: ='Revenue & Demand'!Q171 -> 0 | AJ7: ='Manufacturing & Production'!J211 -> 0
A8: 43282 | B8: =YEAR(A8) -> 2018 | C8: ='Revenue & Demand'!C172 -> 0 | D8: ='Revenue & Demand'!F172 -> 0 | E8: ='Revenue & Demand'!E172 -> 0 | F8: ='Revenue & Demand'!H172 -> 0 | G8: ='Revenue & Demand'!J172 -> 0 | H8: ='Manufacturing & Production'!F212 -> 0 | I8: ='Manufacturing & Production'!G212 -> 0 | J8: ='Workforce & Expenses'!M264 -> 0 | K8: ='Manufacturing & Production'!K212 -> 0 | L8: ='Clinical Trials & R&D'!F212 -> 89438 | M8: ='Clinical Trials & R&D'!I212 -> 0 | N8: ='Workforce & Expenses'!P264 -> 8761 | O8: ='Workforce & Expenses'!S264 -> 49211 | P8: ='Funding & Cap'!F67 -> 3363 | Q8: ='Working Capital & Assets'!B11 -> 2500 | R8: ='Funding & Cap'!H67 -> 0 | S8: ='Working Capital & Assets'!C11 -> 0 | T8: ='Working Capital & Assets'!D11 -> 23826 | U8: ='Funding & Cap'!B67 -> 0 | V8: ='Funding & Cap'!C67 -> 0 | W8: ='Funding & Cap'!D67 -> 0 | X8: ='Working Capital & Assets'!E11 -> 0 | Y8: ='Working Capital & Assets'!F11 -> 0 | Z8: ='Working Capital & Assets'!G11 -> 0 | AA8: ='Working Capital & Assets'!H11 -> 5429 | AB8: ='Working Capital & Assets'!I11 -> 53126 | AC8: ='Working Capital & Assets'!J11 -> 0 | AD8: =MIN(AE8,SUMIFS($W$2:$W$181,$A$2:$A$181,">"&A8,$A$2:$A$181,"<="&EDATE(A8,12))+IF(AND(DATE(2033,12,1)>A8,DATE(2033,12,1)<=EDATE(A8,12)),'Funding & Cap'!$B$200,0)) -> 0 | AE8: ='Funding & Cap'!Q67 -> 0 | AF8: =AF7+AG8+U8 -> 4803864 | AG8: =SUM(E8:G8)-SUM(H8:S8)+P8+Q8-(X8-X7)-(Y8-Y7)-(Z8-Z7)+(AA8-AA7)+(AB8-AB7)+(AC8-AC7)-T8+V8-W8 -> -163657 | AH8: ='Revenue & Demand'!P172 -> 0 | AI8: ='Revenue & Demand'!Q172 -> 0 | AJ8: ='Manufacturing & Production'!J212 -> 0
A9: 43313 | B9: =YEAR(A9) -> 2018 | C9: ='Revenue & Demand'!C173 -> 0 | D9: ='Revenue & Demand'!F173 -> 0 | E9: ='Revenue & Demand'!E173 -> 0 | F9: ='Revenue & Demand'!H173 -> 0 | G9: ='Revenue & Demand'!J173 -> 0 | H9: ='Manufacturing & Production'!F213 -> 0 | I9: ='Manufacturing & Production'!G213 -> 0 | J9: ='Workforce & Expenses'!M265 -> 0 | K9: ='Manufacturing & Production'!K213 -> 0 | L9: ='Clinical Trials & R&D'!F213 -> 89433 | M9: ='Clinical Trials & R&D'!I213 -> 0 | N9: ='Workforce & Expenses'!P265 -> 9615 | O9: ='Workforce & Expenses'!S265 -> 48845 | P9: ='Funding & Cap'!F68 -> 3422 | Q9: ='Working Capital & Assets'!B12 -> 2500 | R9: ='Funding & Cap'!H68 -> 0 | S9: ='Working Capital & Assets'!C12 -> 0 | T9: ='Working Capital & Assets'!D12 -> 24100 | U9: ='Funding & Cap'!B68 -> 0 | V9: ='Funding & Cap'!C68 -> 0 | W9: ='Funding & Cap'!D68 -> 0 | X9: ='Working Capital & Assets'!E12 -> 0 | Y9: ='Working Capital & Assets'!F12 -> 0 | Z9: ='Working Capital & Assets'!G12 -> 0 | AA9: ='Working Capital & Assets'!H12 -> 6154 | AB9: ='Working Capital & Assets'!I12 -> 60225 | AC9: ='Working Capital & Assets'!J12 -> 0 | AD9: =MIN(AE9,SUMIFS($W$2:$W$181,$A$2:$A$181,">"&A9,$A$2:$A$181,"<="&EDATE(A9,12))+IF(AND(DATE(2033,12,1)>A9,DATE(2033,12,1)<=EDATE(A9,12)),'Funding & Cap'!$B$200,0)) -> 0 | AE9: ='Funding & Cap'!Q68 -> 0 | AF9: =AF8+AG9+U9 -> 4639695 | AG9: =SUM(E9:G9)-SUM(H9:S9)+P9+Q9-(X9-X8)-(Y9-Y8)-(Z9-Z8)+(AA9-AA8)+(AB9-AB8)+(AC9-AC8)-T9+V9-W9 -> -164169 | AH9: ='Revenue & Demand'!P173 -> 0 | AI9: ='Revenue & Demand'!Q173 -> 0 | AJ9: ='Manufacturing & Production'!J213 -> 0
A10: 43344 | B10: =YEAR(A10) -> 2018 | C10: ='Revenue & Demand'!C174 -> 0 | D10: ='Revenue & Demand'!F174 -> 0 | E10: ='Revenue & Demand'!E174 -> 0 | F10: ='Revenue & Demand'!H174 -> 0 | G10: ='Revenue & Demand'!J174 -> 0 | H10: ='Manufacturing & Production'!F214 -> 0 | I10: ='Manufacturing & Production'!G214 -> 0 | J10: ='Workforce & Expenses'!M266 -> 0 | K10: ='Manufacturing & Production'!K214 -> 0 | L10: ='Clinical Trials & R&D'!F214 -> 91572 | M10: ='Clinical Trials & R&D'!I214 -> 0 | N10: ='Workforce & Expenses'!P266 -> 10470 | O10: ='Workforce & Expenses'!S266 -> 48924 | P10: ='Funding & Cap'!F69 -> 3481 | Q10: ='Working Capital & Assets'!B13 -> 2500 | R10: ='Funding & Cap'!H69 -> 0 | S10: ='Working Capital & Assets'!C13 -> 0 | T10: ='Working Capital & Assets'!D13 -> 57238 | U10: ='Funding & Cap'!B69 -> 0 | V10: ='Funding & Cap'!C69 -> 0 | W10: ='Funding & Cap'!D69 -> 0 | X10: ='Working Capital & Assets'!E13 -> 0 | Y10: ='Working Capital & Assets'!F13 -> 0 | Z10: ='Working Capital & Assets'!G13 -> 0 | AA10: ='Working Capital & Assets'!H13 -> 6919 | AB10: ='Working Capital & Assets'!I13 -> 67710 | AC10: ='Working Capital & Assets'!J13 -> 0 | AD10: =MIN(AE10,SUMIFS($W$2:$W$181,$A$2:$A$181,">"&A10,$A$2:$A$181,"<="&EDATE(A10,12))+IF(AND(DATE(2033,12,1)>A10,DATE(2033,12,1)<=EDATE(A10,12)),'Funding & Cap'!$B$200,0)) -> 0 | AE10: ='Funding & Cap'!Q69 -> 0 | AF10: =AF9+AG10+U10 -> 4439741 | AG10: =SUM(E10:G10)-SUM(H10:S10)+P10+Q10-(X10-X9)-(Y10-Y9)-(Z10-Z9)+(AA10-AA9)+(AB10-AB9)+(AC10-AC9)-T10+V10-W10 -> -199954 | AH10: ='Revenue & Demand'!P174 -> 0 | AI10: ='Revenue & Demand'!Q174 -> 0 | AJ10: ='Manufacturing & Production'!J214 -> 0
A11: 43374 | B11: =YEAR(A11) -> 2018 | C11: ='Revenue & Demand'!C175 -> 0 | D11: ='Revenue & Demand'!F175 -> 0 | E11: ='Revenue & Demand'!E175 -> 0 | F11: ='Revenue & Demand'!H175 -> 0 | G11: ='Revenue & Demand'!J175 -> 0 | H11: ='Manufacturing & Production'!F215 -> 0 | I11: ='Manufacturing & Production'!G215 -> 0 | J11: ='Workforce & Expenses'!M267 -> 0 | K11: ='Manufacturing & Production'!K215 -> 0 | L11: ='Clinical Trials & R&D'!F215 -> 95567 | M11: ='Clinical Trials & R&D'!I215 -> 0 | N11: ='Workforce & Expenses'!P267 -> 11325 | O11: ='Workforce & Expenses'!S267 -> 49515 | P11: ='Funding & Cap'!F70 -> 3540 | Q11: ='Working Capital & Assets'!B14 -> 2500 | R11: ='Funding & Cap'!H70 -> 0 | S11: ='Working Capital & Assets'!C14 -> 0 | T11: ='Working Capital & Assets'!D14 -> 24648 | U11: ='Funding & Cap'!B70 -> 0 | V11: ='Funding & Cap'!C70 -> 0 | W11: ='Funding & Cap'!D70 -> 0 | X11: ='Working Capital & Assets'!E14 -> 0 | Y11: ='Working Capital & Assets'!F14 -> 0 | Z11: ='Working Capital & Assets'!G14 -> 0 | AA11: ='Working Capital & Assets'!H14 -> 7729 | AB11: ='Working Capital & Assets'!I14 -> 75641 | AC11: ='Working Capital & Assets'!J14 -> 0 | AD11: =MIN(AE11,SUMIFS($W$2:$W$181,$A$2:$A$181,">"&A11,$A$2:$A$181,"<="&EDATE(A11,12))+IF(AND(DATE(2033,12,1)>A11,DATE(2033,12,1)<=EDATE(A11,12)),'Funding & Cap'!$B$200,0)) -> 0 | AE11: ='Funding & Cap'!Q70 -> 0 | AF11: =AF10+AG11+U11 -> 4267427 | AG11: =SUM(E11:G11)-SUM(H11:S11)+P11+Q11-(X11-X10)-(Y11-Y10)-(Z11-Z10)+(AA11-AA10)+(AB11-AB10)+(AC11-AC10)-T11+V11-W11 -> -172314 | AH11: ='Revenue & Demand'!P175 -> 0 | AI11: ='Revenue & Demand'!Q175 -> 0 | AJ11: ='Manufacturing & Production'!J215 -> 0
A12: 43405 | B12: =YEAR(A12) -> 2018 | C12: ='Revenue & Demand'!C176 -> 0 | D12: ='Revenue & Demand'!F176 -> 0 | E12: ='Revenue & Demand'!E176 -> 0 | F12: ='Revenue & Demand'!H176 -> 0 | G12: ='Revenue & Demand'!J176 -> 0 | H12: ='Manufacturing & Production'!F216 -> 0 | I12: ='Manufacturing & Production'!G216 -> 0 | J12: ='Workforce & Expenses'!M268 -> 0 | K12: ='Manufacturing & Production'!K216 -> 0 | L12: ='Clinical Trials & R&D'!F216 -> 100634 | M12: ='Clinical Trials & R&D'!I216 -> 0 | N12: ='Workforce & Expenses'!P268 -> 12179 | O12: ='Workforce & Expenses'!S268 -> 50550 | P12: ='Funding & Cap'!F71 -> 3599 | Q12: ='Working Capital & Assets'!B15 -> 2500 | R12: ='Funding & Cap'!H71 -> 0 | S12: ='Working Capital & Assets'!C15 -> 0 | T12: ='Working Capital & Assets'!D15 -> 24922 | U12: ='Funding & Cap'!B71 -> 0 | V12: ='Funding & Cap'!C71 -> 0 | W12: ='Funding & Cap'!D71 -> 0 | X12: ='Working Capital & Assets'!E15 -> 0 | Y12: ='Working Capital & Assets'!F15 -> 0 | Z12: ='Working Capital & Assets'!G15 -> 0 | AA12: ='Working Capital & Assets'!H15 -> 8579 | AB12: ='Working Capital & Assets'!I15 -> 83959 | AC12: ='Working Capital & Assets'!J15 -> 0 | AD12: =MIN(AE12,SUMIFS($W$2:$W$181,$A$2:$A$181,">"&A12,$A$2:$A$181,"<="&EDATE(A12,12))+IF(AND(DATE(2033,12,1)>A12,DATE(2033,12,1)<=EDATE(A12,12)),'Funding & Cap'!$B$200,0)) -> 0 | AE12: ='Funding & Cap'!Q71 -> 0 | AF12: =AF11+AG12+U12 -> 4088310 | AG12: =SUM(E12:G12)-SUM(H12:S12)+P12+Q12-(X12-X11)-(Y12-Y11)-(Z12-Z11)+(AA12-AA11)+(AB12-AB11)+(AC12-AC11)-T12+V12-W12 -> -179117 | AH12: ='Revenue & Demand'!P176 -> 0 | AI12: ='Revenue & Demand'!Q176 -> 0 | AJ12: ='Manufacturing & Production'!J216 -> 0
A13: 43435 | B13: =YEAR(A13) -> 2018 | C13: ='Revenue & Demand'!C177 -> 0 | D13: ='Revenue & Demand'!F177 -> 0 | E13: ='Revenue & Demand'!E177 -> 0 | F13: ='Revenue & Demand'!H177 -> 0 | G13: ='Revenue & Demand'!J177 -> 0 | H13: ='Manufacturing & Production'!F217 -> 0 | I13: ='Manufacturing & Production'!G217 -> 0 | J13: ='Workforce & Expenses'!M269 -> 0 | K13: ='Manufacturing & Production'!K217 -> 0 | L13: ='Clinical Trials & R&D'!F217 -> 105700 | M13: ='Clinical Trials & R&D'!I217 -> 0 | N13: ='Workforce & Expenses'!P269 -> 13035 | O13: ='Workforce & Expenses'!S269 -> 51842 | P13: ='Funding & Cap'!F72 -> 3656 | Q13: ='Working Capital & Assets'!B16 -> 2500 | R13: ='Funding & Cap'!H72 -> 0 | S13: ='Working Capital & Assets'!C16 -> 0 | T13: ='Working Capital & Assets'!D16 -> 25195 | U13: ='Funding & Cap'!B72 -> 0 | V13: ='Funding & Cap'!C72 -> 0 | W13: ='Funding & Cap'!D72 -> 0 | X13: ='Working Capital & Assets'!E16 -> 0 | Y13: ='Working Capital & Assets'!F16 -> 0 | Z13: ='Working Capital & Assets'!G16 -> 0 | AA13: ='Working Capital & Assets'!H16 -> 9452 | AB13: ='Working Capital & Assets'!I16 -> 92500 | AC13: ='Working Capital & Assets'!J16 -> 0 | AD13: =MIN(AE13,SUMIFS($W$2:$W$181,$A$2:$A$181,">"&A13,$A$2:$A$181,"<="&EDATE(A13,12))+IF(AND(DATE(2033,12,1)>A13,DATE(2033,12,1)<=EDATE(A13,12)),'Funding & Cap'!$B$200,0)) -> 0 | AE13: ='Funding & Cap'!Q72 -> 0 | AF13: =AF12+AG13+U13 -> 3901952 | AG13: =SUM(E13:G13)-SUM(H13:S13)+P13+Q13-(X13-X12)-(Y13-Y12)-(Z13-Z12)+(AA13-AA12)+(AB13-AB12)+(AC13-AC12)-T13+V13-W13 -> -186358 | AH13: ='Revenue & Demand'!P177 -> 0 | AI13: ='Revenue & Demand'!Q177 -> 0 | AJ13: ='Manufacturing & Production'!J217 -> 0
A14: 43466 | B14: =YEAR(A14) -> 2019 | C14: ='Revenue & Demand'!C178 -> 0 | D14: ='Revenue & Demand'!F178 -> 0 | E14: ='Revenue & Demand'!E178 -> 0 | F14: ='Revenue & Demand'!H178 -> 25277 | G14: ='Revenue & Demand'!J178 -> 2941 | H14: ='Manufacturing & Production'!F218 -> 0 | I14: ='Manufacturing & Production'!G218 -> 0 | J14: ='Workforce & Expenses'!M270 -> 10111 | K14: ='Manufacturing & Production'!K218 -> 294 | L14: ='Clinical Trials & R&D'!F218 -> 139023 | M14: ='Clinical Trials & R&D'!I218 -> 0 | N14: ='Workforce & Expenses'!P270 -> 7326 | O14: ='Workforce & Expenses'!S270 -> 69580 | P14: ='Funding & Cap'!F73 -> 7522 | Q14: ='Working Capital & Assets'!B17 -> 10000 | R14: ='Funding & Cap'!H73 -> 0 | S14: ='Working Capital & Assets'!C17 -> 0 | T14: ='Working Capital & Assets'!D17 -> 47535 | U14: ='Funding & Cap'!B73 -> 0 | V14: ='Funding & Cap'!C73 -> 0 | W14: ='Funding & Cap'!D73 -> 0 | X14: ='Working Capital & Assets'!E17 -> 4047 | Y14: ='Working Capital & Assets'!F17 -> 0 | Z14: ='Working Capital & Assets'!G17 -> 1847 | AA14: ='Working Capital & Assets'!H17 -> 12007 | AB14: ='Working Capital & Assets'!I17 -> 99750 | AC14: ='Working Capital & Assets'!J17 -> 3693 | AD14: =MIN(AE14,SUMIFS($W$2:$W$181,$A$2:$A$181,">"&A14,$A$2:$A$181,"<="&EDATE(A14,12))+IF(AND(DATE(2033,12,1)>A14,DATE(2033,12,1)<=EDATE(A14,12)),'Funding & Cap'!$B$200,0)) -> 0 | AE14: ='Funding & Cap'!Q73 -> 0 | AF14: =AF13+AG14+U14 -> 3663905 | AG14: =SUM(E14:G14)-SUM(H14:S14)+P14+Q14-(X14-X13)-(Y14-Y13)-(Z14-Z13)+(AA14-AA13)+(AB14-AB13)+(AC14-AC13)-T14+V14-W14 -> -238047 | AH14: ='Revenue & Demand'!P178 -> 0 | AI14: ='Revenue & Demand'!Q178 -> 0 | AJ14: ='Manufacturing & Production'!J218 -> 0
A15: 43497 | B15: =YEAR(A15) -> 2019 | C15: ='Revenue & Demand'!C179 -> 0 | D15: ='Revenue & Demand'!F179 -> 0 | E15: ='Revenue & Demand'!E179 -> 0 | F15: ='Revenue & Demand'!H179 -> 25835 | G15: ='Revenue & Demand'!J179 -> 2941 | H15: ='Manufacturing & Production'!F219 -> 0 | I15: ='Manufacturing & Production'!G219 -> 0 | J15: ='Workforce & Expenses'!M271 -> 10334 | K15: ='Manufacturing & Production'!K219 -> 294 | L15: ='Clinical Trials & R&D'!F219 -> 142092 | M15: ='Clinical Trials & R&D'!I219 -> 0 | N15: ='Workforce & Expenses'!P271 -> 9027 | O15: ='Workforce & Expenses'!S271 -> 71046 | P15: ='Funding & Cap'!F74 -> 7670 | Q15: ='Working Capital & Assets'!B18 -> 10000 | R15: ='Funding & Cap'!H74 -> 0 | S15: ='Working Capital & Assets'!C18 -> 0 | T15: ='Working Capital & Assets'!D18 -> 48122 | U15: ='Funding & Cap'!B74 -> 0 | V15: ='Funding & Cap'!C74 -> 0 | W15: ='Funding & Cap'!D74 -> 0 | X15: ='Working Capital & Assets'!E18 -> 7989 | Y15: ='Working Capital & Assets'!F18 -> 0 | Z15: ='Working Capital & Assets'!G18 -> 3645 | AA15: ='Working Capital & Assets'!H18 -> 14474 | AB15: ='Working Capital & Assets'!I18 -> 106609 | AC15: ='Working Capital & Assets'!J18 -> 7290 | AD15: =MIN(AE15,SUMIFS($W$2:$W$181,$A$2:$A$181,">"&A15,$A$2:$A$181,"<="&EDATE(A15,12))+IF(AND(DATE(2033,12,1)>A15,DATE(2033,12,1)<=EDATE(A15,12)),'Funding & Cap'!$B$200,0)) -> 0 | AE15: ='Funding & Cap'!Q74 -> 0 | AF15: =AF14+AG15+U15 -> 3418949 | AG15: =SUM(E15:G15)-SUM(H15:S15)+P15+Q15-(X15-X14)-(Y15-Y14)-(Z15-Z14)+(AA15-AA14)+(AB15-AB14)+(AC15-AC14)-T15+V15-W15 -> -244956 | AH15: ='Revenue & Demand'!P179 -> 0 | AI15: ='Revenue & Demand'!Q179 -> 0 | AJ15: ='Manufacturing & Production'!J219 -> 0
A16: 43525 | B16: =YEAR(A16) -> 2019 | C16: ='Revenue & Demand'!C180 -> 0 | D16: ='Revenue & Demand'!F180 -> 0 | E16: ='Revenue & Demand'!E180 -> 0 | F16: ='Revenue & Demand'!H180 -> 25833 | G16: ='Revenue & Demand'!J180 -> 18382 | H16: ='Manufacturing & Production'!F220 -> 0 | I16: ='Manufacturing & Production'!G220 -> 0 | J16: ='Workforce & Expenses'!M272 -> 10333 | K16: ='Manufacturing & Production'!K220 -> 1838 | L16: ='Clinical Trials & R&D'!F220 -> 142084 | M16: ='Clinical Trials & R&D'!I220 -> 0 | N16: ='Workforce & Expenses'!P272 -> 10725 | O16: ='Workforce & Expenses'!S272 -> 71883 | P16: ='Funding & Cap'!F75 -> 7817 | Q16: ='Working Capital & Assets'!B19 -> 10000 | R16: ='Funding & Cap'!H75 -> 0 | S16: ='Working Capital & Assets'!C19 -> 0 | T16: ='Working Capital & Assets'!D19 -> 119131 | U16: ='Funding & Cap'!B75 -> 0 | V16: ='Funding & Cap'!C75 -> 0 | W16: ='Funding & Cap'!D75 -> 0 | X16: ='Working Capital & Assets'!E19 -> 11748 | Y16: ='Working Capital & Assets'!F19 -> 0 | Z16: ='Working Capital & Assets'!G19 -> 5360 | AA16: ='Working Capital & Assets'!H19 -> 16790 | AB16: ='Working Capital & Assets'!I19 -> 112791 | AC16: ='Working Capital & Assets'!J19 -> 10720 | AD16: =MIN(AE16,SUMIFS($W$2:$W$181,$A$2:$A$181,">"&A16,$A$2:$A$181,"<="&EDATE(A16,12))+IF(AND(DATE(2033,12,1)>A16,DATE(2033,12,1)<=EDATE(A16,12)),'Funding & Cap'!$B$200,0)) -> 0 | AE16: ='Funding & Cap'!Q75 -> 0 | AF16: =AF15+AG16+U16 -> 3113624 | AG16: =SUM(E16:G16)-SUM(H16:S16)+P16+Q16-(X16-X15)-(Y16-Y15)-(Z16-Z15)+(AA16-AA15)+(AB16-AB15)+(AC16-AC15)-T16+V16-W16 -> -305325 | AH16: ='Revenue & Demand'!P180 -> 0 | AI16: ='Revenue & Demand'!Q180 -> 0 | AJ16: ='Manufacturing & Production'!J220 -> 0
... A72: 45231 | B72: =YEAR(A72) -> 2023 | C72: ='Revenue & Demand'!C236 -> 0 | D72: ='Revenue & Demand'!F236 -> 23 | E72: ='Revenue & Demand'!E236 -> 0 | F72: ='Revenue & Demand'!H236 -> 962585 | G72: ='Revenue & Demand'!J236 -> 176471 | H72: ='Manufacturing & Production'!F276 -> 0 | I72: ='Manufacturing & Production'!G276 -> 0 | J72: ='Workforce & Expenses'!M328 -> 433163 | K72: ='Manufacturing & Production'!K276 -> 14118 | L72: ='Clinical Trials & R&D'!F276 -> 1443878 | M72: ='Clinical Trials & R&D'!I276 -> 481292 | N72: ='Workforce & Expenses'!P328 -> 1037427 | O72: ='Workforce & Expenses'!S328 -> 1011000 | P72: ='Funding & Cap'!F131 -> 179941 | Q72: ='Working Capital & Assets'!B75 -> 250000 | R72: ='Funding & Cap'!H131 -> 354712 | S72: ='Working Capital & Assets'!C75 -> 0 | T72: ='Working Capital & Assets'!D75 -> 427230 | U72: ='Funding & Cap'!B131 -> 0 | V72: ='Funding & Cap'!C131 -> 0 | W72: ='Funding & Cap'!D131 -> 0 | X72: ='Working Capital & Assets'!E75 -> 2090838 | Y72: ='Working Capital & Assets'!F75 -> 0 | Z72: ='Working Capital & Assets'!G75 -> 955820 | AA72: ='Working Capital & Assets'!H75 -> 1285269 | AB72: ='Working Capital & Assets'!I75 -> 4086300 | AC72: ='Working Capital & Assets'!J75 -> 3504673 | AD72: =MIN(AE72,SUMIFS($W$2:$W$181,$A$2:$A$181,">"&A72,$A$2:$A$181,"<="&EDATE(A72,12))+IF(AND(DATE(2033,12,1)>A72,DATE(2033,12,1)<=EDATE(A72,12)),'Funding & Cap'!$B$200,0)) -> 5000000 | AE72: ='Funding & Cap'!Q131 -> 62000000 | AF72: =AF71+AG72+U72 -> 80082268 | AG72: =SUM(E72:G72)-SUM(H72:S72)+P72+Q72-(X72-X71)-(Y72-Y71)-(Z72-Z71)+(AA72-AA71)+(AB72-AB71)+(AC72-AC71)-T72+V72-W72 -> -3776218 | AH72: ='Revenue & Demand'!P236 -> 0 | AI72: ='Revenue & Demand'!Q236 -> 0 | AJ72: ='Manufacturing & Production'!J276 -> 0
A73: 45261 | B73: =YEAR(A73) -> 2023 | C73: ='Revenue & Demand'!C237 -> 0 | D73: ='Revenue & Demand'!F237 -> 24 | E73: ='Revenue & Demand'!E237 -> 0 | F73: ='Revenue & Demand'!H237 -> 1011054 | G73: ='Revenue & Demand'!J237 -> 1279409 | H73: ='Manufacturing & Production'!F277 -> 0 | I73: ='Manufacturing & Production'!G277 -> 0 | J73: ='Workforce & Expenses'!M329 -> 454973 | K73: ='Manufacturing & Production'!K277 -> 102351 | L73: ='Clinical Trials & R&D'!F277 -> 1516582 | M73: ='Clinical Trials & R&D'!I277 -> 505527 | N73: ='Workforce & Expenses'!P329 -> 1107257 | O73: ='Workforce & Expenses'!S329 -> 1036825 | P73: ='Funding & Cap'!F132 -> 182892 | Q73: ='Working Capital & Assets'!B76 -> 250000 | R73: ='Funding & Cap'!H132 -> 354709 | S73: ='Working Capital & Assets'!C76 -> 0 | T73: ='Working Capital & Assets'!D76 -> 431923 | U73: ='Funding & Cap'!B132 -> 0 | V73: ='Funding & Cap'!C132 -> 0 | W73: ='Funding & Cap'!D132 -> 0 | X73: ='Working Capital & Assets'!E76 -> 2235616 | Y73: ='Working Capital & Assets'!F76 -> 0 | Z73: ='Working Capital & Assets'!G76 -> 1020000 | AA73: ='Working Capital & Assets'!H76 -> 1347534 | AB73: ='Working Capital & Assets'!I76 -> 4300000 | AC73: ='Working Capital & Assets'!J76 -> 3740000 | AD73: =MIN(AE73,SUMIFS($W$2:$W$181,$A$2:$A$181,">"&A73,$A$2:$A$181,"<="&EDATE(A73,12))+IF(AND(DATE(2033,12,1)>A73,DATE(2033,12,1)<=EDATE(A73,12)),'Funding & Cap'!$B$200,0)) -> 5000000 | AE73: ='Funding & Cap'!Q132 -> 62000000 | AF73: =AF72+AG73+U73 -> 77164918 | AG73: =SUM(E73:G73)-SUM(H73:S73)+P73+Q73-(X73-X72)-(Y73-Y72)-(Z73-Z72)+(AA73-AA72)+(AB73-AB72)+(AC73-AC72)-T73+V73-W73 -> -2917350 | AH73: ='Revenue & Demand'!P237 -> 0 | AI73: ='Revenue & Demand'!Q237 -> 0 | AJ73: ='Manufacturing & Production'!J277 -> 0 | AK73: Month | AL73: Historical fills | AM73: Projected fills
A74: 45292 | B74: =YEAR(A74) -> 2024 | C74: ='Revenue & Demand'!C238 -> 510 | D74: ='Revenue & Demand'!F238 -> 25 | E74: ='Revenue & Demand'!E238 -> 815476 | F74: ='Revenue & Demand'!H238 -> 1685127 | G74: ='Revenue & Demand'!J238 -> 205882 | H74: ='Manufacturing & Production'!F278 -> 187560 | I74: ='Manufacturing & Production'!G278 -> 65238 | J74: ='Workforce & Expenses'!M330 -> 758307 | K74: ='Manufacturing & Production'!K278 -> 16471 | L74: ='Clinical Trials & R&D'!F278 -> 2595095 | M74: ='Clinical Trials & R&D'!I278 -> 1112184 | N74: ='Workforce & Expenses'!P330 -> 842774 | O74: ='Workforce & Expenses'!S330 -> 1555316 | P74: ='Funding & Cap'!F133 -> 300885 | Q74: ='Working Capital & Assets'!B77 -> 416667 | R74: ='Funding & Cap'!H133 -> 433101 | S74: ='Working Capital & Assets'!C77 -> 0 | T74: ='Working Capital & Assets'!D77 -> 760563 | U74: ='Funding & Cap'!B133 -> 0 | V74: ='Funding & Cap'!C133 -> 0 | W74: ='Funding & Cap'!D133 -> 0 | X74: ='Working Capital & Assets'!E77 -> 2693878 | Y74: ='Working Capital & Assets'!F77 -> 239291 | Z74: ='Working Capital & Assets'!G77 -> 1206460 | AA74: ='Working Capital & Assets'!H77 -> 1560774 | AB74: ='Working Capital & Assets'!I77 -> 4726962 | AC74: ='Working Capital & Assets'!J77 -> 3976793 | AD74: =MIN(AE74,SUMIFS($W$2:$W$181,$A$2:$A$181,">"&A74,$A$2:$A$181,"<="&EDATE(A74,12))+IF(AND(DATE(2033,12,1)>A74,DATE(2033,12,1)<=EDATE(A74,12)),'Funding & Cap'!$B$200,0)) -> 5000000 | AE74: ='Funding & Cap'!Q133 -> 62000000 | AF74: =AF73+AG74+U74 -> 71537776 | AG74: =SUM(E74:G74)-SUM(H74:S74)+P74+Q74-(X74-X73)-(Y74-Y73)-(Z74-Z73)+(AA74-AA73)+(AB74-AB73)+(AC74-AC73)-T74+V74-W74 -> -5627142 | AH74: ='Revenue & Demand'!P238 -> 0 | AI74: ='Revenue & Demand'!Q238 -> 0 | AJ74: ='Manufacturing & Production'!J278 -> 0 | AK74: =A74 -> 45292 | AL74: =IF(B74<=2025,C74,"") -> 510 | AM74: =IF(OR(B74>=2026,AND(B74=2025,MONTH(A74)=12)),C74,"")
A75: 45323 | B75: =YEAR(A75) -> 2024 | C75: ='Revenue & Demand'!C239 -> 597 | D75: ='Revenue & Demand'!F239 -> 26 | E75: ='Revenue & Demand'!E239 -> 955660 | F75: ='Revenue & Demand'!H239 -> 1722325 | G75: ='Revenue & Demand'!J239 -> 205882 | H75: ='Manufacturing & Production'!F279 -> 219802 | I75: ='Manufacturing & Production'!G279 -> 76453 | J75: ='Workforce & Expenses'!M331 -> 775046 | K75: ='Manufacturing & Production'!K279 -> 16471 | L75: ='Clinical Trials & R&D'!F279 -> 2652381 | M75: ='Clinical Trials & R&D'!I279 -> 1136735 | N75: ='Workforce & Expenses'!P331 -> 959701 | O75: ='Workforce & Expenses'!S331 -> 1588090 | P75: ='Funding & Cap'!F134 -> 306785 | Q75: ='Working Capital & Assets'!B78 -> 416667 | R75: ='Funding & Cap'!H134 -> 433101 | S75: ='Working Capital & Assets'!C78 -> 0 | T75: ='Working Capital & Assets'!D78 -> 769953 | U75: ='Funding & Cap'!B134 -> 0 | V75: ='Funding & Cap'!C134 -> 0 | W75: ='Funding & Cap'!D134 -> 0 | X75: ='Working Capital & Assets'!E78 -> 3135304 | Y75: ='Working Capital & Assets'!F78 -> 472332 | Z75: ='Working Capital & Assets'!G78 -> 1385830 | AA75: ='Working Capital & Assets'!H78 -> 1765512 | AB75: ='Working Capital & Assets'!I78 -> 5133413 | AC75: ='Working Capital & Assets'!J78 -> 4199262 | AD75: =MIN(AE75,SUMIFS($W$2:$W$181,$A$2:$A$181,">"&A75,$A$2:$A$181,"<="&EDATE(A75,12))+IF(AND(DATE(2033,12,1)>A75,DATE(2033,12,1)<=EDATE(A75,12)),'Funding & Cap'!$B$200,0)) -> 5000000 | AE75: ='Funding & Cap'!Q134 -> 62000000 | AF75: =AF74+AG75+U75 -> 65773731 | AG75: =SUM(E75:G75)-SUM(H75:S75)+P75+Q75-(X75-X74)-(Y75-Y74)-(Z75-Z74)+(AA75-AA74)+(AB75-AB74)+(AC75-AC74)-T75+V75-W75 -> -5764045 | AH75: ='Revenue & Demand'!P239 -> 0 | AI75: ='Revenue & Demand'!Q239 -> 0 | AJ75: ='Manufacturing & Production'!J279 -> 0 | AK75: =A75 -> 45323 | AL75: =IF(B75<=2025,C75,"") -> 597 | AM75: =IF(OR(B75>=2026,AND(B75=2025,MONTH(A75)=12)),C75,"")
A76: 45352 | B76: =YEAR(A76) -> 2024 | C76: ='Revenue & Demand'!C240 -> 691 | D76: ='Revenue & Demand'!F240 -> 27 | E76: ='Revenue & Demand'!E240 -> 1105320 | F76: ='Revenue & Demand'!H240 -> 1722233 | G76: ='Revenue & Demand'!J240 -> 1286765 | H76: ='Manufacturing & Production'!F280 -> 254223 | I76: ='Manufacturing & Production'!G280 -> 88426 | J76: ='Workforce & Expenses'!M332 -> 775005 | K76: ='Manufacturing & Production'!K280 -> 102941 | L76: ='Clinical Trials & R&D'!F280 -> 2652238 | M76: ='Clinical Trials & R&D'!I280 -> 1136674 | N76: ='Workforce & Expenses'!P332 -> 1071621 | O76: ='Workforce & Expenses'!S332 -> 1606807 | P76: ='Funding & Cap'!F135 -> 312684 | Q76: ='Working Capital & Assets'!B79 -> 416667 | R76: ='Funding & Cap'!H135 -> 433101 | S76: ='Working Capital & Assets'!C79 -> 0 | T76: ='Working Capital & Assets'!D79 -> 1906103 | U76: ='Funding & Cap'!B135 -> 110000000 | V76: ='Funding & Cap'!C135 -> 0 | W76: ='Funding & Cap'!D135 -> 0 | X76: ='Working Capital & Assets'!E79 -> 3547573 | Y76: ='Working Capital & Assets'!F79 -> 694549 | Z76: ='Working Capital & Assets'!G79 -> 1552920 | AA76: ='Working Capital & Assets'!H79 -> 1955523 | AB76: ='Working Capital & Assets'!I79 -> 5504340 | AC76: ='Working Capital & Assets'!J79 -> 4396920 | AD76: =MIN(AE76,SUMIFS($W$2:$W$181,$A$2:$A$181,">"&A76,$A$2:$A$181,"<="&EDATE(A76,12))+IF(AND(DATE(2033,12,1)>A76,DATE(2033,12,1)<=EDATE(A76,12)),'Funding & Cap'!$B$200,0)) -> 5000000 | AE76: ='Funding & Cap'!Q135 -> 62000000 | AF76: =AF75+AG76+U76 -> 169817930 | AG76: =SUM(E76:G76)-SUM(H76:S76)+P76+Q76-(X76-X75)-(Y76-Y75)-(Z76-Z75)+(AA76-AA75)+(AB76-AB75)+(AC76-AC75)-T76+V76-W76 -> -5955801 | AH76: ='Revenue & Demand'!P240 -> 0 | AI76: ='Revenue & Demand'!Q240 -> 0 | AJ76: ='Manufacturing & Production'!J280 -> 0 | AK76: =A76 -> 45352 | AL76: =IF(B76<=2025,C76,"") -> 691 | AM76: =IF(OR(B76>=2026,AND(B76=2025,MONTH(A76)=12)),C76,"")
A77: 45383 | B77: =YEAR(A77) -> 2024 | C77: ='Revenue & Demand'!C241 -> 790 | D77: ='Revenue & Demand'!F241 -> 28 | E77: ='Revenue & Demand'!E241 -> 1264495 | F77: ='Revenue & Demand'!H241 -> 1689858 | G77: ='Revenue & Demand'!J241 -> 205882 | H77: ='Manufacturing & Production'!F281 -> 290833 | I77: ='Manufacturing & Production'!G281 -> 101160 | J77: ='Workforce & Expenses'!M333 -> 760436 | K77: ='Manufacturing & Production'!K281 -> 16471 | L77: ='Clinical Trials & R&D'!F281 -> 2602381 | M77: ='Clinical Trials & R&D'!I281 -> 1115306 | N77: ='Workforce & Expenses'!P333 -> 1179512 | O77: ='Workforce & Expenses'!S333 -> 1609292 | P77: ='Funding & Cap'!F136 -> 318584 | Q77: ='Working Capital & Assets'!B80 -> 416667 | R77: ='Funding & Cap'!H136 -> 433101 | S77: ='Working Capital & Assets'!C80 -> 0 | T77: ='Working Capital & Assets'!D80 -> 788732 | U77: ='Funding & Cap'!B136 -> 0 | V77: ='Funding & Cap'!C136 -> 0 | W77: ='Funding & Cap'!D136 -> 0 | X77: ='Working Capital & Assets'!E80 -> 3926172 | Y77: ='Working Capital & Assets'!F80 -> 904266 | Z77: ='Working Capital & Assets'!G80 -> 1705830 | AA77: ='Working Capital & Assets'!H80 -> 2128530 | AB77: ='Working Capital & Assets'!I80 -> 5834246 | AC77: ='Working Capital & Assets'!J80 -> 4565929 | AD77: =MIN(AE77,SUMIFS($W$2:$W$181,$A$2:$A$181,">"&A77,$A$2:$A$181,"<="&EDATE(A77,12))+IF(AND(DATE(2033,12,1)>A77,DATE(2033,12,1)<=EDATE(A77,12)),'Funding & Cap'!$B$200,0)) -> 5000000 | AE77: ='Funding & Cap'!Q136 -> 62000000 | AF77: =AF76+AG77+U77 -> 164011637 | AG77: =SUM(E77:G77)-SUM(H77:S77)+P77+Q77-(X77-X76)-(Y77-Y76)-(Z77-Z76)+(AA77-AA76)+(AB77-AB76)+(AC77-AC76)-T77+V77-W77 -> -5806293 | AH77: ='Revenue & Demand'!P241 -> 0 | AI77: ='Revenue & Demand'!Q241 -> 0 | AJ77: ='Manufacturing & Production'!J281 -> 0 | AK77: =A77 -> 45383 | AL77: =IF(B77<=2025,C77,"") -> 790 | AM77: =IF(OR(B77>=2026,AND(B77=2025,MONTH(A77)=12)),C77,"")
A78: 45413 | B78: =YEAR(A78) -> 2024 | C78: ='Revenue & Demand'!C242 -> 896 | D78: ='Revenue & Demand'!F242 -> 29 | E78: ='Revenue & Demand'!E242 -> 1433164 | F78: ='Revenue & Demand'!H242 -> 1638837 | G78: ='Revenue & Demand'!J242 -> 205882 | H78: ='Manufacturing & Production'!F282 -> 329628 | I78: ='Manufacturing & Production'!G282 -> 114653 | J78: ='Workforce & Expenses'!M334 -> 737477 | K78: ='Manufacturing & Production'!K282 -> 16471 | L78: ='Clinical Trials & R&D'!F282 -> 2523809 | M78: ='Clinical Trials & R&D'!I282 -> 1081633 | N78: ='Workforce & Expenses'!P334 -> 1286002 | O78: ='Workforce & Expenses'!S334 -> 1597720 | P78: ='Funding & Cap'!F137 -> 324484 | Q78: ='Working Capital & Assets'!B81 -> 416667 | R78: ='Funding & Cap'!H137 -> 433101 | S78: ='Working Capital & Assets'!C81 -> 0 | T78: ='Working Capital & Assets'!D81 -> 798122 | U78: ='Funding & Cap'!B137 -> 0 | V78: ='Funding & Cap'!C137 -> 0 | W78: ='Funding & Cap'!D137 -> 0 | X78: ='Working Capital & Assets'!E81 -> 4275613 | Y78: ='Working Capital & Assets'!F81 -> 1103158 | Z78: ='Working Capital & Assets'!G81 -> 1846460 | AA78: ='Working Capital & Assets'!H81 -> 2286811 | AB78: ='Working Capital & Assets'!I81 -> 6128628 | AC78: ='Working Capital & Assets'!J81 -> 4710127 | AD78: =MIN(AE78,SUMIFS($W$2:$W$181,$A$2:$A$181,">"&A78,$A$2:$A$181,"<="&EDATE(A78,12))+IF(AND(DATE(2033,12,1)>A78,DATE(2033,12,1)<=EDATE(A78,12)),'Funding & Cap'!$B$200,0)) -> 5000000 | AE78: ='Funding & Cap'!Q137 -> 62000000 | AF78: =AF77+AG78+U78 -> 158278802 | AG78: =SUM(E78:G78)-SUM(H78:S78)+P78+Q78-(X78-X77)-(Y78-Y77)-(Z78-Z77)+(AA78-AA77)+(AB78-AB77)+(AC78-AC77)-T78+V78-W78 -> -5732835 | AH78: ='Revenue & Demand'!P242 -> 0 | AI78: ='Revenue & Demand'!Q242 -> 0 | AJ78: ='Manufacturing & Production'!J282 -> 0 | AK78: =A78 -> 45413 | AL78: =IF(B78<=2025,C78,"") -> 896 | AM78: =IF(OR(B78>=2026,AND(B78=2025,MONTH(A78)=12)),C78,"")
A79: 45444 | B79: =YEAR(A79) -> 2024 | C79: ='Revenue & Demand'!C243 -> 1007 | D79: ='Revenue & Demand'!F243 -> 30 | E79: ='Revenue & Demand'!E243 -> 1611310 | F79: ='Revenue & Demand'!H243 -> 1587817 | G79: ='Revenue & Demand'!J243 -> 1286765 | H79: ='Manufacturing & Production'!F283 -> 370601 | I79: ='Manufacturing & Production'!G283 -> 128905 | J79: ='Workforce & Expenses'!M335 -> 714518 | K79: ='Manufacturing & Production'!K283 -> 102941 | L79: ='Clinical Trials & R&D'!F283 -> 2445238 | M79: ='Clinical Trials & R&D'!I283 -> 1047959 | N79: ='Workforce & Expenses'!P335 -> 1394689 | O79: ='Workforce & Expenses'!S335 -> 1578033 | P79: ='Funding & Cap'!F138 -> 330383 | Q79: ='Working Capital & Assets'!B82 -> 416667 | R79: ='Funding & Cap'!H138 -> 433101 | S79: ='Working Capital & Assets'!C82 -> 0 | T79: ='Working Capital & Assets'!D82 -> 807512 | U79: ='Funding & Cap'!B138 -> 0 | V79: ='Funding & Cap'!C138 -> 0 | W79: ='Funding & Cap'!D138 -> 0 | X79: ='Working Capital & Assets'!E82 -> 4608219 | Y79: ='Working Capital & Assets'!F82 -> 1295800 | Z79: ='Working Capital & Assets'!G82 -> 1980000 | AA79: ='Working Capital & Assets'!H82 -> 2436589 | AB79: ='Working Capital & Assets'!I82 -> 6402500 | AC79: ='Working Capital & Assets'!J82 -> 4840000 | AD79: =MIN(AE79,SUMIFS($W$2:$W$181,$A$2:$A$181,">"&A79,$A$2:$A$181,"<="&EDATE(A79,12))+IF(AND(DATE(2033,12,1)>A79,DATE(2033,12,1)<=EDATE(A79,12)),'Funding & Cap'!$B$200,0)) -> 5000000 | AE79: ='Funding & Cap'!Q138 -> 62000000 | AF79: =AF78+AG79+U79 -> 153635932 | AG79: =SUM(E79:G79)-SUM(H79:S79)+P79+Q79-(X79-X78)-(Y79-Y78)-(Z79-Z78)+(AA79-AA78)+(AB79-AB78)+(AC79-AC78)-T79+V79-W79 -> -4642870 | AH79: ='Revenue & Demand'!P243 -> 0 | AI79: ='Revenue & Demand'!Q243 -> 0 | AJ79: ='Manufacturing & Production'!J283 -> 0 | AK79: =A79 -> 45444 | AL79: =IF(B79<=2025,C79,"") -> 1007 | AM79: =IF(OR(B79>=2026,AND(B79=2025,MONTH(A79)=12)),C79,"")
A80: 45474 | B80: =YEAR(A80) -> 2024 | C80: ='Revenue & Demand'!C244 -> 1124 | D80: ='Revenue & Demand'!F244 -> 31 | E80: ='Revenue & Demand'!E244 -> 1798951 | F80: ='Revenue & Demand'!H244 -> 1555442 | G80: ='Revenue & Demand'!J244 -> 205882 | H80: ='Manufacturing & Production'!F284 -> 413759 | I80: ='Manufacturing & Production'!G284 -> 143916 | J80: ='Workforce & Expenses'!M336 -> 699949 | K80: ='Manufacturing & Production'!K284 -> 16471 | L80: ='Clinical Trials & R&D'!F284 -> 2395381 | M80: ='Clinical Trials & R&D'!I284 -> 1026592 | N80: ='Workforce & Expenses'!P336 -> 1509177 | O80: ='Workforce & Expenses'!S336 -> 1558345 | P80: ='Funding & Cap'!F139 -> 336283 | Q80: ='Working Capital & Assets'!B83 -> 416667 | R80: ='Funding & Cap'!H139 -> 433101 | S80: ='Working Capital & Assets'!C83 -> 0 | T80: ='Working Capital & Assets'!D83 -> 816901 | U80: ='Funding & Cap'!B139 -> 0 | V80: ='Funding & Cap'!C139 -> 0 | W80: ='Funding & Cap'!D139 -> 0 | X80: ='Working Capital & Assets'!E83 -> 4940826 | Y80: ='Working Capital & Assets'!F83 -> 1488442 | Z80: ='Working Capital & Assets'!G83 -> 2113540 | AA80: ='Working Capital & Assets'!H83 -> 2586367 | AB80: ='Working Capital & Assets'!I83 -> 6676372 | AC80: ='Working Capital & Assets'!J83 -> 4969873 | AD80: =MIN(AE80,SUMIFS($W$2:$W$181,$A$2:$A$181,">"&A80,$A$2:$A$181,"<="&EDATE(A80,12))+IF(AND(DATE(2033,12,1)>A80,DATE(2033,12,1)<=EDATE(A80,12)),'Funding & Cap'!$B$200,0)) -> 5000000 | AE80: ='Funding & Cap'!Q139 -> 62000000 | AF80: =AF79+AG80+U80 -> 148077349 | AG80: =SUM(E80:G80)-SUM(H80:S80)+P80+Q80-(X80-X79)-(Y80-Y79)-(Z80-Z79)+(AA80-AA79)+(AB80-AB79)+(AC80-AC79)-T80+V80-W80 -> -5558583 | AH80: ='Revenue & Demand'!P244 -> 0 | AI80: ='Revenue & Demand'!Q244 -> 0 | AJ80: ='Manufacturing & Production'!J284 -> 0 | AK80: =A80 -> 45474 | AL80: =IF(B80<=2025,C80,"") -> 1124 | AM80: =IF(OR(B80>=2026,AND(B80=2025,MONTH(A80)=12)),C80,"")
A81: 45505 | B81: =YEAR(A81) -> 2024 | C81: ='Revenue & Demand'!C245 -> 1248 | D81: ='Revenue & Demand'!F245 -> 32 | E81: ='Revenue & Demand'!E245 -> 1996106 | F81: ='Revenue & Demand'!H245 -> 1555349 | G81: ='Revenue & Demand'!J245 -> 205882 | H81: ='Manufacturing & Production'!F285 -> 459105 | I81: ='Manufacturing & Production'!G285 -> 159688 | J81: ='Workforce & Expenses'!M337 -> 699907 | K81: ='Manufacturing & Production'!K285 -> 16471 | L81: ='Clinical Trials & R&D'!F285 -> 2395238 | M81: ='Clinical Trials & R&D'!I285 -> 1026531 | N81: ='Workforce & Expenses'!P337 -> 1632105 | O81: ='Workforce & Expenses'!S337 -> 1546774 | P81: ='Funding & Cap'!F140 -> 342183 | Q81: ='Working Capital & Assets'!B84 -> 416667 | R81: ='Funding & Cap'!H140 -> 433101 | S81: ='Working Capital & Assets'!C84 -> 0 | T81: ='Working Capital & Assets'!D84 -> 826291 | U81: ='Funding & Cap'!B140 -> 0 | V81: ='Funding & Cap'!C140 -> 0 | W81: ='Funding & Cap'!D140 -> 0 | X81: ='Working Capital & Assets'!E84 -> 5290267 | Y81: ='Working Capital & Assets'!F84 -> 1687334 | Z81: ='Working Capital & Assets'!G84 -> 2254170 | AA81: ='Working Capital & Assets'!H84 -> 2744648 | AB81: ='Working Capital & Assets'!I84 -> 6970754 | AC81: ='Working Capital & Assets'!J84 -> 5114071 | AD81: =MIN(AE81,SUMIFS($W$2:$W$181,$A$2:$A$181,">"&A81,$A$2:$A$181,"<="&EDATE(A81,12))+IF(AND(DATE(2033,12,1)>A81,DATE(2033,12,1)<=EDATE(A81,12)),'Funding & Cap'!$B$200,0)) -> 5000000 | AE81: ='Funding & Cap'!Q140 -> 62000000 | AF81: =AF80+AG81+U81 -> 142547373 | AG81: =SUM(E81:G81)-SUM(H81:S81)+P81+Q81-(X81-X80)-(Y81-Y80)-(Z81-Z80)+(AA81-AA80)+(AB81-AB80)+(AC81-AC80)-T81+V81-W81 -> -5529976 | AH81: ='Revenue & Demand'!P245 -> 0 | AI81: ='Revenue & Demand'!Q245 -> 0 | AJ81: ='Manufacturing & Production'!J285 -> 0 | AK81: =A81 -> 45505 | AL81: =IF(B81<=2025,C81,"") -> 1248 | AM81: =IF(OR(B81>=2026,AND(B81=2025,MONTH(A81)=12)),C81,"")
A82: 45536 | B82: =YEAR(A82) -> 2024 | C82: ='Revenue & Demand'!C246 -> 1377 | D82: ='Revenue & Demand'!F246 -> 33 | E82: ='Revenue & Demand'!E246 -> 2202756 | F82: ='Revenue & Demand'!H246 -> 1592548 | G82: ='Revenue & Demand'!J246 -> 1286765 | H82: ='Manufacturing & Production'!F286 -> 506635 | I82: ='Manufacturing & Production'!G286 -> 176220 | J82: ='Workforce & Expenses'!M338 -> 716647 | K82: ='Manufacturing & Production'!K286 -> 102941 | L82: ='Clinical Trials & R&D'!F286 -> 2452524 | M82: ='Clinical Trials & R&D'!I286 -> 1051081 | N82: ='Workforce & Expenses'!P338 -> 1764436 | O82: ='Workforce & Expenses'!S338 -> 1549259 | P82: ='Funding & Cap'!F141 -> 348083 | Q82: ='Working Capital & Assets'!B85 -> 416667 | R82: ='Funding & Cap'!H141 -> 398173 | S82: ='Working Capital & Assets'!C85 -> 0 | T82: ='Working Capital & Assets'!D85 -> 1962441 | U82: ='Funding & Cap'!B141 -> 0 | V82: ='Funding & Cap'!C141 -> 0 | W82: ='Funding & Cap'!D141 -> 5000000 | X82: ='Working Capital & Assets'!E85 -> 5668866 | Y82: ='Working Capital & Assets'!F85 -> 1897051 | Z82: ='Working Capital & Assets'!G85 -> 2407080 | AA82: ='Working Capital & Assets'!H85 -> 2917655 | AB82: ='Working Capital & Assets'!I85 -> 7300660 | AC82: ='Working Capital & Assets'!J85 -> 5283080 | AD82: =MIN(AE82,SUMIFS($W$2:$W$181,$A$2:$A$181,">"&A82,$A$2:$A$181,"<="&EDATE(A82,12))+IF(AND(DATE(2033,12,1)>A82,DATE(2033,12,1)<=EDATE(A82,12)),'Funding & Cap'!$B$200,0)) -> 0 | AE82: ='Funding & Cap'!Q141 -> 57000000 | AF82: =AF81+AG82+U82 -> 131879781 | AG82: =SUM(E82:G82)-SUM(H82:S82)+P82+Q82-(X82-X81)-(Y82-Y81)-(Z82-Z81)+(AA82-AA81)+(AB82-AB81)+(AC82-AC81)-T82+V82-W82 -> -10667592 | AH82: ='Revenue & Demand'!P246 -> 0 | AI82: ='Revenue & Demand'!Q246 -> 0 | AJ82: ='Manufacturing & Production'!J286 -> 0 | AK82: =A82 -> 45536 | AL82: =IF(B82<=2025,C82,"") -> 1377 | AM82: =IF(OR(B82>=2026,AND(B82=2025,MONTH(A82)=12)),C82,"")
A83: 45566 | B83: =YEAR(A83) -> 2024 | C83: ='Revenue & Demand'!C247 -> 1678 | D83: ='Revenue & Demand'!F247 -> 34 | E83: ='Revenue & Demand'!E247 -> 2684960 | F83: ='Revenue & Demand'!H247 -> 1662028 | G83: ='Revenue & Demand'!J247 -> 205882 | H83: ='Manufacturing & Production'!F287 -> 617541 | I83: ='Manufacturing & Production'!G287 -> 214797 | J83: ='Workforce & Expenses'!M339 -> 747913 | K83: ='Manufacturing & Production'!K287 -> 16471 | L83: ='Clinical Trials & R&D'!F287 -> 2559524 | M83: ='Clinical Trials & R&D'!I287 -> 1096939 | N83: ='Workforce & Expenses'!P339 -> 1966863 | O83: ='Workforce & Expenses'!S339 -> 1567976 | P83: ='Funding & Cap'!F142 -> 353982 | Q83: ='Working Capital & Assets'!B86 -> 416667 | R83: ='Funding & Cap'!H142 -> 398173 | S83: ='Working Capital & Assets'!C86 -> 0 | T83: ='Working Capital & Assets'!D86 -> 845070 | U83: ='Funding & Cap'!B142 -> 0 | V83: ='Funding & Cap'!C142 -> 0 | W83: ='Funding & Cap'!D142 -> 0 | X83: ='Working Capital & Assets'!E86 -> 6081134 | Y83: ='Working Capital & Assets'!F86 -> 2119268 | Z83: ='Working Capital & Assets'!G86 -> 2574170 | AA83: ='Working Capital & Assets'!H86 -> 3107666 | AB83: ='Working Capital & Assets'!I86 -> 7671587 | AC83: ='Working Capital & Assets'!J86 -> 5480738 | AD83: =MIN(AE83,SUMIFS($W$2:$W$181,$A$2:$A$181,">"&A83,$A$2:$A$181,"<="&EDATE(A83,12))+IF(AND(DATE(2033,12,1)>A83,DATE(2033,12,1)<=EDATE(A83,12)),'Funding & Cap'!$B$200,0)) -> 0 | AE83: ='Funding & Cap'!Q142 -> 57000000 | AF83: =AF82+AG83+U83 -> 126358405 | AG83: =SUM(E83:G83)-SUM(H83:S83)+P83+Q83-(X83-X82)-(Y83-Y82)-(Z83-Z82)+(AA83-AA82)+(AB83-AB82)+(AC83-AC82)-T83+V83-W83 -> -5521376 | AH83: ='Revenue & Demand'!P247 -> 0 | AI83: ='Revenue & Demand'!Q247 -> 0 | AJ83: ='Manufacturing & Production'!J287 -> 0 | AK83: =A83 -> 45566 | AL83: =IF(B83<=2025,C83,"") -> 1678 | AM83: =IF(OR(B83>=2026,AND(B83=2025,MONTH(A83)=12)),C83,"")
A84: 45597 | B84: =YEAR(A84) -> 2024 | C84: ='Revenue & Demand'!C248 -> 1835 | D84: ='Revenue & Demand'!F248 -> 35 | E84: ='Revenue & Demand'!E248 -> 2935404 | F84: ='Revenue & Demand'!H248 -> 1750155 | G84: ='Revenue & Demand'!J248 -> 205882 | H84: ='Manufacturing & Production'!F288 -> 675143 | I84: ='Manufacturing & Production'!G288 -> 234832 | J84: ='Workforce & Expenses'!M340 -> 787570 | K84: ='Manufacturing & Production'!K288 -> 16471 | L84: ='Clinical Trials & R&D'!F288 -> 2695238 | M84: ='Clinical Trials & R&D'!I288 -> 1155102 | N84: ='Workforce & Expenses'!P340 -> 2119179 | O84: ='Workforce & Expenses'!S340 -> 1600749 | P84: ='Funding & Cap'!F143 -> 359882 | Q84: ='Working Capital & Assets'!B87 -> 416667 | R84: ='Funding & Cap'!H143 -> 398173 | S84: ='Working Capital & Assets'!C87 -> 0 | T84: ='Working Capital & Assets'!D87 -> 854460 | U84: ='Funding & Cap'!B143 -> 0 | V84: ='Funding & Cap'!C143 -> 0 | W84: ='Funding & Cap'!D143 -> 0 | X84: ='Working Capital & Assets'!E87 -> 6522561 | Y84: ='Working Capital & Assets'!F87 -> 2352309 | Z84: ='Working Capital & Assets'!G87 -> 2753540 | AA84: ='Working Capital & Assets'!H87 -> 3312404 | AB84: ='Working Capital & Assets'!I87 -> 8078038 | AC84: ='Working Capital & Assets'!J87 -> 5703207 | AD84: =MIN(AE84,SUMIFS($W$2:$W$181,$A$2:$A$181,">"&A84,$A$2:$A$181,"<="&EDATE(A84,12))+IF(AND(DATE(2033,12,1)>A84,DATE(2033,12,1)<=EDATE(A84,12)),'Funding & Cap'!$B$200,0)) -> 0 | AE84: ='Funding & Cap'!Q143 -> 57000000 | AF84: =AF83+AG84+U84 -> 120692749 | AG84: =SUM(E84:G84)-SUM(H84:S84)+P84+Q84-(X84-X83)-(Y84-Y83)-(Z84-Z83)+(AA84-AA83)+(AB84-AB83)+(AC84-AC83)-T84+V84-W84 -> -5665656 | AH84: ='Revenue & Demand'!P248 -> 0 | AI84: ='Revenue & Demand'!Q248 -> 0 | AJ84: ='Manufacturing & Production'!J288 -> 0 | AK84: =A84 -> 45597 | AL84: =IF(B84<=2025,C84,"") -> 1835 | AM84: =IF(OR(B84>=2026,AND(B84=2025,MONTH(A84)=12)),C84,"")
A85: 45627 | B85: =YEAR(A85) -> 2024 | C85: ='Revenue & Demand'!C249 -> 1998 | D85: ='Revenue & Demand'!F249 -> 36 | E85: ='Revenue & Demand'!E249 -> 3196398 | F85: ='Revenue & Demand'!H249 -> 1838281 | G85: ='Revenue & Demand'!J249 -> 1492649 | H85: ='Manufacturing & Production'!F289 -> 735170 | I85: ='Manufacturing & Production'!G289 -> 255712 | J85: ='Workforce & Expenses'!M341 -> 827225 | K85: ='Manufacturing & Production'!K289 -> 119409 | L85: ='Clinical Trials & R&D'!F289 -> 2830952 | M85: ='Clinical Trials & R&D'!I289 -> 1213265 | N85: ='Workforce & Expenses'!P341 -> 2273941 | O85: ='Workforce & Expenses'!S341 -> 1641639 | P85: ='Funding & Cap'!F144 -> 365782 | Q85: ='Working Capital & Assets'!B88 -> 416663 | R85: ='Funding & Cap'!H144 -> 398173 | S85: ='Working Capital & Assets'!C88 -> 0 | T85: ='Working Capital & Assets'!D88 -> 863852 | U85: ='Funding & Cap'!B144 -> 0 | V85: ='Funding & Cap'!C144 -> 0 | W85: ='Funding & Cap'!D144 -> 0 | X85: ='Working Capital & Assets'!E88 -> 6980822 | Y85: ='Working Capital & Assets'!F88 -> 2591600 | Z85: ='Working Capital & Assets'!G88 -> 2940000 | AA85: ='Working Capital & Assets'!H88 -> 3525644 | AB85: ='Working Capital & Assets'!I88 -> 8505000 | AC85: ='Working Capital & Assets'!J88 -> 5940000 | AD85: =MIN(AE85,SUMIFS($W$2:$W$181,$A$2:$A$181,">"&A85,$A$2:$A$181,"<="&EDATE(A85,12))+IF(AND(DATE(2033,12,1)>A85,DATE(2033,12,1)<=EDATE(A85,12)),'Funding & Cap'!$B$200,0)) -> 0 | AE85: ='Funding & Cap'!Q144 -> 57000000 | AF85: =AF84+AG85+U85 -> 116053722 | AG85: =SUM(E85:G85)-SUM(H85:S85)+P85+Q85-(X85-X84)-(Y85-Y84)-(Z85-Z84)+(AA85-AA84)+(AB85-AB84)+(AC85-AC84)-T85+V85-W85 -> -4639027 | AH85: ='Revenue & Demand'!P249 -> 0 | AI85: ='Revenue & Demand'!Q249 -> 0 | AJ85: ='Manufacturing & Production'!J289 -> 0 | AK85: =A85 -> 45627 | AL85: =IF(B85<=2025,C85,"") -> 1998 | AM85: =IF(OR(B85>=2026,AND(B85=2025,MONTH(A85)=12)),C85,"")
... A97: 45992 | B97: =YEAR(A97) -> 2025 | C97: ='Revenue & Demand'!C261 -> 4724 | D97: ='Revenue & Demand'!F261 -> 58 | E97: ='Revenue & Demand'!E261 -> 7085598 | F97: ='Revenue & Demand'!H261 -> 2022109 | G97: ='Revenue & Demand'!J261 -> 1492649 | H97: ='Manufacturing & Production'!F301 -> 1558830 | I97: ='Manufacturing & Production'!G301 -> 566848 | J97: ='Workforce & Expenses'!M353 -> 869508 | K97: ='Manufacturing & Production'!K301 -> 119409 | L97: ='Clinical Trials & R&D'!F301 -> 4117748 | M97: ='Clinical Trials & R&D'!I301 -> 2316233 | N97: ='Workforce & Expenses'!P353 -> 4076933 | O97: ='Workforce & Expenses'!S353 -> 2419258 | P97: ='Funding & Cap'!F156 -> 640116 | Q97: ='Working Capital & Assets'!B100 -> 583337 | R97: ='Funding & Cap'!H156 -> 608110 | S97: ='Working Capital & Assets'!C100 -> 0 | T97: ='Working Capital & Assets'!D100 -> 1151800 | U97: ='Funding & Cap'!B156 -> 0 | V97: ='Funding & Cap'!C156 -> 0 | W97: ='Funding & Cap'!D156 -> 0 | X97: ='Working Capital & Assets'!E100 -> 14421918 | Y97: ='Working Capital & Assets'!F100 -> 6240000 | Z97: ='Working Capital & Assets'!G100 -> 5640000 | AA97: ='Working Capital & Assets'!H100 -> 6183452 | AB97: ='Working Capital & Assets'!I100 -> 14740000 | AC97: ='Working Capital & Assets'!J100 -> 6960000 | AD97: =MIN(AE97,SUMIFS($W$2:$W$181,$A$2:$A$181,">"&A97,$A$2:$A$181,"<="&EDATE(A97,12))+IF(AND(DATE(2033,12,1)>A97,DATE(2033,12,1)<=EDATE(A97,12)),'Funding & Cap'!$B$200,0)) -> 0 | AE97: ='Funding & Cap'!Q156 -> 97000000 | AF97: =AF96+AG97+U97 -> 60112034 | AG97: =SUM(E97:G97)-SUM(H97:S97)+P97+Q97-(X97-X96)-(Y97-Y96)-(Z97-Z96)+(AA97-AA96)+(AB97-AB96)+(AC97-AC96)-T97+V97-W97 -> -7513145 | AH97: ='Revenue & Demand'!P261 -> 0 | AI97: ='Revenue & Demand'!Q261 -> 0 | AJ97: ='Manufacturing & Production'!J301 -> 0 | AK97: =A97 -> 45992 | AL97: =IF(B97<=2025,C97,"") -> 4724 | AM97: =IF(OR(B97>=2026,AND(B97=2025,MONTH(A97)=12)),C97,"") -> 4724
A98: 46023 | B98: =YEAR(A98) -> 2026 | C98: ='Revenue & Demand'!C262 -> 4754 | D98: ='Revenue & Demand'!F262 -> 59 | E98: ='Revenue & Demand'!E262 -> 7131000 | F98: ='Revenue & Demand'!H262 -> 2831970 | G98: ='Revenue & Demand'!J262 -> 205882 | H98: ='Manufacturing & Production'!F302 -> 1966713 | I98: ='Manufacturing & Production'!G302 -> 570480 | J98: ='Workforce & Expenses'!M354 -> 1045452 | K98: ='Manufacturing & Production'!K302 -> 16471 | L98: ='Clinical Trials & R&D'!F302 -> 6167770 | M98: ='Clinical Trials & R&D'!I302 -> 4189174 | N98: ='Workforce & Expenses'!P354 -> 3917386 | O98: ='Workforce & Expenses'!S354 -> 3629032 | P98: ='Workforce & Expenses'!Y354 -> 922075 | Q98: ='Working Capital & Assets'!B104 -> 816666 | R98: ='Funding & Cap'!H157 -> 687083 | S98: ='Working Capital & Assets'!C104 -> 0 | T98: ='Working Capital & Assets'!D104 -> 1327775 | U98: ='Funding & Cap'!B157 -> 0 | V98: ='Funding & Cap'!C157 -> 0 | W98: ='Funding & Cap'!D157 -> 0 | X98: ='Working Capital & Assets'!E104 -> 12741677 | Y98: ='Working Capital & Assets'!F104 -> 6064369 | Z98: ='Working Capital & Assets'!G104 -> 5300182 | AA98: ='Working Capital & Assets'!H104 -> 6600326 | AB98: ='Working Capital & Assets'!I104 -> 15961986 | AC98: ='Working Capital & Assets'!J104 -> 8979442 | AD98: =MIN(AE98,SUMIFS($W$2:$W$181,$A$2:$A$181,">"&A98,$A$2:$A$181,"<="&EDATE(A98,12))+IF(AND(DATE(2033,12,1)>A98,DATE(2033,12,1)<=EDATE(A98,12)),'Funding & Cap'!$B$200,0)) -> 0 | AE98: ='Funding & Cap'!Q157 -> 97000000 | AF98: =AF97+AG98+U98 -> 52617542 | AG98: =SUM(E98:G98)+AI98-SUM(H98:S98)-AJ98+P98+Q98-(X98-X97)-(Y98-Y97)-(Z98-Z97)+(AA98-AA97)+(AB98-AB97)+(AC98-AC97)-T98+V98-W98 -> -7494492 | AH98: ='Revenue & Demand'!P262 -> 0 | AI98: ='Revenue & Demand'!Q262 -> 0 | AJ98: ='Manufacturing & Production'!J302 -> 0 | AK98: =A98 -> 46023 | AL98: =IF(B98<=2025,C98,"") | AM98: =IF(OR(B98>=2026,AND(B98=2025,MONTH(A98)=12)),C98,"") -> 4754
A99: 46054 | B99: =YEAR(A99) -> 2026 | C99: ='Revenue & Demand'!C263 -> 4882 | D99: ='Revenue & Demand'!F263 -> 61 | E99: ='Revenue & Demand'!E263 -> 7323000 | F99: ='Revenue & Demand'!H263 -> 2906536 | G99: ='Revenue & Demand'!J263 -> 205882 | H99: ='Manufacturing & Production'!F303 -> 1964464 | I99: ='Manufacturing & Production'!G303 -> 585840 | J99: ='Workforce & Expenses'!M355 -> 1085501 | K99: ='Manufacturing & Production'!K303 -> 16471 | L99: ='Clinical Trials & R&D'!F303 -> 6143630 | M99: ='Clinical Trials & R&D'!I303 -> 4230569 | N99: ='Workforce & Expenses'!P355 -> 3900001 | O99: ='Workforce & Expenses'!S355 -> 3619141 | P99: ='Workforce & Expenses'!Y355 -> 940781 | Q99: ='Working Capital & Assets'!B105 -> 816666 | R99: ='Funding & Cap'!H158 -> 687083 | S99: ='Working Capital & Assets'!C105 -> 0 | T99: ='Working Capital & Assets'!D105 -> 1368805 | U99: ='Funding & Cap'!B158 -> 155000000 | V99: ='Funding & Cap'!C158 -> 0 | W99: ='Funding & Cap'!D158 -> 0 | X99: ='Working Capital & Assets'!E105 -> 13734100 | Y99: ='Working Capital & Assets'!F105 -> 6537591 | Z99: ='Working Capital & Assets'!G105 -> 5655590 | AA99: ='Working Capital & Assets'!H105 -> 6898881 | AB99: ='Working Capital & Assets'!I105 -> 16470279 | AC99: ='Working Capital & Assets'!J105 -> 9214526 | AD99: =MIN(AE99,SUMIFS($W$2:$W$181,$A$2:$A$181,">"&A99,$A$2:$A$181,"<="&EDATE(A99,12))+IF(AND(DATE(2033,12,1)>A99,DATE(2033,12,1)<=EDATE(A99,12)),'Funding & Cap'!$B$200,0)) -> 0 | AE99: ='Funding & Cap'!Q158 -> 97000000 | AF99: =AF98+AG99+U99 -> 193672334 | AG99: =SUM(E99:G99)+AI99-SUM(H99:S99)-AJ99+P99+Q99-(X99-X98)-(Y99-Y98)-(Z99-Z98)+(AA99-AA98)+(AB99-AB98)+(AC99-AC98)-T99+V99-W99 -> -13945208 | AH99: ='Revenue & Demand'!P263 -> 0 | AI99: ='Revenue & Demand'!Q263 -> 0 | AJ99: ='Manufacturing & Production'!J303 -> 0 | AK99: =A99 -> 46054 | AL99: =IF(B99<=2025,C99,"") | AM99: =IF(OR(B99>=2026,AND(B99=2025,MONTH(A99)=12)),C99,"") -> 4882
A100: 46082 | B100: =YEAR(A100) -> 2026 | C100: ='Revenue & Demand'!C264 -> 5134 | D100: ='Revenue & Demand'!F264 -> 64 | E100: ='Revenue & Demand'!E264 -> 7701000 | F100: ='Revenue & Demand'!H264 -> 2855035 | G100: ='Revenue & Demand'!J264 -> 1286765 | H100: ='Manufacturing & Production'!F304 -> 2027731 | I100: ='Manufacturing & Production'!G304 -> 616080 | J100: ='Workforce & Expenses'!M356 -> 1098257 | K100: ='Manufacturing & Production'!K304 -> 102941 | L100: ='Clinical Trials & R&D'!F304 -> 6161735 | M100: ='Clinical Trials & R&D'!I304 -> 4271964 | N100: ='Workforce & Expenses'!P356 -> 3853315 | O100: ='Workforce & Expenses'!S356 -> 3598562 | P100: ='Workforce & Expenses'!Y356 -> 959512 | Q100: ='Working Capital & Assets'!B106 -> 816666 | R100: ='Funding & Cap'!H159 -> 687083 | S100: ='Working Capital & Assets'!C106 -> 0 | T100: ='Working Capital & Assets'!D106 -> 3449623 | U100: ='Funding & Cap'!B159 -> 0 | V100: ='Funding & Cap'!C159 -> 0 | W100: ='Funding & Cap'!D159 -> 0 | X100: ='Working Capital & Assets'!E106 -> 13988514 | Y100: ='Working Capital & Assets'!F106 -> 7035149 | Z100: ='Working Capital & Assets'!G106 -> 5712598 | AA100: ='Working Capital & Assets'!H106 -> 7274535 | AB100: ='Working Capital & Assets'!I106 -> 17098451 | AC100: ='Working Capital & Assets'!J106 -> 8228707 | AD100: =MIN(AE100,SUMIFS($W$2:$W$181,$A$2:$A$181,">"&A100,$A$2:$A$181,"<="&EDATE(A100,12))+IF(AND(DATE(2033,12,1)>A100,DATE(2033,12,1)<=EDATE(A100,12)),'Funding & Cap'!$B$200,0)) -> 0 | AE100: ='Funding & Cap'!Q159 -> 97000000 | AF100: =AF99+AG100+U100 -> 178856870 | AG100: =SUM(E100:G100)+AI100-SUM(H100:S100)-AJ100+P100+Q100-(X100-X99)-(Y100-Y99)-(Z100-Z99)+(AA100-AA99)+(AB100-AB99)+(AC100-AC99)-T100+V100-W100 -> -14815464 | AH100: ='Revenue & Demand'!P264 -> 0 | AI100: ='Revenue & Demand'!Q264 -> 0 | AJ100: ='Manufacturing & Production'!J304 -> 0 | AK100: =A100 -> 46082 | AL100: =IF(B100<=2025,C100,"") | AM100: =IF(OR(B100>=2026,AND(B100=2025,MONTH(A100)=12)),C100,"") -> 5134
A101: 46113 | B101: =YEAR(A101) -> 2026 | C101: ='Revenue & Demand'!C265 -> 5365 | D101: ='Revenue & Demand'!F265 -> 65 | E101: ='Revenue & Demand'!E265 -> 8047500 | F101: ='Revenue & Demand'!H265 -> 2868887 | G101: ='Revenue & Demand'!J265 -> 205882 | H101: ='Manufacturing & Production'!F305 -> 2033516 | I101: ='Manufacturing & Production'!G305 -> 643800 | J101: ='Workforce & Expenses'!M357 -> 1111599 | K101: ='Manufacturing & Production'!K305 -> 16471 | L101: ='Clinical Trials & R&D'!F305 -> 6228120 | M101: ='Clinical Trials & R&D'!I305 -> 4189174 | N101: ='Workforce & Expenses'!P357 -> 3845722 | O101: ='Workforce & Expenses'!S357 -> 3586215 | P101: ='Workforce & Expenses'!Y357 -> 978266 | Q101: ='Working Capital & Assets'!B107 -> 816666 | R101: ='Funding & Cap'!H160 -> 687083 | S101: ='Working Capital & Assets'!C107 -> 0 | T101: ='Working Capital & Assets'!D107 -> 1376952 | U101: ='Funding & Cap'!B160 -> 0 | V101: ='Funding & Cap'!C160 -> 0 | W101: ='Funding & Cap'!D160 -> 0 | X101: ='Working Capital & Assets'!E107 -> 15854615 | Y101: ='Working Capital & Assets'!F107 -> 7368545 | Z101: ='Working Capital & Assets'!G107 -> 6429447 | AA101: ='Working Capital & Assets'!H107 -> 7717252 | AB101: ='Working Capital & Assets'!I107 -> 17796590 | AC101: ='Working Capital & Assets'!J107 -> 9513683 | AD101: =MIN(AE101,SUMIFS($W$2:$W$181,$A$2:$A$181,">"&A101,$A$2:$A$181,"<="&EDATE(A101,12))+IF(AND(DATE(2033,12,1)>A101,DATE(2033,12,1)<=EDATE(A101,12)),'Funding & Cap'!$B$200,0)) -> 0 | AE101: ='Funding & Cap'!Q160 -> 97000000 | AF101: =AF100+AG101+U101 -> 165769973 | AG101: =SUM(E101:G101)+AI101-SUM(H101:S101)-AJ101+P101+Q101-(X101-X100)-(Y101-Y100)-(Z101-Z100)+(AA101-AA100)+(AB101-AB100)+(AC101-AC100)-T101+V101-W101 -> -13086897 | AH101: ='Revenue & Demand'!P265 -> 0 | AI101: ='Revenue & Demand'!Q265 -> 0 | AJ101: ='Manufacturing & Production'!J305 -> 0 | AK101: =A101 -> 46113 | AL101: =IF(B101<=2025,C101,"") | AM101: =IF(OR(B101>=2026,AND(B101=2025,MONTH(A101)=12)),C101,"") -> 5365
A102: 46143 | B102: =YEAR(A102) -> 2026 | C102: ='Revenue & Demand'!C266 -> 5643 | D102: ='Revenue & Demand'!F266 -> 68 | E102: ='Revenue & Demand'!E266 -> 8464500 | F102: ='Revenue & Demand'!H266 -> 2797662 | G102: ='Revenue & Demand'!J266 -> 205882 | H102: ='Manufacturing & Production'!F306 -> 2081804 | I102: ='Manufacturing & Production'!G306 -> 677160 | J102: ='Workforce & Expenses'!M358 -> 1139335 | K102: ='Manufacturing & Production'!K306 -> 16471 | L102: ='Clinical Trials & R&D'!F306 -> 6203980 | M102: ='Clinical Trials & R&D'!I306 -> 4230569 | N102: ='Workforce & Expenses'!P358 -> 3888347 | O102: ='Workforce & Expenses'!S358 -> 3593452 | P102: ='Workforce & Expenses'!Y358 -> 997044 | Q102: ='Working Capital & Assets'!B108 -> 816666 | R102: ='Funding & Cap'!H161 -> 687083 | S102: ='Working Capital & Assets'!C108 -> 0 | T102: ='Working Capital & Assets'!D108 -> 1418884 | U102: ='Funding & Cap'!B161 -> 0 | V102: ='Funding & Cap'!C161 -> 0 | W102: ='Funding & Cap'!D161 -> 0 | X102: ='Working Capital & Assets'!E108 -> 16860181 | Y102: ='Working Capital & Assets'!F108 -> 7747151 | Z102: ='Working Capital & Assets'!G108 -> 6795802 | AA102: ='Working Capital & Assets'!H108 -> 8225069 | AB102: ='Working Capital & Assets'!I108 -> 18648241 | AC102: ='Working Capital & Assets'!J108 -> 9611505 | AD102: =MIN(AE102,SUMIFS($W$2:$W$181,$A$2:$A$181,">"&A102,$A$2:$A$181,"<="&EDATE(A102,12))+IF(AND(DATE(2033,12,1)>A102,DATE(2033,12,1)<=EDATE(A102,12)),'Funding & Cap'!$B$200,0)) -> 0 | AE102: ='Funding & Cap'!Q161 -> 97000000 | AF102: =AF101+AG102+U102 -> 153007695 | AG102: =SUM(E102:G102)+AI102-SUM(H102:S102)-AJ102+P102+Q102-(X102-X101)-(Y102-Y101)-(Z102-Z101)+(AA102-AA101)+(AB102-AB101)+(AC102-AC101)-T102+V102-W102 -> -12762278 | AH102: ='Revenue & Demand'!P266 -> 0 | AI102: ='Revenue & Demand'!Q266 -> 0 | AJ102: ='Manufacturing & Production'!J306 -> 0 | AK102: =A102 -> 46143 | AL102: =IF(B102<=2025,C102,"") | AM102: =IF(OR(B102>=2026,AND(B102=2025,MONTH(A102)=12)),C102,"") -> 5643
A103: 46174 | B103: =YEAR(A103) -> 2026 | C103: ='Revenue & Demand'!C267 -> 5711 | D103: ='Revenue & Demand'!F267 -> 70 | E103: ='Revenue & Demand'!E267 -> 8566500 | F103: ='Revenue & Demand'!H267 -> 2590912 | G103: ='Revenue & Demand'!J267 -> 1286765 | H103: ='Manufacturing & Production'!F307 -> 2100917 | I103: ='Manufacturing & Production'!G307 -> 685320 | J103: ='Workforce & Expenses'!M359 -> 1152107 | K103: ='Manufacturing & Production'!K307 -> 102941 | L103: ='Clinical Trials & R&D'!F307 -> 6179840 | M103: ='Clinical Trials & R&D'!I307 -> 4271964 | N103: ='Workforce & Expenses'!P359 -> 3918743 | O103: ='Workforce & Expenses'!S359 -> 3613619 | P103: ='Workforce & Expenses'!Y359 -> 1015846 | Q103: ='Working Capital & Assets'!B109 -> 816666 | R103: ='Funding & Cap'!H162 -> 687083 | S103: ='Working Capital & Assets'!C109 -> 0 | T103: ='Working Capital & Assets'!D109 -> 1461416 | U103: ='Funding & Cap'!B162 -> 0 | V103: ='Funding & Cap'!C162 -> 0 | W103: ='Funding & Cap'!D162 -> 0 | X103: ='Working Capital & Assets'!E109 -> 16286209 | Y103: ='Working Capital & Assets'!F109 -> 7953000 | Z103: ='Working Capital & Assets'!G109 -> 6528868 | AA103: ='Working Capital & Assets'!H109 -> 8483435 | AB103: ='Working Capital & Assets'!I109 -> 19476112 | AC103: ='Working Capital & Assets'!J109 -> 8245307 | AD103: =MIN(AE103,SUMIFS($W$2:$W$181,$A$2:$A$181,">"&A103,$A$2:$A$181,"<="&EDATE(A103,12))+IF(AND(DATE(2033,12,1)>A103,DATE(2033,12,1)<=EDATE(A103,12)),'Funding & Cap'!$B$200,0)) -> 0 | AE103: ='Funding & Cap'!Q162 -> 97000000 | AF103: =AF102+AG103+U103 -> 141633018 | AG103: =SUM(E103:G103)+AI103-SUM(H103:S103)-AJ103+P103+Q103-(X103-X102)-(Y103-Y102)-(Z103-Z102)+(AA103-AA102)+(AB103-AB102)+(AC103-AC102)-T103+V103-W103 -> -11374677 | AH103: ='Revenue & Demand'!P267 -> 0 | AI103: ='Revenue & Demand'!Q267 -> 0 | AJ103: ='Manufacturing & Production'!J307 -> 0 | AK103: =A103 -> 46174 | AL103: =IF(B103<=2025,C103,"") | AM103: =IF(OR(B103>=2026,AND(B103=2025,MONTH(A103)=12)),C103,"") -> 5711
A104: 46204 | B104: =YEAR(A104) -> 2026 | C104: ='Revenue & Demand'!C268 -> 6081 | D104: ='Revenue & Demand'!F268 -> 71 | E104: ='Revenue & Demand'!E268 -> 9121500 | F104: ='Revenue & Demand'!H268 -> 2556039 | G104: ='Revenue & Demand'!J268 -> 205882 | H104: ='Manufacturing & Production'!F308 -> 2115766 | I104: ='Manufacturing & Production'!G308 -> 729720 | J104: ='Workforce & Expenses'!M360 -> 1191452 | K104: ='Manufacturing & Production'!K308 -> 16471 | L104: ='Clinical Trials & R&D'!F308 -> 6246225 | M104: ='Clinical Trials & R&D'!I308 -> 4189174 | N104: ='Workforce & Expenses'!P360 -> 3892381 | O104: ='Workforce & Expenses'!S360 -> 3628175 | P104: ='Workforce & Expenses'!Y360 -> 1034674 | Q104: ='Working Capital & Assets'!B110 -> 816666 | R104: ='Funding & Cap'!H163 -> 687083 | S104: ='Working Capital & Assets'!C110 -> 0 | T104: ='Working Capital & Assets'!D110 -> 1426128 | U104: ='Funding & Cap'!B163 -> 0 | V104: ='Funding & Cap'!C163 -> 0 | W104: ='Funding & Cap'!D163 -> 0 | X104: ='Working Capital & Assets'!E110 -> 18301254 | Y104: ='Working Capital & Assets'!F110 -> 8276068 | Z104: ='Working Capital & Assets'!G110 -> 7300183 | AA104: ='Working Capital & Assets'!H110 -> 8986020 | AB104: ='Working Capital & Assets'!I110 -> 20078235 | AC104: ='Working Capital & Assets'!J110 -> 9325706 | AD104: =MIN(AE104,SUMIFS($W$2:$W$181,$A$2:$A$181,">"&A104,$A$2:$A$181,"<="&EDATE(A104,12))+IF(AND(DATE(2033,12,1)>A104,DATE(2033,12,1)<=EDATE(A104,12)),'Funding & Cap'!$B$200,0)) -> 0 | AE104: ='Funding & Cap'!Q163 -> 97000000 | AF104: =AF103+AG104+U104 -> 128469543 | AG104: =SUM(E104:G104)+AI104-SUM(H104:S104)-AJ104+P104+Q104-(X104-X103)-(Y104-Y103)-(Z104-Z103)+(AA104-AA103)+(AB104-AB103)+(AC104-AC103)-T104+V104-W104 -> -13163475 | AH104: ='Revenue & Demand'!P268 -> 0 | AI104: ='Revenue & Demand'!Q268 -> 0 | AJ104: ='Manufacturing & Production'!J308 -> 0 | AK104: =A104 -> 46204 | AL104: =IF(B104<=2025,C104,"") | AM104: =IF(OR(B104>=2026,AND(B104=2025,MONTH(A104)=12)),C104,"") -> 6081
A105: 46235 | B105: =YEAR(A105) -> 2026 | C105: ='Revenue & Demand'!C269 -> 6301 | D105: ='Revenue & Demand'!F269 -> 74 | E105: ='Revenue & Demand'!E269 -> 9451500 | F105: ='Revenue & Demand'!H269 -> 2527143 | G105: ='Revenue & Demand'!J269 -> 205882 | H105: ='Manufacturing & Production'!F309 -> 2157852 | I105: ='Manufacturing & Production'!G309 -> 756120 | J105: ='Workforce & Expenses'!M361 -> 1202334 | K105: ='Manufacturing & Production'!K309 -> 16471 | L105: ='Clinical Trials & R&D'!F309 -> 6222085 | M105: ='Clinical Trials & R&D'!I309 -> 4230569 | N105: ='Workforce & Expenses'!P361 -> 3847880 | O105: ='Workforce & Expenses'!S361 -> 3623737 | P105: ='Workforce & Expenses'!Y361 -> 1053524 | Q105: ='Working Capital & Assets'!B111 -> 816666 | R105: ='Funding & Cap'!H164 -> 687083 | S105: ='Working Capital & Assets'!C111 -> 0 | T105: ='Working Capital & Assets'!D111 -> 1468961 | U105: ='Funding & Cap'!B164 -> 0 | V105: ='Funding & Cap'!C164 -> 0 | W105: ='Funding & Cap'!D164 -> 0 | X105: ='Working Capital & Assets'!E111 -> 19102397 | Y105: ='Working Capital & Assets'!F111 -> 8580892 | Z105: ='Working Capital & Assets'!G111 -> 7584526 | AA105: ='Working Capital & Assets'!H111 -> 9282948 | AB105: ='Working Capital & Assets'!I111 -> 20478069 | AC105: ='Working Capital & Assets'!J111 -> 9284442 | AD105: =MIN(AE105,SUMIFS($W$2:$W$181,$A$2:$A$181,">"&A105,$A$2:$A$181,"<="&EDATE(A105,12))+IF(AND(DATE(2033,12,1)>A105,DATE(2033,12,1)<=EDATE(A105,12)),'Funding & Cap'!$B$200,0)) -> 0 | AE105: ='Funding & Cap'!Q164 -> 97000000 | AF105: =AF104+AG105+U105 -> 115706164 | AG105: =SUM(E105:G105)+AI105-SUM(H105:S105)-AJ105+P105+Q105-(X105-X104)-(Y105-Y104)-(Z105-Z104)+(AA105-AA104)+(AB105-AB104)+(AC105-AC104)-T105+V105-W105 -> -12763379 | AH105: ='Revenue & Demand'!P269 -> 0 | AI105: ='Revenue & Demand'!Q269 -> 0 | AJ105: ='Manufacturing & Production'!J309 -> 0 | AK105: =A105 -> 46235 | AL105: =IF(B105<=2025,C105,"") | AM105: =IF(OR(B105>=2026,AND(B105=2025,MONTH(A105)=12)),C105,"") -> 6301
A106: 46266 | B106: =YEAR(A106) -> 2026 | C106: ='Revenue & Demand'!C270 -> 6576 | D106: ='Revenue & Demand'!F270 -> 76 | E106: ='Revenue & Demand'!E270 -> 9864000 | F106: ='Revenue & Demand'!H270 -> 2572308 | G106: ='Revenue & Demand'!J270 -> 1286765 | H106: ='Manufacturing & Production'!F310 -> 2167051 | I106: ='Manufacturing & Production'!G310 -> 789120 | J106: ='Workforce & Expenses'!M362 -> 1210114 | K106: ='Manufacturing & Production'!K310 -> 102941 | L106: ='Clinical Trials & R&D'!F310 -> 6197945 | M106: ='Clinical Trials & R&D'!I310 -> 4271964 | N106: ='Workforce & Expenses'!P362 -> 3850435 | O106: ='Workforce & Expenses'!S362 -> 3604385 | P106: ='Workforce & Expenses'!Y362 -> 1072400 | Q106: ='Working Capital & Assets'!B112 -> 816666 | R106: ='Funding & Cap'!H165 -> 687083 | S106: ='Working Capital & Assets'!C112 -> 0 | T106: ='Working Capital & Assets'!D112 -> 3551582 | U106: ='Funding & Cap'!B165 -> 0 | V106: ='Funding & Cap'!C165 -> 0 | W106: ='Funding & Cap'!D165 -> 0 | X106: ='Working Capital & Assets'!E112 -> 19179911 | Y106: ='Working Capital & Assets'!F112 -> 8860034 | Z106: ='Working Capital & Assets'!G112 -> 7582567 | AA106: ='Working Capital & Assets'!H112 -> 9343155 | AB106: ='Working Capital & Assets'!I112 -> 20699914 | AC106: ='Working Capital & Assets'!J112 -> 8356443 | AD106: =MIN(AE106,SUMIFS($W$2:$W$181,$A$2:$A$181,">"&A106,$A$2:$A$181,"<="&EDATE(A106,12))+IF(AND(DATE(2033,12,1)>A106,DATE(2033,12,1)<=EDATE(A106,12)),'Funding & Cap'!$B$200,0)) -> 0 | AE106: ='Funding & Cap'!Q165 -> 97000000 | AF106: =AF105+AG106+U106 -> 101995973 | AG106: =SUM(E106:G106)+AI106-SUM(H106:S106)-AJ106+P106+Q106-(X106-X105)-(Y106-Y105)-(Z106-Z105)+(AA106-AA105)+(AB106-AB105)+(AC106-AC105)-T106+V106-W106 -> -13710191 | AH106: ='Revenue & Demand'!P270 -> 0 | AI106: ='Revenue & Demand'!Q270 -> 0 | AJ106: ='Manufacturing & Production'!J310 -> 0 | AK106: =A106 -> 46266 | AL106: =IF(B106<=2025,C106,"") | AM106: =IF(OR(B106>=2026,AND(B106=2025,MONTH(A106)=12)),C106,"") -> 6576
A107: 46296 | B107: =YEAR(A107) -> 2026 | C107: ='Revenue & Demand'!C37 -> 6612 | D107: ='Revenue & Demand'!D37 -> 76 | E107: ='Revenue & Demand'!F37 -> 9918000 | F107: ='Revenue & Demand'!G37 -> 2595441 | G107: ='Revenue & Demand'!H37 -> 205882 | H107: ='Manufacturing & Production'!F311 -> 2116305 | I107: ='Manufacturing & Production'!G311 -> 793440 | J107: ='Workforce & Expenses'!M363 -> 1206667 | K107: ='Manufacturing & Production'!K311 -> 16471 | L107: ='Clinical Trials & R&D'!F311 -> 6035000 | M107: ='Clinical Trials & R&D'!I311 -> 4139500 | N107: ='Workforce & Expenses'!P363 -> 3880000 | O107: ='Workforce & Expenses'!S363 -> 3586000 | P107: =ROUND(P95*IFERROR(SUM($P$86:$P$97)/SUM($P$74:$P$85),1),0) -> 1084071 | Q107: =ROUND(Q95*IFERROR(SUM($Q$86:$Q$97)/SUM($Q$74:$Q$85),1),0) -> 816666 | R107: =ROUND(AE107*IFERROR(SUM($R$86:$R$97)/AVERAGE($AE$85,$AE$97),0)/12,0) -> 687083 | S107: =0 -> 0 | T107: =MAX(0,ROUND(T95*IFERROR(SUM($T$86:$T$97)/SUM($T$74:$T$85),1),0)) -> 1502348 | U107: =0 -> 0 | V107: =0 -> 0 | W107: =0 -> 0 | X107: =ROUND(X95*IFERROR((SUM(E107:G107)+AI107)/(SUM(E95:G95)+AI95),1),0) -> 19028351 | Y107: =ROUND(Y95*IFERROR((SUM(H107:I107)+AJ107)/(SUM(H95:I95)+AJ95),1),0) -> 8100644 | Z107: =ROUND(Z95*IFERROR(SUM(E107:G107)/SUM(E95:G95),1),0) -> 7492844 | AA107: =ROUND(AA95*IFERROR((SUM(H107:K107)+AJ107+0.25*SUM(L107:M107))/(SUM(H95:K95)+AJ95+0.25*SUM(L95:M95)),1),0) -> 8877138 | AB107: =ROUND(AB95*IFERROR(SUM(L107:O107)/SUM(L95:O95),1),0) -> 20094395 | AC107: =ROUND(AC95*IFERROR(SUM(F107:G107)/SUM(F95:G95),1),0) -> 9201579 | AD107: =MIN(AE107,SUMIFS($W$2:$W$181,$A$2:$A$181,">"&A107,$A$2:$A$181,"<="&EDATE(A107,12))+IF(AND(DATE(2033,12,1)>A107,DATE(2033,12,1)<=EDATE(A107,12)),'Funding & Cap'!$B$200,0)) -> 0 | AE107: =SUM($V$2:V107)-SUM($W$2:W107) -> 97000000 | AF107: =AF106+AG107+U107 -> 91526755 | AG107: =SUM(E107:G107)+AI107-SUM(H107:S107)-AJ107+P107+Q107-(X107-X106)-(Y107-Y106)-(Z107-Z106)+(AA107-AA106)+(AB107-AB106)+(AC107-AC106)-T107+V107-W107 -> -10469218 | AH107: ='Revenue & Demand'!I37 -> 0 | AI107: ='Revenue & Demand'!K37 -> 0 | AJ107: ='Manufacturing & Production'!J311 -> 0 | AK107: =A107 -> 46296 | AL107: =IF(B107<=2025,C107,"") | AM107: =IF(OR(B107>=2026,AND(B107=2025,MONTH(A107)=12)),C107,"") -> 6612
A108: 46327 | B108: =YEAR(A108) -> 2026 | C108: ='Revenue & Demand'!C38 -> 6839 | D108: ='Revenue & Demand'!D38 -> 78 | E108: ='Revenue & Demand'!F38 -> 10258500 | F108: ='Revenue & Demand'!G38 -> 2704805 | G108: ='Revenue & Demand'!H38 -> 205882 | H108: ='Manufacturing & Production'!F312 -> 2134419 | I108: ='Manufacturing & Production'!G312 -> 820680 | J108: ='Workforce & Expenses'!M364 -> 1224667 | K108: ='Manufacturing & Production'!K312 -> 16471 | L108: ='Clinical Trials & R&D'!F312 -> 6035000 | M108: ='Clinical Trials & R&D'!I312 -> 4139500 | N108: ='Workforce & Expenses'!P364 -> 3880000 | O108: ='Workforce & Expenses'!S364 -> 3586000 | P108: =ROUND(P96*IFERROR(SUM($P$86:$P$97)/SUM($P$74:$P$85),1),0) -> 1102140 | Q108: =ROUND(Q96*IFERROR(SUM($Q$86:$Q$97)/SUM($Q$74:$Q$85),1),0) -> 816666 | R108: =ROUND(AE108*IFERROR(SUM($R$86:$R$97)/AVERAGE($AE$85,$AE$97),0)/12,0) -> 687083 | S108: =0 -> 0 | T108: =MAX(0,ROUND(T96*IFERROR(SUM($T$86:$T$97)/SUM($T$74:$T$85),1),0)) -> 1519040 | U108: =0 -> 0 | V108: =0 -> 0 | W108: =0 -> 0 | X108: =ROUND(X96*IFERROR((SUM(E108:G108)+AI108)/(SUM(E96:G96)+AI96),1),0) -> 20033858 | Y108: =ROUND(Y96*IFERROR((SUM(H108:I108)+AJ108)/(SUM(H96:I96)+AJ96),1),0) -> 8447530 | Z108: =ROUND(Z96*IFERROR(SUM(E108:G108)/SUM(E96:G96),1),0) -> 7860312 | AA108: =ROUND(AA96*IFERROR((SUM(H108:K108)+AJ108+0.25*SUM(L108:M108))/(SUM(H96:K96)+AJ96+0.25*SUM(L96:M96)),1),0) -> 8980797 | AB108: =ROUND(AB96*IFERROR(SUM(L108:O108)/SUM(L96:O96),1),0) -> 20086727 | AC108: =ROUND(AC96*IFERROR(SUM(F108:G108)/SUM(F96:G96),1),0) -> 9304629 | AD108: =MIN(AE108,SUMIFS($W$2:$W$181,$A$2:$A$181,">"&A108,$A$2:$A$181,"<="&EDATE(A108,12))+IF(AND(DATE(2033,12,1)>A108,DATE(2033,12,1)<=EDATE(A108,12)),'Funding & Cap'!$B$200,0)) -> 0 | AE108: =SUM($V$2:V108)-SUM($W$2:W108) -> 97000000 | AF108: =AF107+AG108+U108 -> 79132262 | AG108: =SUM(E108:G108)+AI108-SUM(H108:S108)-AJ108+P108+Q108-(X108-X107)-(Y108-Y107)-(Z108-Z107)+(AA108-AA107)+(AB108-AB107)+(AC108-AC107)-T108+V108-W108 -> -12394493 | AH108: ='Revenue & Demand'!I38 -> 0 | AI108: ='Revenue & Demand'!K38 -> 0 | AJ108: ='Manufacturing & Production'!J312 -> 0 | AK108: =A108 -> 46327 | AL108: =IF(B108<=2025,C108,"") | AM108: =IF(OR(B108>=2026,AND(B108=2025,MONTH(A108)=12)),C108,"") -> 6839
A109: 46357 | B109: =YEAR(A109) -> 2026 | C109: ='Revenue & Demand'!C39 -> 7074 | D109: ='Revenue & Demand'!D39 -> 80 | E109: ='Revenue & Demand'!F39 -> 10611000 | F109: ='Revenue & Demand'!G39 -> 2813370 | G109: ='Revenue & Demand'!H39 -> 1492649 | H109: ='Manufacturing & Production'!F313 -> 2153172 | I109: ='Manufacturing & Production'!G313 -> 848880 | J109: ='Workforce & Expenses'!M365 -> 1242667 | K109: ='Manufacturing & Production'!K313 -> 119412 | L109: ='Clinical Trials & R&D'!F313 -> 6035000 | M109: ='Clinical Trials & R&D'!I313 -> 4139500 | N109: ='Workforce & Expenses'!P365 -> 3880000 | O109: ='Workforce & Expenses'!S365 -> 3586000 | P109: =ROUND(P97*IFERROR(SUM($P$86:$P$97)/SUM($P$74:$P$85),1),0) -> 1120203 | Q109: =ROUND(Q97*IFERROR(SUM($Q$86:$Q$97)/SUM($Q$74:$Q$85),1),0) -> 816672 | R109: =ROUND(AE109*IFERROR(SUM($R$86:$R$97)/AVERAGE($AE$85,$AE$97),0)/12,0) -> 687083 | S109: =ROUND(0.25*MAX(0,SUM(E98:G109)+SUM(AI98:AI109)-SUM(H98:R109)-SUM(AJ98:AJ109)),0) -> 0 | T109: =MAX(0,ROUND(T97*IFERROR(SUM($T$86:$T$97)/SUM($T$74:$T$85),1),0)) -> 1535733 | U109: =0 -> 0 | V109: =0 -> 0 | W109: =0 -> 0 | X109: =ROUND(X97*IFERROR((SUM(E109:G109)+AI109)/(SUM(E97:G97)+AI97),1),0) -> 20294792 | Y109: =ROUND(Y97*IFERROR((SUM(H109:I109)+AJ109)/(SUM(H97:I97)+AJ97),1),0) -> 8812626 | Z109: =ROUND(Z97*IFERROR(SUM(E109:G109)/SUM(E97:G97),1),0) -> 7936713 | AA109: =ROUND(AA97*IFERROR((SUM(H109:K109)+AJ109+0.25*SUM(L109:M109))/(SUM(H97:K97)+AJ97+0.25*SUM(L97:M97)),1),0) -> 9043608 | AB109: =ROUND(AB97*IFERROR(SUM(L109:O109)/SUM(L97:O97),1),0) -> 20109630 | AC109: =ROUND(AC97*IFERROR(SUM(F109:G109)/SUM(F97:G97),1),0) -> 8526872 | AD109: =MIN(AE109,SUMIFS($W$2:$W$181,$A$2:$A$181,">"&A109,$A$2:$A$181,"<="&EDATE(A109,12))+IF(AND(DATE(2033,12,1)>A109,DATE(2033,12,1)<=EDATE(A109,12)),'Funding & Cap'!$B$200,0)) -> 15000000 | AE109: =SUM($V$2:V109)-SUM($W$2:W109) -> 97000000 | AF109: =AF108+AG109+U109 -> 68427360 | AG109: =SUM(E109:G109)+AI109-SUM(H109:S109)-AJ109+P109+Q109-(X109-X108)-(Y109-Y108)-(Z109-Z108)+(AA109-AA108)+(AB109-AB108)+(AC109-AC108)-T109+V109-W109 -> -10704902 | AH109: ='Revenue & Demand'!I39 -> 0 | AI109: ='Revenue & Demand'!K39 -> 0 | AJ109: ='Manufacturing & Production'!J313 -> 0 | AK109: =A109 -> 46357 | AL109: =IF(B109<=2025,C109,"") | AM109: =IF(OR(B109>=2026,AND(B109=2025,MONTH(A109)=12)),C109,"") -> 7074
A110: =EDATE(A98,12) -> 46388 | B110: =YEAR(A110) -> 2027 | C110: ='Revenue & Demand'!C40 -> 7230 | D110: ='Revenue & Demand'!D40 -> 77 | E110: ='Revenue & Demand'!F40 -> 10845000 | F110: ='Revenue & Demand'!G40 -> 3695961 | G110: ='Revenue & Demand'!H40 -> 205882 | H110: ='Manufacturing & Production'!F314 -> 2241644 | I110: ='Manufacturing & Production'!G314 -> 867600 | J110: ='Workforce & Expenses'!M366 -> 1252137 | K110: ='Manufacturing & Production'!K314 -> 16471 | L110: ='Clinical Trials & R&D'!F314 -> 6387477 | M110: ='Clinical Trials & R&D'!I314 -> 4383870 | N110: ='Workforce & Expenses'!P366 -> 4808240 | O110: ='Workforce & Expenses'!S366 -> 3816223 | P110: =ROUND(P98*(1+MIN(0.2,MAX(0,IFERROR(SUM($P$86:$P$97)/SUM($P$74:$P$85)-1,0)))),0) -> 1106490 | Q110: =ROUND(Q98*IFERROR(SUM($T$86:$T$97)/SUM($T$74:$T$85),1),0) -> 1088888 | R110: =ROUND(AE110*IFERROR(SUM($R$86:$R$97)/AVERAGE($AE$85,$AE$97),0)/12,0) -> 687083 | S110: =0 -> 0 | T110: =MAX(0,ROUND(T98*IFERROR(SUM($T$86:$T$97)/SUM($T$74:$T$85),1)+('Funding & Cap'!$F$10-'Funding & Cap'!$F$5)*'Funding & Cap'!$B$6/12,0)) -> 1770367 | U110: =IF(MONTH(A110)=2,'Funding & Cap'!$F$10,0) -> 0 | V110: =0 -> 0 | W110: =IF(MONTH(A110)=12,MIN(AE109,'Funding & Cap'!$F$9),0) -> 0 | X110: =ROUND(X98*IFERROR((SUM(E110:G110)+AI110)/(SUM(E98:G98)+AI98),1),0) -> 18477947 | Y110: =ROUND(Y98*IFERROR((SUM(H110:I110)+AJ110)/(SUM(H98:I98)+AJ98),1),0) -> 7431679 | Z110: =ROUND(Z98*IFERROR(SUM(E110:G110)/SUM(E98:G98),1),0) -> 7686310 | AA110: =ROUND(AA98*IFERROR((SUM(H110:K110)+AJ110+0.25*SUM(L110:M110))/(SUM(H98:K98)+AJ98+0.25*SUM(L98:M98)),1),0) -> 7541402 | AB110: =ROUND(AB98*IFERROR(SUM(L110:O110)/SUM(L98:O98),1),0) -> 17292598 | AC110: =ROUND(AC98*IFERROR(SUM(F110:G110)/SUM(F98:G98),1),0) -> 11533272 | AD110: =MIN(AE110,SUMIFS($W$2:$W$181,$A$2:$A$181,">"&A110,$A$2:$A$181,"<="&EDATE(A110,12))+IF(AND(DATE(2033,12,1)>A110,DATE(2033,12,1)<=EDATE(A110,12)),'Funding & Cap'!$B$200,0)) -> 15000000 | AE110: =SUM($V$2:V110)-SUM($W$2:W110) -> 97000000 | AF110: =AF109+AG110+U110 -> 59078448 | AG110: =SUM(E110:G110)+AI110-SUM(H110:S110)-AJ110+P110+Q110-(X110-X109)-(Y110-Y109)-(Z110-Z109)+(AA110-AA109)+(AB110-AB109)+(AC110-AC109)-T110+V110-W110 -> -9348912 | AH110: ='Revenue & Demand'!I40 -> 0 | AI110: ='Revenue & Demand'!K40 -> 0 | AJ110: ='Manufacturing & Production'!J314 -> 0 | AK110: =A110 -> 46388 | AL110: =IF(B110<=2025,C110,"") | AM110: =IF(OR(B110>=2026,AND(B110=2025,MONTH(A110)=12)),C110,"") -> 7230
A111: =EDATE(A99,12) -> 46419 | B111: =YEAR(A111) -> 2027 | C111: ='Revenue & Demand'!C41 -> 7390 | D111: ='Revenue & Demand'!D41 -> 79 | E111: ='Revenue & Demand'!F41 -> 11085000 | F111: ='Revenue & Demand'!G41 -> 3764202 | G111: ='Revenue & Demand'!H41 -> 205882 | H111: ='Manufacturing & Production'!F315 -> 2281954 | I111: ='Manufacturing & Production'!G315 -> 886800 | J111: ='Workforce & Expenses'!M367 -> 1284135 | K111: ='Manufacturing & Production'!K315 -> 16471 | L111: ='Clinical Trials & R&D'!F315 -> 6426891 | M111: ='Clinical Trials & R&D'!I315 -> 4383870 | N111: ='Workforce & Expenses'!P367 -> 4822660 | O111: ='Workforce & Expenses'!S367 -> 3819004 | P111: =ROUND(P99*(1+MIN(0.2,MAX(0,IFERROR(SUM($P$86:$P$97)/SUM($P$74:$P$85)-1,0)))),0) -> 1128937 | Q111: =ROUND(Q99*IFERROR(SUM($T$86:$T$97)/SUM($T$74:$T$85),1),0) -> 1088888 | R111: =ROUND(AE111*IFERROR(SUM($R$86:$R$97)/AVERAGE($AE$85,$AE$97),0)/12,0) -> 687083 | S111: =0 -> 0 | T111: =MAX(0,ROUND(T99*IFERROR(SUM($T$86:$T$97)/SUM($T$74:$T$85),1)+('Funding & Cap'!$F$10-'Funding & Cap'!$F$5)*'Funding & Cap'!$B$6/12,0)) -> 1825073 | U111: =IF(MONTH(A111)=2,'Funding & Cap'!$F$10,0) -> 200000000 | V111: =0 -> 0 | W111: =IF(MONTH(A111)=12,MIN(AE110,'Funding & Cap'!$F$9),0) -> 0 | X111: =ROUND(X99*IFERROR((SUM(E111:G111)+AI111)/(SUM(E99:G99)+AI99),1),0) -> 19814063 | Y111: =ROUND(Y99*IFERROR((SUM(H111:I111)+AJ111)/(SUM(H99:I99)+AJ99),1),0) -> 8122960 | Z111: =ROUND(Z99*IFERROR(SUM(E111:G111)/SUM(E99:G99),1),0) -> 8159269 | AA111: =ROUND(AA99*IFERROR((SUM(H111:K111)+AJ111+0.25*SUM(L111:M111))/(SUM(H99:K99)+AJ99+0.25*SUM(L99:M99)),1),0) -> 7921950 | AB111: =ROUND(AB99*IFERROR(SUM(L111:O111)/SUM(L99:O99),1),0) -> 17905369 | AC111: =ROUND(AC99*IFERROR(SUM(F111:G111)/SUM(F99:G99),1),0) -> 11753705 | AD111: =MIN(AE111,SUMIFS($W$2:$W$181,$A$2:$A$181,">"&A111,$A$2:$A$181,"<="&EDATE(A111,12))+IF(AND(DATE(2033,12,1)>A111,DATE(2033,12,1)<=EDATE(A111,12)),'Funding & Cap'!$B$200,0)) -> 15000000 | AE111: =SUM($V$2:V111)-SUM($W$2:W111) -> 97000000 | AF111: =AF110+AG111+U111 -> 246412987 | AG111: =SUM(E111:G111)+AI111-SUM(H111:S111)-AJ111+P111+Q111-(X111-X110)-(Y111-Y110)-(Z111-Z110)+(AA111-AA110)+(AB111-AB110)+(AC111-AC110)-T111+V111-W111 -> -12665461 | AH111: ='Revenue & Demand'!I41 -> 0 | AI111: ='Revenue & Demand'!K41 -> 0 | AJ111: ='Manufacturing & Production'!J315 -> 0 | AK111: =A111 -> 46419 | AL111: =IF(B111<=2025,C111,"") | AM111: =IF(OR(B111>=2026,AND(B111=2025,MONTH(A111)=12)),C111,"") -> 7390
A112: =EDATE(A100,12) -> 46447 | B112: =YEAR(A112) -> 2027 | C112: ='Revenue & Demand'!C42 -> 7554 | D112: ='Revenue & Demand'!D42 -> 82 | E112: ='Revenue & Demand'!F42 -> 11331000 | F112: ='Revenue & Demand'!G42 -> 3658014 | G112: ='Revenue & Demand'!H42 -> 1286765 | H112: ='Manufacturing & Production'!F316 -> 2306488 | I112: ='Manufacturing & Production'!G316 -> 906480 | J112: ='Workforce & Expenses'!M368 -> 1311945 | K112: ='Manufacturing & Production'!K316 -> 102941 | L112: ='Clinical Trials & R&D'!F316 -> 6445877 | M112: ='Clinical Trials & R&D'!I316 -> 4401895 | N112: ='Workforce & Expenses'!P368 -> 4851500 | O112: ='Workforce & Expenses'!S368 -> 3837647 | P112: =ROUND(P100*(1+MIN(0.2,MAX(0,IFERROR(SUM($P$86:$P$97)/SUM($P$74:$P$85)-1,0)))),0) -> 1151414 | Q112: =ROUND(Q100*IFERROR(SUM($T$86:$T$97)/SUM($T$74:$T$85),1),0) -> 1088888 | R112: =ROUND(AE112*IFERROR(SUM($R$86:$R$97)/AVERAGE($AE$85,$AE$97),0)/12,0) -> 687083 | S112: =0 -> 0 | T112: =MAX(0,ROUND(T100*IFERROR(SUM($T$86:$T$97)/SUM($T$74:$T$85),1)+('Funding & Cap'!$F$10-'Funding & Cap'!$F$5)*'Funding & Cap'!$B$6/12,0)) -> 4599497 | U112: =IF(MONTH(A112)=2,'Funding & Cap'!$F$10,0) -> 0 | V112: =0 -> 0 | W112: =IF(MONTH(A112)=12,MIN(AE111,'Funding & Cap'!$F$9),0) -> 0 | X112: =ROUND(X100*IFERROR((SUM(E112:G112)+AI112)/(SUM(E100:G100)+AI100),1),0) -> 19224673 | Y112: =ROUND(Y100*IFERROR((SUM(H112:I112)+AJ112)/(SUM(H100:I100)+AJ100),1),0) -> 8549669 | Z112: =ROUND(Z100*IFERROR(SUM(E112:G112)/SUM(E100:G100),1),0) -> 7850929 | AA112: =ROUND(AA100*IFERROR((SUM(H112:K112)+AJ112+0.25*SUM(L112:M112))/(SUM(H100:K100)+AJ100+0.25*SUM(L100:M100)),1),0) -> 8273674 | AB112: =ROUND(AB100*IFERROR(SUM(L112:O112)/SUM(L100:O100),1),0) -> 18677120 | AC112: =ROUND(AC100*IFERROR(SUM(F112:G112)/SUM(F100:G100),1),0) -> 9824023 | AD112: =MIN(AE112,SUMIFS($W$2:$W$181,$A$2:$A$181,">"&A112,$A$2:$A$181,"<="&EDATE(A112,12))+IF(AND(DATE(2033,12,1)>A112,DATE(2033,12,1)<=EDATE(A112,12)),'Funding & Cap'!$B$200,0)) -> 15000000 | AE112: =SUM($V$2:V112)-SUM($W$2:W112) -> 97000000 | AF112: =AF111+AG112+U112 -> 232902227 | AG112: =SUM(E112:G112)+AI112-SUM(H112:S112)-AJ112+P112+Q112-(X112-X111)-(Y112-Y111)-(Z112-Z111)+(AA112-AA111)+(AB112-AB111)+(AC112-AC111)-T112+V112-W112 -> -13510760 | AH112: ='Revenue & Demand'!I42 -> 0 | AI112: ='Revenue & Demand'!K42 -> 0 | AJ112: ='Manufacturing & Production'!J316 -> 0 | AK112: =A112 -> 46447 | AL112: =IF(B112<=2025,C112,"") | AM112: =IF(OR(B112>=2026,AND(B112=2025,MONTH(A112)=12)),C112,"") -> 7554
A113: =EDATE(A101,12) -> 46478 | B113: =YEAR(A113) -> 2027 | C113: ='Revenue & Demand'!C43 -> 7721 | D113: ='Revenue & Demand'!D43 -> 83 | E113: ='Revenue & Demand'!F43 -> 11581500 | F113: ='Revenue & Demand'!G43 -> 3663348 | G113: ='Revenue & Demand'!H43 -> 205882 | H113: ='Manufacturing & Production'!F317 -> 2320215 | I113: ='Manufacturing & Production'!G317 -> 926520 | J113: ='Workforce & Expenses'!M369 -> 1321215 | K113: ='Manufacturing & Production'!K317 -> 16471 | L113: ='Clinical Trials & R&D'!F317 -> 6466305 | M113: ='Clinical Trials & R&D'!I317 -> 4401895 | N113: ='Workforce & Expenses'!P369 -> 4865920 | O113: ='Workforce & Expenses'!S369 -> 3838574 | P113: =ROUND(P101*(1+MIN(0.2,MAX(0,IFERROR(SUM($P$86:$P$97)/SUM($P$74:$P$85)-1,0)))),0) -> 1173919 | Q113: =ROUND(Q101*IFERROR(SUM($T$86:$T$97)/SUM($T$74:$T$85),1),0) -> 1088888 | R113: =ROUND(AE113*IFERROR(SUM($R$86:$R$97)/AVERAGE($AE$85,$AE$97),0)/12,0) -> 687083 | S113: =0 -> 0 | T113: =MAX(0,ROUND(T101*IFERROR(SUM($T$86:$T$97)/SUM($T$74:$T$85),1)+('Funding & Cap'!$F$10-'Funding & Cap'!$F$5)*'Funding & Cap'!$B$6/12,0)) -> 1835936 | U113: =IF(MONTH(A113)=2,'Funding & Cap'!$F$10,0) -> 0 | V113: =0 -> 0 | W113: =IF(MONTH(A113)=12,MIN(AE112,'Funding & Cap'!$F$9),0) -> 0 | X113: =ROUND(X101*IFERROR((SUM(E113:G113)+AI113)/(SUM(E101:G101)+AI101),1),0) -> 22024766 | Y113: =ROUND(Y101*IFERROR((SUM(H113:I113)+AJ113)/(SUM(H101:I101)+AJ101),1),0) -> 8935708 | Z113: =ROUND(Z101*IFERROR(SUM(E113:G113)/SUM(E101:G101),1),0) -> 8931599 | AA113: =ROUND(AA101*IFERROR((SUM(H113:K113)+AJ113+0.25*SUM(L113:M113))/(SUM(H101:K101)+AJ101+0.25*SUM(L101:M101)),1),0) -> 8790928 | AB113: =ROUND(AB101*IFERROR(SUM(L113:O113)/SUM(L101:O101),1),0) -> 19514970 | AC113: =ROUND(AC101*IFERROR(SUM(F113:G113)/SUM(F101:G101),1),0) -> 11971835 | AD113: =MIN(AE113,SUMIFS($W$2:$W$181,$A$2:$A$181,">"&A113,$A$2:$A$181,"<="&EDATE(A113,12))+IF(AND(DATE(2033,12,1)>A113,DATE(2033,12,1)<=EDATE(A113,12)),'Funding & Cap'!$B$200,0)) -> 15000000 | AE113: =SUM($V$2:V113)-SUM($W$2:W113) -> 97000000 | AF113: =AF112+AG113+U113 -> 220908937 | AG113: =SUM(E113:G113)+AI113-SUM(H113:S113)-AJ113+P113+Q113-(X113-X112)-(Y113-Y112)-(Z113-Z112)+(AA113-AA112)+(AB113-AB112)+(AC113-AC112)-T113+V113-W113 -> -11993290 | AH113: ='Revenue & Demand'!I43 -> 0 | AI113: ='Revenue & Demand'!K43 -> 0 | AJ113: ='Manufacturing & Production'!J317 -> 0 | AK113: =A113 -> 46478 | AL113: =IF(B113<=2025,C113,"") | AM113: =IF(OR(B113>=2026,AND(B113=2025,MONTH(A113)=12)),C113,"") -> 7721
A114: =EDATE(A102,12) -> 46508 | B114: =YEAR(A114) -> 2027 | C114: ='Revenue & Demand'!C44 -> 7891 | D114: ='Revenue & Demand'!D44 -> 86 | E114: ='Revenue & Demand'!F44 -> 11836500 | F114: ='Revenue & Demand'!G44 -> 3538220 | G114: ='Revenue & Demand'!H44 -> 205882 | H114: ='Manufacturing & Production'!F318 -> 2345243 | I114: ='Manufacturing & Production'!G318 -> 946920 | J114: ='Workforce & Expenses'!M370 -> 1349025 | K114: ='Manufacturing & Production'!K318 -> 16471 | L114: ='Clinical Trials & R&D'!F318 -> 6485292 | M114: ='Clinical Trials & R&D'!I318 -> 4419920 | N114: ='Workforce & Expenses'!P370 -> 4894760 | O114: ='Workforce & Expenses'!S370 -> 3857217 | P114: =ROUND(P102*(1+MIN(0.2,MAX(0,IFERROR(SUM($P$86:$P$97)/SUM($P$74:$P$85)-1,0)))),0) -> 1196453 | Q114: =ROUND(Q102*IFERROR(SUM($T$86:$T$97)/SUM($T$74:$T$85),1),0) -> 1088888 | R114: =ROUND(AE114*IFERROR(SUM($R$86:$R$97)/AVERAGE($AE$85,$AE$97),0)/12,0) -> 687083 | S114: =0 -> 0 | T114: =MAX(0,ROUND(T102*IFERROR(SUM($T$86:$T$97)/SUM($T$74:$T$85),1)+('Funding & Cap'!$F$10-'Funding & Cap'!$F$5)*'Funding & Cap'!$B$6/12,0)) -> 1891845 | U114: =IF(MONTH(A114)=2,'Funding & Cap'!$F$10,0) -> 0 | V114: =0 -> 0 | W114: =IF(MONTH(A114)=12,MIN(AE113,'Funding & Cap'!$F$9),0) -> 0 | X114: =ROUND(X102*IFERROR((SUM(E114:G114)+AI114)/(SUM(E102:G102)+AI102),1),0) -> 22906415 | Y114: =ROUND(Y102*IFERROR((SUM(H114:I114)+AJ114)/(SUM(H102:I102)+AJ102),1),0) -> 9244370 | Z114: =ROUND(Z102*IFERROR(SUM(E114:G114)/SUM(E102:G102),1),0) -> 9232846 | AA114: =ROUND(AA102*IFERROR((SUM(H114:K114)+AJ114+0.25*SUM(L114:M114))/(SUM(H102:K102)+AJ102+0.25*SUM(L102:M102)),1),0) -> 9310104 | AB114: =ROUND(AB102*IFERROR(SUM(L114:O114)/SUM(L102:O102),1),0) -> 20460196 | AC114: =ROUND(AC102*IFERROR(SUM(F114:G114)/SUM(F102:G102),1),0) -> 11981331 | AD114: =MIN(AE114,SUMIFS($W$2:$W$181,$A$2:$A$181,">"&A114,$A$2:$A$181,"<="&EDATE(A114,12))+IF(AND(DATE(2033,12,1)>A114,DATE(2033,12,1)<=EDATE(A114,12)),'Funding & Cap'!$B$200,0)) -> 15000000 | AE114: =SUM($V$2:V114)-SUM($W$2:W114) -> 97000000 | AF114: =AF113+AG114+U114 -> 209578103 | AG114: =SUM(E114:G114)+AI114-SUM(H114:S114)-AJ114+P114+Q114-(X114-X113)-(Y114-Y113)-(Z114-Z113)+(AA114-AA113)+(AB114-AB113)+(AC114-AC113)-T114+V114-W114 -> -11330834 | AH114: ='Revenue & Demand'!I44 -> 0 | AI114: ='Revenue & Demand'!K44 -> 0 | AJ114: ='Manufacturing & Production'!J318 -> 0 | AK114: =A114 -> 46508 | AL114: =IF(B114<=2025,C114,"") | AM114: =IF(OR(B114>=2026,AND(B114=2025,MONTH(A114)=12)),C114,"") -> 7891
A115: =EDATE(A103,12) -> 46539 | B115: =YEAR(A115) -> 2027 | C115: ='Revenue & Demand'!C45 -> 8066 | D115: ='Revenue & Demand'!D45 -> 88 | E115: ='Revenue & Demand'!F45 -> 12099000 | F115: ='Revenue & Demand'!G45 -> 3257147 | G115: ='Revenue & Demand'!H45 -> 1286765 | H115: ='Manufacturing & Production'!F319 -> 2386785 | I115: ='Manufacturing & Production'!G319 -> 967920 | J115: ='Workforce & Expenses'!M371 -> 1381024 | K115: ='Manufacturing & Production'!K319 -> 102941 | L115: ='Clinical Trials & R&D'!F319 -> 6524707 | M115: ='Clinical Trials & R&D'!I319 -> 4437945 | N115: ='Workforce & Expenses'!P371 -> 4909180 | O115: ='Workforce & Expenses'!S371 -> 3860462 | P115: =ROUND(P103*(1+MIN(0.2,MAX(0,IFERROR(SUM($P$86:$P$97)/SUM($P$74:$P$85)-1,0)))),0) -> 1219015 | Q115: =ROUND(Q103*IFERROR(SUM($T$86:$T$97)/SUM($T$74:$T$85),1),0) -> 1088888 | R115: =ROUND(AE115*IFERROR(SUM($R$86:$R$97)/AVERAGE($AE$85,$AE$97),0)/12,0) -> 687083 | S115: =0 -> 0 | T115: =MAX(0,ROUND(T103*IFERROR(SUM($T$86:$T$97)/SUM($T$74:$T$85),1)+('Funding & Cap'!$F$10-'Funding & Cap'!$F$5)*'Funding & Cap'!$B$6/12,0)) -> 1948555 | U115: =IF(MONTH(A115)=2,'Funding & Cap'!$F$10,0) -> 0 | V115: =0 -> 0 | W115: =IF(MONTH(A115)=12,MIN(AE114,'Funding & Cap'!$F$9),0) -> 0 | X115: =ROUND(X103*IFERROR((SUM(E115:G115)+AI115)/(SUM(E103:G103)+AI103),1),0) -> 21781267 | Y115: =ROUND(Y103*IFERROR((SUM(H115:I115)+AJ115)/(SUM(H103:I103)+AJ103),1),0) -> 9575628 | Z115: =ROUND(Z103*IFERROR(SUM(E115:G115)/SUM(E103:G103),1),0) -> 8731745 | AA115: =ROUND(AA103*IFERROR((SUM(H115:K115)+AJ115+0.25*SUM(L115:M115))/(SUM(H103:K103)+AJ103+0.25*SUM(L103:M103)),1),0) -> 9662834 | AB115: =ROUND(AB103*IFERROR(SUM(L115:O115)/SUM(L103:O103),1),0) -> 21369263 | AC115: =ROUND(AC103*IFERROR(SUM(F115:G115)/SUM(F103:G103),1),0) -> 9661957 | AD115: =MIN(AE115,SUMIFS($W$2:$W$181,$A$2:$A$181,">"&A115,$A$2:$A$181,"<="&EDATE(A115,12))+IF(AND(DATE(2033,12,1)>A115,DATE(2033,12,1)<=EDATE(A115,12)),'Funding & Cap'!$B$200,0)) -> 15000000 | AE115: =SUM($V$2:V115)-SUM($W$2:W115) -> 97000000 | AF115: =AF114+AG115+U115 -> 199251827 | AG115: =SUM(E115:G115)+AI115-SUM(H115:S115)-AJ115+P115+Q115-(X115-X114)-(Y115-Y114)-(Z115-Z114)+(AA115-AA114)+(AB115-AB114)+(AC115-AC114)-T115+V115-W115 -> -10326276 | AH115: ='Revenue & Demand'!I45 -> 0 | AI115: ='Revenue & Demand'!K45 -> 0 | AJ115: ='Manufacturing & Production'!J319 -> 0 | AK115: =A115 -> 46539 | AL115: =IF(B115<=2025,C115,"") | AM115: =IF(OR(B115>=2026,AND(B115=2025,MONTH(A115)=12)),C115,"") -> 8066
A116: =EDATE(A104,12) -> 46569 | B116: =YEAR(A116) -> 2027 | C116: ='Revenue & Demand'!C46 -> 8244 | D116: ='Revenue & Demand'!D46 -> 89 | E116: ='Revenue & Demand'!F46 -> 12366000 | F116: ='Revenue & Demand'!G46 -> 3204049 | G116: ='Revenue & Demand'!H46 -> 205882 | H116: ='Manufacturing & Production'!F320 -> 2412472 | I116: ='Manufacturing & Production'!G320 -> 989280 | J116: ='Workforce & Expenses'!M372 -> 1390294 | K116: ='Manufacturing & Production'!K320 -> 16471 | L116: ='Clinical Trials & R&D'!F320 -> 4204048 | M116: ='Clinical Trials & R&D'!I320 -> 4437945 | N116: ='Workforce & Expenses'!P372 -> 5658020 | O116: ='Workforce & Expenses'!S372 -> 3878641 | P116: =ROUND(P104*(1+MIN(0.2,MAX(0,IFERROR(SUM($P$86:$P$97)/SUM($P$74:$P$85)-1,0)))),0) -> 1241609 | Q116: =ROUND(Q104*IFERROR(SUM($T$86:$T$97)/SUM($T$74:$T$85),1),0) -> 1088888 | R116: =ROUND(AE116*IFERROR(SUM($R$86:$R$97)/AVERAGE($AE$85,$AE$97),0)/12,0) -> 687083 | S116: =0 -> 0 | T116: =MAX(0,ROUND(T104*IFERROR(SUM($T$86:$T$97)/SUM($T$74:$T$85),1)+('Funding & Cap'!$F$10-'Funding & Cap'!$F$5)*'Funding & Cap'!$B$6/12,0)) -> 1901504 | U116: =IF(MONTH(A116)=2,'Funding & Cap'!$F$10,0) -> 0 | V116: =0 -> 0 | W116: =IF(MONTH(A116)=12,MIN(AE115,'Funding & Cap'!$F$9),0) -> 0 | X116: =ROUND(X104*IFERROR((SUM(E116:G116)+AI116)/(SUM(E104:G104)+AI104),1),0) -> 33536373 | Y116: =ROUND(Y104*IFERROR((SUM(H116:I116)+AJ116)/(SUM(H104:I104)+AJ104),1),0) -> 15250354 | Z116: =ROUND(Z104*IFERROR(SUM(E116:G116)/SUM(E104:G104),1),0) -> 9691417 | AA116: =ROUND(AA104*IFERROR((SUM(H116:K116)+AJ116+0.25*SUM(L116:M116))/(SUM(H104:K104)+AJ104+0.25*SUM(L104:M104)),1),0) -> 11883766 | AB116: =ROUND(AB104*IFERROR(SUM(L116:O116)/SUM(L104:O104),1),0) -> 20327256 | AC116: =ROUND(AC104*IFERROR(SUM(F116:G116)/SUM(F104:G104),1),0) -> 11513730 | AD116: =MIN(AE116,SUMIFS($W$2:$W$181,$A$2:$A$181,">"&A116,$A$2:$A$181,"<="&EDATE(A116,12))+IF(AND(DATE(2033,12,1)>A116,DATE(2033,12,1)<=EDATE(A116,12)),'Funding & Cap'!$B$200,0)) -> 15000000 | AE116: =SUM($V$2:V116)-SUM($W$2:W116) -> 97000000 | AF116: =AF115+AG116+U116 -> 178251554 | AG116: =SUM(E116:G116)+AI116-SUM(H116:S116)-AJ116+P116+Q116-(X116-X115)-(Y116-Y115)-(Z116-Z115)+(AA116-AA115)+(AB116-AB115)+(AC116-AC115)-T116+V116-W116 -> -21000273 | AH116: ='Revenue & Demand'!I46 -> 4000 | AI116: ='Revenue & Demand'!K46 -> 6000000 | AJ116: ='Manufacturing & Production'!J320 -> 1841640 | AK116: =A116 -> 46569 | AL116: =IF(B116<=2025,C116,"") | AM116: =IF(OR(B116>=2026,AND(B116=2025,MONTH(A116)=12)),C116,"") -> 8244
A117: =EDATE(A105,12) -> 46600 | B117: =YEAR(A117) -> 2027 | C117: ='Revenue & Demand'!C47 -> 8426 | D117: ='Revenue & Demand'!D47 -> 92 | E117: ='Revenue & Demand'!F47 -> 12639000 | F117: ='Revenue & Demand'!G47 -> 3141853 | G117: ='Revenue & Demand'!H47 -> 205882 | H117: ='Manufacturing & Production'!F321 -> 2438485 | I117: ='Manufacturing & Production'!G321 -> 1011120 | J117: ='Workforce & Expenses'!M373 -> 1418104 | K117: ='Manufacturing & Production'!K321 -> 16471 | L117: ='Clinical Trials & R&D'!F321 -> 4223035 | M117: ='Clinical Trials & R&D'!I321 -> 4455970 | N117: ='Workforce & Expenses'!P373 -> 4966840 | O117: ='Workforce & Expenses'!S373 -> 3880495 | P117: =ROUND(P105*(1+MIN(0.2,MAX(0,IFERROR(SUM($P$86:$P$97)/SUM($P$74:$P$85)-1,0)))),0) -> 1264229 | Q117: =ROUND(Q105*IFERROR(SUM($T$86:$T$97)/SUM($T$74:$T$85),1),0) -> 1088888 | R117: =ROUND(AE117*IFERROR(SUM($R$86:$R$97)/AVERAGE($AE$85,$AE$97),0)/12,0) -> 687083 | S117: =0 -> 0 | T117: =MAX(0,ROUND(T105*IFERROR(SUM($T$86:$T$97)/SUM($T$74:$T$85),1)+('Funding & Cap'!$F$10-'Funding & Cap'!$F$5)*'Funding & Cap'!$B$6/12,0)) -> 1958615 | U117: =IF(MONTH(A117)=2,'Funding & Cap'!$F$10,0) -> 0 | V117: =0 -> 0 | W117: =IF(MONTH(A117)=12,MIN(AE116,'Funding & Cap'!$F$9),0) -> 0 | X117: =ROUND(X105*IFERROR((SUM(E117:G117)+AI117)/(SUM(E105:G105)+AI105),1),0) -> 34658030 | Y117: =ROUND(Y105*IFERROR((SUM(H117:I117)+AJ117)/(SUM(H105:I105)+AJ105),1),0) -> 15680709 | Z117: =ROUND(Z105*IFERROR(SUM(E117:G117)/SUM(E105:G105),1),0) -> 9951295 | AA117: =ROUND(AA105*IFERROR((SUM(H117:K117)+AJ117+0.25*SUM(L117:M117))/(SUM(H105:K105)+AJ105+0.25*SUM(L105:M105)),1),0) -> 12287443 | AB117: =ROUND(AB105*IFERROR(SUM(L117:O117)/SUM(L105:O105),1),0) -> 20023442 | AC117: =ROUND(AC105*IFERROR(SUM(F117:G117)/SUM(F105:G105),1),0) -> 11372692 | AD117: =MIN(AE117,SUMIFS($W$2:$W$181,$A$2:$A$181,">"&A117,$A$2:$A$181,"<="&EDATE(A117,12))+IF(AND(DATE(2033,12,1)>A117,DATE(2033,12,1)<=EDATE(A117,12)),'Funding & Cap'!$B$200,0)) -> 15000000 | AE117: =SUM($V$2:V117)-SUM($W$2:W117) -> 97000000 | AF117: =AF116+AG117+U117 -> 171573623 | AG117: =SUM(E117:G117)+AI117-SUM(H117:S117)-AJ117+P117+Q117-(X117-X116)-(Y117-Y116)-(Z117-Z116)+(AA117-AA116)+(AB117-AB116)+(AC117-AC116)-T117+V117-W117 -> -6677931 | AH117: ='Revenue & Demand'!I47 -> 4080 | AI117: ='Revenue & Demand'!K47 -> 6120000 | AJ117: ='Manufacturing & Production'!J321 -> 1875383 | AK117: =A117 -> 46600 | AL117: =IF(B117<=2025,C117,"") | AM117: =IF(OR(B117>=2026,AND(B117=2025,MONTH(A117)=12)),C117,"") -> 8426
A118: =EDATE(A106,12) -> 46631 | B118: =YEAR(A118) -> 2027 | C118: ='Revenue & Demand'!C48 -> 8612 | D118: ='Revenue & Demand'!D48 -> 94 | E118: ='Revenue & Demand'!F48 -> 12918000 | F118: ='Revenue & Demand'!G48 -> 3181539 | G118: ='Revenue & Demand'!H48 -> 1286765 | H118: ='Manufacturing & Production'!F322 -> 2464828 | I118: ='Manufacturing & Production'!G322 -> 1033440 | J118: ='Workforce & Expenses'!M374 -> 1436644 | K118: ='Manufacturing & Production'!K322 -> 102941 | L118: ='Clinical Trials & R&D'!F322 -> 4262449 | M118: ='Clinical Trials & R&D'!I322 -> 4455970 | N118: ='Workforce & Expenses'!P374 -> 4996040 | O118: ='Workforce & Expenses'!S374 -> 3899138 | P118: =ROUND(P106*(1+MIN(0.2,MAX(0,IFERROR(SUM($P$86:$P$97)/SUM($P$74:$P$85)-1,0)))),0) -> 1286880 | Q118: =ROUND(Q106*IFERROR(SUM($T$86:$T$97)/SUM($T$74:$T$85),1),0) -> 1088888 | R118: =ROUND(AE118*IFERROR(SUM($R$86:$R$97)/AVERAGE($AE$85,$AE$97),0)/12,0) -> 687083 | S118: =0 -> 0 | T118: =MAX(0,ROUND(T106*IFERROR(SUM($T$86:$T$97)/SUM($T$74:$T$85),1)+('Funding & Cap'!$F$10-'Funding & Cap'!$F$5)*'Funding & Cap'!$B$6/12,0)) -> 4735443 | U118: =IF(MONTH(A118)=2,'Funding & Cap'!$F$10,0) -> 0 | V118: =0 -> 0 | W118: =IF(MONTH(A118)=12,MIN(AE117,'Funding & Cap'!$F$9),0) -> 0 | X118: =ROUND(X106*IFERROR((SUM(E118:G118)+AI118)/(SUM(E106:G106)+AI106),1),0) -> 33025252 | Y118: =ROUND(Y106*IFERROR((SUM(H118:I118)+AJ118)/(SUM(H106:I106)+AJ106),1),0) -> 16209199 | Z118: =ROUND(Z106*IFERROR(SUM(E118:G118)/SUM(E106:G106),1),0) -> 9606654 | AA118: =ROUND(AA106*IFERROR((SUM(H118:K118)+AJ118+0.25*SUM(L118:M118))/(SUM(H106:K106)+AJ106+0.25*SUM(L106:M106)),1),0) -> 12383133 | AB118: =ROUND(AB106*IFERROR(SUM(L118:O118)/SUM(L106:O106),1),0) -> 20340611 | AC118: =ROUND(AC106*IFERROR(SUM(F118:G118)/SUM(F106:G106),1),0) -> 9675673 | AD118: =MIN(AE118,SUMIFS($W$2:$W$181,$A$2:$A$181,">"&A118,$A$2:$A$181,"<="&EDATE(A118,12))+IF(AND(DATE(2033,12,1)>A118,DATE(2033,12,1)<=EDATE(A118,12)),'Funding & Cap'!$B$200,0)) -> 15000000 | AE118: =SUM($V$2:V118)-SUM($W$2:W118) -> 97000000 | AF118: =AF117+AG118+U118 -> 165383751 | AG118: =SUM(E118:G118)+AI118-SUM(H118:S118)-AJ118+P118+Q118-(X118-X117)-(Y118-Y117)-(Z118-Z117)+(AA118-AA117)+(AB118-AB117)+(AC118-AC117)-T118+V118-W118 -> -6189872 | AH118: ='Revenue & Demand'!I48 -> 4162 | AI118: ='Revenue & Demand'!K48 -> 6243000 | AJ118: ='Manufacturing & Production'!J322 -> 1909969 | AK118: =A118 -> 46631 | AL118: =IF(B118<=2025,C118,"") | AM118: =IF(OR(B118>=2026,AND(B118=2025,MONTH(A118)=12)),C118,"") -> 8612
A119: =EDATE(A107,12) -> 46661 | B119: =YEAR(A119) -> 2027 | C119: ='Revenue & Demand'!C49 -> 8803 | D119: ='Revenue & Demand'!D49 -> 94 | E119: ='Revenue & Demand'!F49 -> 13204500 | F119: ='Revenue & Demand'!G49 -> 3210151 | G119: ='Revenue & Demand'!H49 -> 205882 | H119: ='Manufacturing & Production'!F323 -> 2496630 | I119: ='Manufacturing & Production'!G323 -> 1056360 | J119: ='Workforce & Expenses'!M375 -> 1450103 | K119: ='Manufacturing & Production'!K323 -> 16471 | L119: ='Clinical Trials & R&D'!F323 -> 4262449 | M119: ='Clinical Trials & R&D'!I323 -> 4473995 | N119: ='Workforce & Expenses'!P375 -> 5010640 | O119: ='Workforce & Expenses'!S375 -> 3900992 | P119: =ROUND(P107*(1+MIN(0.2,MAX(0,IFERROR(SUM($P$86:$P$97)/SUM($P$74:$P$85)-1,0)))),0) -> 1300885 | Q119: =ROUND(Q107*IFERROR(SUM($T$86:$T$97)/SUM($T$74:$T$85),1),0) -> 1088888 | R119: =ROUND(AE119*IFERROR(SUM($R$86:$R$97)/AVERAGE($AE$85,$AE$97),0)/12,0) -> 687083 | S119: =0 -> 0 | T119: =MAX(0,ROUND(T107*IFERROR(SUM($T$86:$T$97)/SUM($T$74:$T$85),1)+('Funding & Cap'!$F$10-'Funding & Cap'!$F$5)*'Funding & Cap'!$B$6/12,0)) -> 2003131 | U119: =IF(MONTH(A119)=2,'Funding & Cap'!$F$10,0) -> 0 | V119: =0 -> 0 | W119: =IF(MONTH(A119)=12,MIN(AE118,'Funding & Cap'!$F$9),0) -> 0 | X119: =ROUND(X107*IFERROR((SUM(E119:G119)+AI119)/(SUM(E107:G107)+AI107),1),0) -> 34390538 | Y119: =ROUND(Y107*IFERROR((SUM(H119:I119)+AJ119)/(SUM(H107:I107)+AJ107),1),0) -> 15306180 | Z119: =ROUND(Z107*IFERROR(SUM(E119:G119)/SUM(E107:G107),1),0) -> 9791013 | AA119: =ROUND(AA107*IFERROR((SUM(H119:K119)+AJ119+0.25*SUM(L119:M119))/(SUM(H107:K107)+AJ107+0.25*SUM(L107:M107)),1),0) -> 12164122 | AB119: =ROUND(AB107*IFERROR(SUM(L119:O119)/SUM(L107:O107),1),0) -> 20103025 | AC119: =ROUND(AC107*IFERROR(SUM(F119:G119)/SUM(F107:G107),1),0) -> 11220733 | AD119: =MIN(AE119,SUMIFS($W$2:$W$181,$A$2:$A$181,">"&A119,$A$2:$A$181,"<="&EDATE(A119,12))+IF(AND(DATE(2033,12,1)>A119,DATE(2033,12,1)<=EDATE(A119,12)),'Funding & Cap'!$B$200,0)) -> 15000000 | AE119: =SUM($V$2:V119)-SUM($W$2:W119) -> 97000000 | AF119: =AF118+AG119+U119 -> 161510789 | AG119: =SUM(E119:G119)+AI119-SUM(H119:S119)-AJ119+P119+Q119-(X119-X118)-(Y119-Y118)-(Z119-Z118)+(AA119-AA118)+(AB119-AB118)+(AC119-AC118)-T119+V119-W119 -> -3872962 | AH119: ='Revenue & Demand'!I49 -> 4245 | AI119: ='Revenue & Demand'!K49 -> 6367500 | AJ119: ='Manufacturing & Production'!J323 -> 1944978 | AK119: =A119 -> 46661 | AL119: =IF(B119<=2025,C119,"") | AM119: =IF(OR(B119>=2026,AND(B119=2025,MONTH(A119)=12)),C119,"") -> 8803
A120: =EDATE(A108,12) -> 46692 | B120: =YEAR(A120) -> 2027 | C120: ='Revenue & Demand'!C50 -> 8997 | D120: ='Revenue & Demand'!D50 -> 96 | E120: ='Revenue & Demand'!F50 -> 13495500 | F120: ='Revenue & Demand'!G50 -> 3328991 | G120: ='Revenue & Demand'!H50 -> 205882 | H120: ='Manufacturing & Production'!F324 -> 2523631 | I120: ='Manufacturing & Production'!G324 -> 1079640 | J120: ='Workforce & Expenses'!M376 -> 1468643 | K120: ='Manufacturing & Production'!K324 -> 16471 | L120: ='Clinical Trials & R&D'!F324 -> 4301863 | M120: ='Clinical Trials & R&D'!I324 -> 4473995 | N120: ='Workforce & Expenses'!P376 -> 5039840 | O120: ='Workforce & Expenses'!S376 -> 3919635 | P120: =ROUND(P108*(1+MIN(0.2,MAX(0,IFERROR(SUM($P$86:$P$97)/SUM($P$74:$P$85)-1,0)))),0) -> 1322568 | Q120: =ROUND(Q108*IFERROR(SUM($T$86:$T$97)/SUM($T$74:$T$85),1),0) -> 1088888 | R120: =ROUND(AE120*IFERROR(SUM($R$86:$R$97)/AVERAGE($AE$85,$AE$97),0)/12,0) -> 687083 | S120: =0 -> 0 | T120: =MAX(0,ROUND(T108*IFERROR(SUM($T$86:$T$97)/SUM($T$74:$T$85),1)+('Funding & Cap'!$F$10-'Funding & Cap'!$F$5)*'Funding & Cap'!$B$6/12,0)) -> 2025387 | U120: =IF(MONTH(A120)=2,'Funding & Cap'!$F$10,0) -> 0 | V120: =0 -> 0 | W120: =IF(MONTH(A120)=12,MIN(AE119,'Funding & Cap'!$F$9),0) -> 0 | X120: =ROUND(X108*IFERROR((SUM(E120:G120)+AI120)/(SUM(E108:G108)+AI108),1),0) -> 35788389 | Y120: =ROUND(Y108*IFERROR((SUM(H120:I120)+AJ120)/(SUM(H108:I108)+AJ108),1),0) -> 15962870 | Z120: =ROUND(Z108*IFERROR(SUM(E120:G120)/SUM(E108:G108),1),0) -> 10164944 | AA120: =ROUND(AA108*IFERROR((SUM(H120:K120)+AJ120+0.25*SUM(L120:M120))/(SUM(H108:K108)+AJ108+0.25*SUM(L108:M108)),1),0) -> 12343092 | AB120: =ROUND(AB108*IFERROR(SUM(L120:O120)/SUM(L108:O108),1),0) -> 20194711 | AC120: =ROUND(AC108*IFERROR(SUM(F120:G120)/SUM(F108:G108),1),0) -> 11299972 | AD120: =MIN(AE120,SUMIFS($W$2:$W$181,$A$2:$A$181,">"&A120,$A$2:$A$181,"<="&EDATE(A120,12))+IF(AND(DATE(2033,12,1)>A120,DATE(2033,12,1)<=EDATE(A120,12)),'Funding & Cap'!$B$200,0)) -> 15000000 | AE120: =SUM($V$2:V120)-SUM($W$2:W120) -> 97000000 | AF120: =AF119+AG120+U120 -> 155440567 | AG120: =SUM(E120:G120)+AI120-SUM(H120:S120)-AJ120+P120+Q120-(X120-X119)-(Y120-Y119)-(Z120-Z119)+(AA120-AA119)+(AB120-AB119)+(AC120-AC119)-T120+V120-W120 -> -6070222 | AH120: ='Revenue & Demand'!I50 -> 4330 | AI120: ='Revenue & Demand'!K50 -> 6495000 | AJ120: ='Manufacturing & Production'!J324 -> 1980830 | AK120: =A120 -> 46692 | AL120: =IF(B120<=2025,C120,"") | AM120: =IF(OR(B120>=2026,AND(B120=2025,MONTH(A120)=12)),C120,"") -> 8997
A121: =EDATE(A109,12) -> 46722 | B121: =YEAR(A121) -> 2027 | C121: ='Revenue & Demand'!C51 -> 9196 | D121: ='Revenue & Demand'!D51 -> 98 | E121: ='Revenue & Demand'!F51 -> 13794000 | F121: ='Revenue & Demand'!G51 -> 3446378 | G121: ='Revenue & Demand'!H51 -> 1492649 | H121: ='Manufacturing & Production'!F325 -> 2551043 | I121: ='Manufacturing & Production'!G325 -> 1103520 | J121: ='Workforce & Expenses'!M377 -> 1487183 | K121: ='Manufacturing & Production'!K325 -> 119412 | L121: ='Clinical Trials & R&D'!F325 -> 4320850 | M121: ='Clinical Trials & R&D'!I325 -> 4492020 | N121: ='Workforce & Expenses'!P377 -> 5054440 | O121: ='Workforce & Expenses'!S377 -> 3921489 | P121: =ROUND(P109*(1+MIN(0.2,MAX(0,IFERROR(SUM($P$86:$P$97)/SUM($P$74:$P$85)-1,0)))),0) -> 1344244 | Q121: =ROUND(Q109*IFERROR(SUM($T$86:$T$97)/SUM($T$74:$T$85),1),0) -> 1088896 | R121: =ROUND(AE121*IFERROR(SUM($R$86:$R$97)/AVERAGE($AE$85,$AE$97),0)/12,0) -> 580833 | S121: =ROUND(0.25*MAX(0,SUM(E110:G121)+SUM(AI110:AI121)-SUM(H110:R121)-SUM(AJ110:AJ121)),0) -> 0 | T121: =MAX(0,ROUND(T109*IFERROR(SUM($T$86:$T$97)/SUM($T$74:$T$85),1)+('Funding & Cap'!$F$10-'Funding & Cap'!$F$5)*'Funding & Cap'!$B$6/12,0)) -> 2047644 | U121: =IF(MONTH(A121)=2,'Funding & Cap'!$F$10,0) -> 0 | V121: =0 -> 0 | W121: =IF(MONTH(A121)=12,MIN(AE120,'Funding & Cap'!$F$9),0) -> 15000000 | X121: =ROUND(X109*IFERROR((SUM(E121:G121)+AI121)/(SUM(E109:G109)+AI109),1),0) -> 34498554 | Y121: =ROUND(Y109*IFERROR((SUM(H121:I121)+AJ121)/(SUM(H109:I109)+AJ109),1),0) -> 16649366 | Z121: =ROUND(Z109*IFERROR(SUM(E121:G121)/SUM(E109:G109),1),0) -> 9967049 | AA121: =ROUND(AA109*IFERROR((SUM(H121:K121)+AJ121+0.25*SUM(L121:M121))/(SUM(H109:K109)+AJ109+0.25*SUM(L109:M109)),1),0) -> 12413114 | AB121: =ROUND(AB109*IFERROR(SUM(L121:O121)/SUM(L109:O109),1),0) -> 20278686 | AC121: =ROUND(AC109*IFERROR(SUM(F121:G121)/SUM(F109:G109),1),0) -> 9780368 | AD121: =MIN(AE121,SUMIFS($W$2:$W$181,$A$2:$A$181,">"&A121,$A$2:$A$181,"<="&EDATE(A121,12))+IF(AND(DATE(2033,12,1)>A121,DATE(2033,12,1)<=EDATE(A121,12)),'Funding & Cap'!$B$200,0)) -> 15000000 | AE121: =SUM($V$2:V121)-SUM($W$2:W121) -> 82000000 | AF121: =AF120+AG121+U121 -> 137537685 | AG121: =SUM(E121:G121)+AI121-SUM(H121:S121)-AJ121+P121+Q121-(X121-X120)-(Y121-Y120)-(Z121-Z120)+(AA121-AA120)+(AB121-AB120)+(AC121-AC120)-T121+V121-W121 -> -17902882 | AH121: ='Revenue & Demand'!I51 -> 4416 | AI121: ='Revenue & Demand'!K51 -> 6624000 | AJ121: ='Manufacturing & Production'!J325 -> 2017102 | AK121: =A121 -> 46722 | AL121: =IF(B121<=2025,C121,"") | AM121: =IF(OR(B121>=2026,AND(B121=2025,MONTH(A121)=12)),C121,"") -> 9196
A122: =EDATE(A110,12) -> 46753 | B122: =YEAR(A122) -> 2028 | C122: ='Revenue & Demand'!C52 -> 9337 | D122: ='Revenue & Demand'!D52 -> 91 | E122: ='Revenue & Demand'!F52 -> 14005500 | F122: ='Revenue & Demand'!G52 -> 4367954 | G122: ='Revenue & Demand'!H52 -> 205882 | H122: ='Manufacturing & Production'!F326 -> 2650897 | I122: ='Manufacturing & Production'!G326 -> 1120440 | J122: ='Workforce & Expenses'!M378 -> 1464961 | K122: ='Manufacturing & Production'!K326 -> 16471 | L122: ='Clinical Trials & R&D'!F326 -> 4491074 | M122: ='Clinical Trials & R&D'!I326 -> 4728484 | N122: ='Workforce & Expenses'!P378 -> 6253754 | O122: ='Workforce & Expenses'!S378 -> 4170093 | P122: =ROUND(P110*(1+MIN(0.2,MAX(0,IFERROR(SUM($P$86:$P$97)/SUM($P$74:$P$85)-1,0)))),0) -> 1327788 | Q122: =ROUND(Q110*IFERROR(SUM($T$86:$T$97)/SUM($T$74:$T$85),1),0) -> 1451851 | R122: =ROUND(AE122*IFERROR(SUM($R$86:$R$97)/AVERAGE($AE$85,$AE$97),0)/12,0) -> 580833 | S122: =0 -> 0 | T122: =MAX(0,ROUND(T110*IFERROR(SUM($T$86:$T$97)/SUM($T$74:$T$85),1)+('Funding & Cap'!$G$10-'Funding & Cap'!$G$5)*'Funding & Cap'!$B$6/12,0)) -> 2360489 | U122: =IF(MONTH(A122)=IF('Funding & Cap'!$N$4="IPO in 2028",'Funding & Cap'!$N$8,2),'Funding & Cap'!$G$10,0) -> 0 | V122: =0 -> 0 | W122: =IF(MONTH(A122)=12,MIN(AE121,'Funding & Cap'!$G$9),0) -> 0 | X122: =ROUND(X110*IFERROR((SUM(E122:G122)+AI122)/(SUM(E110:G110)+AI110),1),0) -> 31747318 | Y122: =ROUND(Y110*IFERROR((SUM(H122:I122)+AJ122)/(SUM(H110:I110)+AJ110),1),0) -> 14072514 | Z122: =ROUND(Z110*IFERROR(SUM(E122:G122)/SUM(E110:G110),1),0) -> 9683872 | AA122: =ROUND(AA110*IFERROR((SUM(H122:K122)+AJ122+0.25*SUM(L122:M122))/(SUM(H110:K110)+AJ110+0.25*SUM(L110:M110)),1),0) -> 10317957 | AB122: =ROUND(AB110*IFERROR(SUM(L122:O122)/SUM(L110:O110),1),0) -> 17513345 | AC122: =ROUND(AC110*IFERROR(SUM(F122:G122)/SUM(F110:G110),1),0) -> 13519584 | AD122: =MIN(AE122,SUMIFS($W$2:$W$181,$A$2:$A$181,">"&A122,$A$2:$A$181,"<="&EDATE(A122,12))+IF(AND(DATE(2033,12,1)>A122,DATE(2033,12,1)<=EDATE(A122,12)),'Funding & Cap'!$B$200,0)) -> 15000000 | AE122: =SUM($V$2:V122)-SUM($W$2:W122) -> 82000000 | AF122: =AF121+AG122+U122 -> 137410728 | AG122: =SUM(E122:G122)+AI122-SUM(H122:S122)-AJ122+P122+Q122-(X122-X121)-(Y122-Y121)-(Z122-Z121)+(AA122-AA121)+(AB122-AB121)+(AC122-AC121)-T122+V122-W122 -> -126957 | AH122: ='Revenue & Demand'!I52 -> 4505 | AI122: ='Revenue & Demand'!K52 -> 6757500 | AJ122: ='Manufacturing & Production'!J326 -> 2116280 | AK122: =A122 -> 46753 | AL122: =IF(B122<=2025,C122,"") | AM122: =IF(OR(B122>=2026,AND(B122=2025,MONTH(A122)=12)),C122,"") -> 9337
A123: =EDATE(A111,12) -> 46784 | B123: =YEAR(A123) -> 2028 | C123: ='Revenue & Demand'!C53 -> 9480 | D123: ='Revenue & Demand'!D53 -> 93 | E123: ='Revenue & Demand'!F53 -> 14220000 | F123: ='Revenue & Demand'!G53 -> 4431276 | G123: ='Revenue & Demand'!H53 -> 205882 | H123: ='Manufacturing & Production'!F327 -> 2702365 | I123: ='Manufacturing & Production'!G327 -> 1137600 | J123: ='Workforce & Expenses'!M379 -> 1497920 | K123: ='Manufacturing & Production'!K327 -> 16471 | L123: ='Clinical Trials & R&D'!F327 -> 4491074 | M123: ='Clinical Trials & R&D'!I327 -> 4747050 | N123: ='Workforce & Expenses'!P379 -> 6283639 | O123: ='Workforce & Expenses'!S379 -> 4173435 | P123: =ROUND(P111*(1+MIN(0.2,MAX(0,IFERROR(SUM($P$86:$P$97)/SUM($P$74:$P$85)-1,0)))),0) -> 1354724 | Q123: =ROUND(Q111*IFERROR(SUM($T$86:$T$97)/SUM($T$74:$T$85),1),0) -> 1451851 | R123: =ROUND(AE123*IFERROR(SUM($R$86:$R$97)/AVERAGE($AE$85,$AE$97),0)/12,0) -> 580833 | S123: =0 -> 0 | T123: =MAX(0,ROUND(T111*IFERROR(SUM($T$86:$T$97)/SUM($T$74:$T$85),1)+('Funding & Cap'!$G$10-'Funding & Cap'!$G$5)*'Funding & Cap'!$B$6/12,0)) -> 2433431 | U123: =IF(MONTH(A123)=IF('Funding & Cap'!$N$4="IPO in 2028",'Funding & Cap'!$N$8,2),'Funding & Cap'!$G$10,0) -> 225000000 | V123: =0 -> 0 | W123: =IF(MONTH(A123)=12,MIN(AE122,'Funding & Cap'!$G$9),0) -> 0 | X123: =ROUND(X111*IFERROR((SUM(E123:G123)+AI123)/(SUM(E111:G111)+AI111),1),0) -> 33889239 | Y123: =ROUND(Y111*IFERROR((SUM(H123:I123)+AJ123)/(SUM(H111:I111)+AJ111),1),0) -> 15368800 | Z123: =ROUND(Z111*IFERROR(SUM(E123:G123)/SUM(E111:G111),1),0) -> 10219845 | AA123: =ROUND(AA111*IFERROR((SUM(H123:K123)+AJ123+0.25*SUM(L123:M123))/(SUM(H111:K111)+AJ111+0.25*SUM(L111:M111)),1),0) -> 10845956 | AB123: =ROUND(AB111*IFERROR(SUM(L123:O123)/SUM(L111:O111),1),0) -> 18128834 | AC123: =ROUND(AC111*IFERROR(SUM(F123:G123)/SUM(F111:G111),1),0) -> 13728623 | AD123: =MIN(AE123,SUMIFS($W$2:$W$181,$A$2:$A$181,">"&A123,$A$2:$A$181,"<="&EDATE(A123,12))+IF(AND(DATE(2033,12,1)>A123,DATE(2033,12,1)<=EDATE(A123,12)),'Funding & Cap'!$B$200,0)) -> 15000000 | AE123: =SUM($V$2:V123)-SUM($W$2:W123) -> 82000000 | AF123: =AF122+AG123+U123 -> 355319535 | AG123: =SUM(E123:G123)+AI123-SUM(H123:S123)-AJ123+P123+Q123-(X123-X122)-(Y123-Y122)-(Z123-Z122)+(AA123-AA122)+(AB123-AB122)+(AC123-AC122)-T123+V123-W123 -> -7091193 | AH123: ='Revenue & Demand'!I53 -> 4595 | AI123: ='Revenue & Demand'!K53 -> 6892500 | AJ123: ='Manufacturing & Production'!J327 -> 2155380 | AK123: =A123 -> 46784 | AL123: =IF(B123<=2025,C123,"") | AM123: =IF(OR(B123>=2026,AND(B123=2025,MONTH(A123)=12)),C123,"") -> 9480
A124: =EDATE(A112,12) -> 46813 | B124: =YEAR(A124) -> 2028 | C124: ='Revenue & Demand'!C54 -> 9625 | D124: ='Revenue & Demand'!D54 -> 96 | E124: ='Revenue & Demand'!F54 -> 14437500 | F124: ='Revenue & Demand'!G54 -> 4282553 | G124: ='Revenue & Demand'!H54 -> 1286765 | H124: ='Manufacturing & Production'!F328 -> 2726026 | I124: ='Manufacturing & Production'!G328 -> 1155000 | J124: ='Workforce & Expenses'!M380 -> 1526565 | K124: ='Manufacturing & Production'!K328 -> 102941 | L124: ='Clinical Trials & R&D'!F328 -> 4531671 | M124: ='Clinical Trials & R&D'!I328 -> 4747050 | N124: ='Workforce & Expenses'!P380 -> 6313704 | O124: ='Workforce & Expenses'!S380 -> 4192638 | P124: =ROUND(P112*(1+MIN(0.2,MAX(0,IFERROR(SUM($P$86:$P$97)/SUM($P$74:$P$85)-1,0)))),0) -> 1381697 | Q124: =ROUND(Q112*IFERROR(SUM($T$86:$T$97)/SUM($T$74:$T$85),1),0) -> 1451851 | R124: =ROUND(AE124*IFERROR(SUM($R$86:$R$97)/AVERAGE($AE$85,$AE$97),0)/12,0) -> 580833 | S124: =0 -> 0 | T124: =MAX(0,ROUND(T112*IFERROR(SUM($T$86:$T$97)/SUM($T$74:$T$85),1)+('Funding & Cap'!$G$10-'Funding & Cap'!$G$5)*'Funding & Cap'!$B$6/12,0)) -> 6132663 | U124: =IF(MONTH(A124)=IF('Funding & Cap'!$N$4="IPO in 2028",'Funding & Cap'!$N$8,2),'Funding & Cap'!$G$10,0) -> 0 | V124: =0 -> 0 | W124: =IF(MONTH(A124)=12,MIN(AE123,'Funding & Cap'!$G$9),0) -> 0 | X124: =ROUND(X112*IFERROR((SUM(E124:G124)+AI124)/(SUM(E112:G112)+AI112),1),0) -> 31936020 | Y124: =ROUND(Y112*IFERROR((SUM(H124:I124)+AJ124)/(SUM(H112:I112)+AJ112),1),0) -> 16169160 | Z124: =ROUND(Z112*IFERROR(SUM(E124:G124)/SUM(E112:G112),1),0) -> 9650666 | AA124: =ROUND(AA112*IFERROR((SUM(H124:K124)+AJ124+0.25*SUM(L124:M124))/(SUM(H112:K112)+AJ112+0.25*SUM(L112:M112)),1),0) -> 11301161 | AB124: =ROUND(AB112*IFERROR(SUM(L124:O124)/SUM(L112:O112),1),0) -> 18914343 | AC124: =ROUND(AC112*IFERROR(SUM(F124:G124)/SUM(F112:G112),1),0) -> 11064824 | AD124: =MIN(AE124,SUMIFS($W$2:$W$181,$A$2:$A$181,">"&A124,$A$2:$A$181,"<="&EDATE(A124,12))+IF(AND(DATE(2033,12,1)>A124,DATE(2033,12,1)<=EDATE(A124,12)),'Funding & Cap'!$B$200,0)) -> 15000000 | AE124: =SUM($V$2:V124)-SUM($W$2:W124) -> 82000000 | AF124: =AF123+AG124+U124 -> 348451366 | AG124: =SUM(E124:G124)+AI124-SUM(H124:S124)-AJ124+P124+Q124-(X124-X123)-(Y124-Y123)-(Z124-Z123)+(AA124-AA123)+(AB124-AB123)+(AC124-AC123)-T124+V124-W124 -> -6868169 | AH124: ='Revenue & Demand'!I54 -> 4687 | AI124: ='Revenue & Demand'!K54 -> 7030500 | AJ124: ='Manufacturing & Production'!J328 -> 2195349 | AK124: =A124 -> 46813 | AL124: =IF(B124<=2025,C124,"") | AM124: =IF(OR(B124>=2026,AND(B124=2025,MONTH(A124)=12)),C124,"") -> 9625
A125: =EDATE(A113,12) -> 46844 | B125: =YEAR(A125) -> 2028 | C125: ='Revenue & Demand'!C55 -> 9772 | D125: ='Revenue & Demand'!D55 -> 97 | E125: ='Revenue & Demand'!F55 -> 14658000 | F125: ='Revenue & Demand'!G55 -> 4281262 | G125: ='Revenue & Demand'!H55 -> 205882 | H125: ='Manufacturing & Production'!F329 -> 2749858 | I125: ='Manufacturing & Production'!G329 -> 1172640 | J125: ='Workforce & Expenses'!M381 -> 1536113 | K125: ='Manufacturing & Production'!K329 -> 16471 | L125: ='Clinical Trials & R&D'!F329 -> 4531671 | M125: ='Clinical Trials & R&D'!I329 -> 4765615 | N125: ='Workforce & Expenses'!P381 -> 6328737 | O125: ='Workforce & Expenses'!S381 -> 4194070 | P125: =ROUND(P113*(1+MIN(0.2,MAX(0,IFERROR(SUM($P$86:$P$97)/SUM($P$74:$P$85)-1,0)))),0) -> 1408703 | Q125: =ROUND(Q113*IFERROR(SUM($T$86:$T$97)/SUM($T$74:$T$85),1),0) -> 1451851 | R125: =ROUND(AE125*IFERROR(SUM($R$86:$R$97)/AVERAGE($AE$85,$AE$97),0)/12,0) -> 580833 | S125: =0 -> 0 | T125: =MAX(0,ROUND(T113*IFERROR(SUM($T$86:$T$97)/SUM($T$74:$T$85),1)+('Funding & Cap'!$G$10-'Funding & Cap'!$G$5)*'Funding & Cap'!$B$6/12,0)) -> 2447915 | U125: =IF(MONTH(A125)=IF('Funding & Cap'!$N$4="IPO in 2028",'Funding & Cap'!$N$8,2),'Funding & Cap'!$G$10,0) -> 0 | V125: =0 -> 0 | W125: =IF(MONTH(A125)=12,MIN(AE124,'Funding & Cap'!$G$9),0) -> 0 | X125: =ROUND(X113*IFERROR((SUM(E125:G125)+AI125)/(SUM(E113:G113)+AI113),1),0) -> 37511813 | Y125: =ROUND(Y113*IFERROR((SUM(H125:I125)+AJ125)/(SUM(H113:I113)+AJ113),1),0) -> 16948822 | Z125: =ROUND(Z113*IFERROR(SUM(E125:G125)/SUM(E113:G113),1),0) -> 11067228 | AA125: =ROUND(AA113*IFERROR((SUM(H125:K125)+AJ125+0.25*SUM(L125:M125))/(SUM(H113:K113)+AJ113+0.25*SUM(L113:M113)),1),0) -> 12082269 | AB125: =ROUND(AB113*IFERROR(SUM(L125:O125)/SUM(L113:O113),1),0) -> 19761639 | AC125: =ROUND(AC113*IFERROR(SUM(F125:G125)/SUM(F113:G113),1),0) -> 13883731 | AD125: =MIN(AE125,SUMIFS($W$2:$W$181,$A$2:$A$181,">"&A125,$A$2:$A$181,"<="&EDATE(A125,12))+IF(AND(DATE(2033,12,1)>A125,DATE(2033,12,1)<=EDATE(A125,12)),'Funding & Cap'!$B$200,0)) -> 15000000 | AE125: =SUM($V$2:V125)-SUM($W$2:W125) -> 82000000 | AF125: =AF124+AG125+U125 -> 340882128 | AG125: =SUM(E125:G125)+AI125-SUM(H125:S125)-AJ125+P125+Q125-(X125-X124)-(Y125-Y124)-(Z125-Z124)+(AA125-AA124)+(AB125-AB124)+(AC125-AC124)-T125+V125-W125 -> -7569238 | AH125: ='Revenue & Demand'!I55 -> 4780 | AI125: ='Revenue & Demand'!K55 -> 7170000 | AJ125: ='Manufacturing & Production'!J329 -> 2235753 | AK125: =A125 -> 46844 | AL125: =IF(B125<=2025,C125,"") | AM125: =IF(OR(B125>=2026,AND(B125=2025,MONTH(A125)=12)),C125,"") -> 9772
A126: =EDATE(A114,12) -> 46874 | B126: =YEAR(A126) -> 2028 | C126: ='Revenue & Demand'!C56 -> 9922 | D126: ='Revenue & Demand'!D56 -> 100 | E126: ='Revenue & Demand'!F56 -> 14883000 | F126: ='Revenue & Demand'!G56 -> 4114209 | G126: ='Revenue & Demand'!H56 -> 205882 | H126: ='Manufacturing & Production'!F330 -> 2801916 | I126: ='Manufacturing & Production'!G330 -> 1190640 | J126: ='Workforce & Expenses'!M382 -> 1564757 | K126: ='Manufacturing & Production'!K330 -> 16471 | L126: ='Clinical Trials & R&D'!F330 -> 4572269 | M126: ='Clinical Trials & R&D'!I330 -> 4784181 | N126: ='Workforce & Expenses'!P382 -> 6358982 | O126: ='Workforce & Expenses'!S382 -> 4214704 | P126: =ROUND(P114*(1+MIN(0.2,MAX(0,IFERROR(SUM($P$86:$P$97)/SUM($P$74:$P$85)-1,0)))),0) -> 1435744 | Q126: =ROUND(Q114*IFERROR(SUM($T$86:$T$97)/SUM($T$74:$T$85),1),0) -> 1451851 | R126: =ROUND(AE126*IFERROR(SUM($R$86:$R$97)/AVERAGE($AE$85,$AE$97),0)/12,0) -> 580833 | S126: =0 -> 0 | T126: =MAX(0,ROUND(T114*IFERROR(SUM($T$86:$T$97)/SUM($T$74:$T$85),1)+('Funding & Cap'!$G$10-'Funding & Cap'!$G$5)*'Funding & Cap'!$B$6/12,0)) -> 2522460 | U126: =IF(MONTH(A126)=IF('Funding & Cap'!$N$4="IPO in 2028",'Funding & Cap'!$N$8,2),'Funding & Cap'!$G$10,0) -> 0 | V126: =0 -> 0 | W126: =IF(MONTH(A126)=12,MIN(AE125,'Funding & Cap'!$G$9),0) -> 0 | X126: =ROUND(X114*IFERROR((SUM(E126:G126)+AI126)/(SUM(E114:G114)+AI114),1),0) -> 38985111 | Y126: =ROUND(Y114*IFERROR((SUM(H126:I126)+AJ126)/(SUM(H114:I114)+AJ114),1),0) -> 17606154 | Z126: =ROUND(Z114*IFERROR(SUM(E126:G126)/SUM(E114:G114),1),0) -> 11379482 | AA126: =ROUND(AA114*IFERROR((SUM(H126:K126)+AJ126+0.25*SUM(L126:M126))/(SUM(H114:K114)+AJ114+0.25*SUM(L114:M114)),1),0) -> 12848557 | AB126: =ROUND(AB114*IFERROR(SUM(L126:O126)/SUM(L114:O114),1),0) -> 20744293 | AC126: =ROUND(AC114*IFERROR(SUM(F126:G126)/SUM(F114:G114),1),0) -> 13824527 | AD126: =MIN(AE126,SUMIFS($W$2:$W$181,$A$2:$A$181,">"&A126,$A$2:$A$181,"<="&EDATE(A126,12))+IF(AND(DATE(2033,12,1)>A126,DATE(2033,12,1)<=EDATE(A126,12)),'Funding & Cap'!$B$200,0)) -> 15000000 | AE126: =SUM($V$2:V126)-SUM($W$2:W126) -> 82000000 | AF126: =AF125+AG126+U126 -> 335761402 | AG126: =SUM(E126:G126)+AI126-SUM(H126:S126)-AJ126+P126+Q126-(X126-X125)-(Y126-Y125)-(Z126-Z125)+(AA126-AA125)+(AB126-AB125)+(AC126-AC125)-T126+V126-W126 -> -5120726 | AH126: ='Revenue & Demand'!I56 -> 4876 | AI126: ='Revenue & Demand'!K56 -> 7314000 | AJ126: ='Manufacturing & Production'!J330 -> 2277458 | AK126: =A126 -> 46874 | AL126: =IF(B126<=2025,C126,"") | AM126: =IF(OR(B126>=2026,AND(B126=2025,MONTH(A126)=12)),C126,"") -> 9922
A127: =EDATE(A115,12) -> 46905 | B127: =YEAR(A127) -> 2028 | C127: ='Revenue & Demand'!C57 -> 10074 | D127: ='Revenue & Demand'!D57 -> 102 | E127: ='Revenue & Demand'!F57 -> 15111000 | F127: ='Revenue & Demand'!G57 -> 3775329 | G127: ='Revenue & Demand'!H57 -> 1286765 | H127: ='Manufacturing & Production'!F331 -> 2826172 | I127: ='Manufacturing & Production'!G331 -> 1208880 | J127: ='Workforce & Expenses'!M383 -> 1597715 | K127: ='Manufacturing & Production'!K331 -> 102941 | L127: ='Clinical Trials & R&D'!F331 -> 4572269 | M127: ='Clinical Trials & R&D'!I331 -> 4802747 | N127: ='Workforce & Expenses'!P383 -> 6388867 | O127: ='Workforce & Expenses'!S383 -> 4233907 | P127: =ROUND(P115*(1+MIN(0.2,MAX(0,IFERROR(SUM($P$86:$P$97)/SUM($P$74:$P$85)-1,0)))),0) -> 1462818 | Q127: =ROUND(Q115*IFERROR(SUM($T$86:$T$97)/SUM($T$74:$T$85),1),0) -> 1451851 | R127: =ROUND(AE127*IFERROR(SUM($R$86:$R$97)/AVERAGE($AE$85,$AE$97),0)/12,0) -> 580833 | S127: =0 -> 0 | T127: =MAX(0,ROUND(T115*IFERROR(SUM($T$86:$T$97)/SUM($T$74:$T$85),1)+('Funding & Cap'!$G$10-'Funding & Cap'!$G$5)*'Funding & Cap'!$B$6/12,0)) -> 2598073 | U127: =IF(MONTH(A127)=IF('Funding & Cap'!$N$4="IPO in 2028",'Funding & Cap'!$N$8,2),'Funding & Cap'!$G$10,0) -> 0 | V127: =0 -> 0 | W127: =IF(MONTH(A127)=12,MIN(AE126,'Funding & Cap'!$G$9),0) -> 0 | X127: =ROUND(X115*IFERROR((SUM(E127:G127)+AI127)/(SUM(E115:G115)+AI115),1),0) -> 36163918 | Y127: =ROUND(Y115*IFERROR((SUM(H127:I127)+AJ127)/(SUM(H115:I115)+AJ115),1),0) -> 18138633 | Z127: =ROUND(Z115*IFERROR(SUM(E127:G127)/SUM(E115:G115),1),0) -> 10583864 | AA127: =ROUND(AA115*IFERROR((SUM(H127:K127)+AJ127+0.25*SUM(L127:M127))/(SUM(H115:K115)+AJ115+0.25*SUM(L115:M115)),1),0) -> 13257683 | AB127: =ROUND(AB115*IFERROR(SUM(L127:O127)/SUM(L115:O115),1),0) -> 21656784 | AC127: =ROUND(AC115*IFERROR(SUM(F127:G127)/SUM(F115:G115),1),0) -> 10763794 | AD127: =MIN(AE127,SUMIFS($W$2:$W$181,$A$2:$A$181,">"&A127,$A$2:$A$181,"<="&EDATE(A127,12))+IF(AND(DATE(2033,12,1)>A127,DATE(2033,12,1)<=EDATE(A127,12)),'Funding & Cap'!$B$200,0)) -> 15000000 | AE127: =SUM($V$2:V127)-SUM($W$2:W127) -> 82000000 | AF127: =AF126+AG127+U127 -> 333507210 | AG127: =SUM(E127:G127)+AI127-SUM(H127:S127)-AJ127+P127+Q127-(X127-X126)-(Y127-Y126)-(Z127-Z126)+(AA127-AA126)+(AB127-AB126)+(AC127-AC126)-T127+V127-W127 -> -2254192 | AH127: ='Revenue & Demand'!I57 -> 4973 | AI127: ='Revenue & Demand'!K57 -> 7459500 | AJ127: ='Manufacturing & Production'!J331 -> 2319598 | AK127: =A127 -> 46905 | AL127: =IF(B127<=2025,C127,"") | AM127: =IF(OR(B127>=2026,AND(B127=2025,MONTH(A127)=12)),C127,"") -> 10074
A128: =EDATE(A116,12) -> 46935 | B128: =YEAR(A128) -> 2028 | C128: ='Revenue & Demand'!C58 -> 10228 | D128: ='Revenue & Demand'!D58 -> 103 | E128: ='Revenue & Demand'!F58 -> 15342000 | F128: ='Revenue & Demand'!G58 -> 3708057 | G128: ='Revenue & Demand'!H58 -> 205882 | H128: ='Manufacturing & Production'!F332 -> 2850597 | I128: ='Manufacturing & Production'!G332 -> 1227360 | J128: ='Workforce & Expenses'!M384 -> 1607263 | K128: ='Manufacturing & Production'!K332 -> 16471 | L128: ='Clinical Trials & R&D'!F332 -> 4612866 | M128: ='Clinical Trials & R&D'!I332 -> 4802747 | N128: ='Workforce & Expenses'!P384 -> 6419113 | O128: ='Workforce & Expenses'!S384 -> 4236294 | P128: =ROUND(P116*(1+MIN(0.2,MAX(0,IFERROR(SUM($P$86:$P$97)/SUM($P$74:$P$85)-1,0)))),0) -> 1489931 | Q128: =ROUND(Q116*IFERROR(SUM($T$86:$T$97)/SUM($T$74:$T$85),1),0) -> 1451851 | R128: =ROUND(AE128*IFERROR(SUM($R$86:$R$97)/AVERAGE($AE$85,$AE$97),0)/12,0) -> 580833 | S128: =0 -> 0 | T128: =MAX(0,ROUND(T116*IFERROR(SUM($T$86:$T$97)/SUM($T$74:$T$85),1)+('Funding & Cap'!$G$10-'Funding & Cap'!$G$5)*'Funding & Cap'!$B$6/12,0)) -> 2535339 | U128: =IF(MONTH(A128)=IF('Funding & Cap'!$N$4="IPO in 2028",'Funding & Cap'!$N$8,2),'Funding & Cap'!$G$10,0) -> 0 | V128: =0 -> 0 | W128: =IF(MONTH(A128)=12,MIN(AE127,'Funding & Cap'!$G$9),0) -> 0 | X128: =ROUND(X116*IFERROR((SUM(E128:G128)+AI128)/(SUM(E116:G116)+AI116),1),0) -> 41374552 | Y128: =ROUND(Y116*IFERROR((SUM(H128:I128)+AJ128)/(SUM(H116:I116)+AJ116),1),0) -> 18733582 | Z128: =ROUND(Z116*IFERROR(SUM(E128:G128)/SUM(E116:G116),1),0) -> 11829244 | AA128: =ROUND(AA116*IFERROR((SUM(H128:K128)+AJ128+0.25*SUM(L128:M128))/(SUM(H116:K116)+AJ116+0.25*SUM(L116:M116)),1),0) -> 14052602 | AB128: =ROUND(AB116*IFERROR(SUM(L128:O128)/SUM(L116:O116),1),0) -> 22443288 | AC128: =ROUND(AC116*IFERROR(SUM(F128:G128)/SUM(F116:G116),1),0) -> 13215527 | AD128: =MIN(AE128,SUMIFS($W$2:$W$181,$A$2:$A$181,">"&A128,$A$2:$A$181,"<="&EDATE(A128,12))+IF(AND(DATE(2033,12,1)>A128,DATE(2033,12,1)<=EDATE(A128,12)),'Funding & Cap'!$B$200,0)) -> 15000000 | AE128: =SUM($V$2:V128)-SUM($W$2:W128) -> 82000000 | AF128: =AF127+AG128+U128 -> 326102917 | AG128: =SUM(E128:G128)+AI128-SUM(H128:S128)-AJ128+P128+Q128-(X128-X127)-(Y128-Y127)-(Z128-Z127)+(AA128-AA127)+(AB128-AB127)+(AC128-AC127)-T128+V128-W128 -> -7404293 | AH128: ='Revenue & Demand'!I58 -> 5073 | AI128: ='Revenue & Demand'!K58 -> 7609500 | AJ128: ='Manufacturing & Production'!J332 -> 2363042 | AK128: =A128 -> 46935 | AL128: =IF(B128<=2025,C128,"") | AM128: =IF(OR(B128>=2026,AND(B128=2025,MONTH(A128)=12)),C128,"") -> 10228
A129: =EDATE(A117,12) -> 46966 | B129: =YEAR(A129) -> 2028 | C129: ='Revenue & Demand'!C59 -> 10385 | D129: ='Revenue & Demand'!D59 -> 106 | E129: ='Revenue & Demand'!F59 -> 15577500 | F129: ='Revenue & Demand'!G59 -> 3619961 | G129: ='Revenue & Demand'!H59 -> 205882 | H129: ='Manufacturing & Production'!F333 -> 2903248 | I129: ='Manufacturing & Production'!G333 -> 1246200 | J129: ='Workforce & Expenses'!M385 -> 1635908 | K129: ='Manufacturing & Production'!K333 -> 16471 | L129: ='Clinical Trials & R&D'!F333 -> 4612866 | M129: ='Clinical Trials & R&D'!I333 -> 4821313 | N129: ='Workforce & Expenses'!P385 -> 6448998 | O129: ='Workforce & Expenses'!S385 -> 4255973 | P129: =ROUND(P117*(1+MIN(0.2,MAX(0,IFERROR(SUM($P$86:$P$97)/SUM($P$74:$P$85)-1,0)))),0) -> 1517075 | Q129: =ROUND(Q117*IFERROR(SUM($T$86:$T$97)/SUM($T$74:$T$85),1),0) -> 1451851 | R129: =ROUND(AE129*IFERROR(SUM($R$86:$R$97)/AVERAGE($AE$85,$AE$97),0)/12,0) -> 580833 | S129: =0 -> 0 | T129: =MAX(0,ROUND(T117*IFERROR(SUM($T$86:$T$97)/SUM($T$74:$T$85),1)+('Funding & Cap'!$G$10-'Funding & Cap'!$G$5)*'Funding & Cap'!$B$6/12,0)) -> 2611487 | U129: =IF(MONTH(A129)=IF('Funding & Cap'!$N$4="IPO in 2028",'Funding & Cap'!$N$8,2),'Funding & Cap'!$G$10,0) -> 0 | V129: =0 -> 0 | W129: =IF(MONTH(A129)=12,MIN(AE128,'Funding & Cap'!$G$9),0) -> 0 | X129: =ROUND(X117*IFERROR((SUM(E129:G129)+AI129)/(SUM(E117:G117)+AI117),1),0) -> 42587140 | Y129: =ROUND(Y117*IFERROR((SUM(H129:I129)+AJ129)/(SUM(H117:I117)+AJ117),1),0) -> 19306801 | Z129: =ROUND(Z117*IFERROR(SUM(E129:G129)/SUM(E117:G117),1),0) -> 12078038 | AA129: =ROUND(AA117*IFERROR((SUM(H129:K129)+AJ129+0.25*SUM(L129:M129))/(SUM(H117:K117)+AJ117+0.25*SUM(L117:M117)),1),0) -> 14541428 | AB129: =ROUND(AB117*IFERROR(SUM(L129:O129)/SUM(L117:O117),1),0) -> 23008518 | AC129: =ROUND(AC117*IFERROR(SUM(F129:G129)/SUM(F117:G117),1),0) -> 12996887 | AD129: =MIN(AE129,SUMIFS($W$2:$W$181,$A$2:$A$181,">"&A129,$A$2:$A$181,"<="&EDATE(A129,12))+IF(AND(DATE(2033,12,1)>A129,DATE(2033,12,1)<=EDATE(A129,12)),'Funding & Cap'!$B$200,0)) -> 15000000 | AE129: =SUM($V$2:V129)-SUM($W$2:W129) -> 82000000 | AF129: =AF128+AG129+U129 -> 320527859 | AG129: =SUM(E129:G129)+AI129-SUM(H129:S129)-AJ129+P129+Q129-(X129-X128)-(Y129-Y128)-(Z129-Z128)+(AA129-AA128)+(AB129-AB128)+(AC129-AC128)-T129+V129-W129 -> -5575058 | AH129: ='Revenue & Demand'!I59 -> 5174 | AI129: ='Revenue & Demand'!K59 -> 7761000 | AJ129: ='Manufacturing & Production'!J333 -> 2406919 | AK129: =A129 -> 46966 | AL129: =IF(B129<=2025,C129,"") | AM129: =IF(OR(B129>=2026,AND(B129=2025,MONTH(A129)=12)),C129,"") -> 10385
A130: =EDATE(A118,12) -> 46997 | B130: =YEAR(A130) -> 2028 | C130: ='Revenue & Demand'!C60 -> 10544 | D130: ='Revenue & Demand'!D60 -> 108 | E130: ='Revenue & Demand'!F60 -> 15816000 | F130: ='Revenue & Demand'!G60 -> 3655385 | G130: ='Revenue & Demand'!H60 -> 1286765 | H130: ='Manufacturing & Production'!F334 -> 2928096 | I130: ='Manufacturing & Production'!G334 -> 1265280 | J130: ='Workforce & Expenses'!M386 -> 1655004 | K130: ='Manufacturing & Production'!K334 -> 102941 | L130: ='Clinical Trials & R&D'!F334 -> 4653463 | M130: ='Clinical Trials & R&D'!I334 -> 4839878 | N130: ='Workforce & Expenses'!P386 -> 6479243 | O130: ='Workforce & Expenses'!S386 -> 4258837 | P130: =ROUND(P118*(1+MIN(0.2,MAX(0,IFERROR(SUM($P$86:$P$97)/SUM($P$74:$P$85)-1,0)))),0) -> 1544256 | Q130: =ROUND(Q118*IFERROR(SUM($T$86:$T$97)/SUM($T$74:$T$85),1),0) -> 1451851 | R130: =ROUND(AE130*IFERROR(SUM($R$86:$R$97)/AVERAGE($AE$85,$AE$97),0)/12,0) -> 580833 | S130: =0 -> 0 | T130: =MAX(0,ROUND(T118*IFERROR(SUM($T$86:$T$97)/SUM($T$74:$T$85),1)+('Funding & Cap'!$G$10-'Funding & Cap'!$G$5)*'Funding & Cap'!$B$6/12,0)) -> 6313924 | U130: =IF(MONTH(A130)=IF('Funding & Cap'!$N$4="IPO in 2028",'Funding & Cap'!$N$8,2),'Funding & Cap'!$G$10,0) -> 0 | V130: =0 -> 0 | W130: =IF(MONTH(A130)=12,MIN(AE129,'Funding & Cap'!$G$9),0) -> 0 | X130: =ROUND(X118*IFERROR((SUM(E130:G130)+AI130)/(SUM(E118:G118)+AI118),1),0) -> 40077526 | Y130: =ROUND(Y118*IFERROR((SUM(H130:I130)+AJ130)/(SUM(H118:I118)+AJ118),1),0) -> 19917373 | Z130: =ROUND(Z118*IFERROR(SUM(E130:G130)/SUM(E118:G118),1),0) -> 11469739 | AA130: =ROUND(AA118*IFERROR((SUM(H130:K130)+AJ130+0.25*SUM(L130:M130))/(SUM(H118:K118)+AJ118+0.25*SUM(L118:M118)),1),0) -> 14620773 | AB130: =ROUND(AB118*IFERROR(SUM(L130:O130)/SUM(L118:O118),1),0) -> 23363738 | AC130: =ROUND(AC118*IFERROR(SUM(F130:G130)/SUM(F118:G118),1),0) -> 10701740 | AD130: =MIN(AE130,SUMIFS($W$2:$W$181,$A$2:$A$181,">"&A130,$A$2:$A$181,"<="&EDATE(A130,12))+IF(AND(DATE(2033,12,1)>A130,DATE(2033,12,1)<=EDATE(A130,12)),'Funding & Cap'!$B$200,0)) -> 15000000 | AE130: =SUM($V$2:V130)-SUM($W$2:W130) -> 82000000 | AF130: =AF129+AG130+U130 -> 314320167 | AG130: =SUM(E130:G130)+AI130-SUM(H130:S130)-AJ130+P130+Q130-(X130-X129)-(Y130-Y129)-(Z130-Z129)+(AA130-AA129)+(AB130-AB129)+(AC130-AC129)-T130+V130-W130 -> -6207692 | AH130: ='Revenue & Demand'!I60 -> 5278 | AI130: ='Revenue & Demand'!K60 -> 7917000 | AJ130: ='Manufacturing & Production'!J334 -> 2452102 | AK130: =A130 -> 46997 | AL130: =IF(B130<=2025,C130,"") | AM130: =IF(OR(B130>=2026,AND(B130=2025,MONTH(A130)=12)),C130,"") -> 10544
A131: =EDATE(A119,12) -> 47027 | B131: =YEAR(A131) -> 2028 | C131: ='Revenue & Demand'!C61 -> 10705 | D131: ='Revenue & Demand'!D61 -> 108 | E131: ='Revenue & Demand'!F61 -> 16057500 | F131: ='Revenue & Demand'!G61 -> 3688259 | G131: ='Revenue & Demand'!H61 -> 205882 | H131: ='Manufacturing & Production'!F335 -> 2953113 | I131: ='Manufacturing & Production'!G335 -> 1284600 | J131: ='Workforce & Expenses'!M387 -> 1668867 | K131: ='Manufacturing & Production'!K335 -> 16471 | L131: ='Clinical Trials & R&D'!F335 -> 4653463 | M131: ='Clinical Trials & R&D'!I335 -> 4858444 | N131: ='Workforce & Expenses'!P387 -> 6494276 | O131: ='Workforce & Expenses'!S387 -> 4277562 | P131: =ROUND(P119*(1+MIN(0.2,MAX(0,IFERROR(SUM($P$86:$P$97)/SUM($P$74:$P$85)-1,0)))),0) -> 1561062 | Q131: =ROUND(Q119*IFERROR(SUM($T$86:$T$97)/SUM($T$74:$T$85),1),0) -> 1451851 | R131: =ROUND(AE131*IFERROR(SUM($R$86:$R$97)/AVERAGE($AE$85,$AE$97),0)/12,0) -> 580833 | S131: =0 -> 0 | T131: =MAX(0,ROUND(T119*IFERROR(SUM($T$86:$T$97)/SUM($T$74:$T$85),1)+('Funding & Cap'!$G$10-'Funding & Cap'!$G$5)*'Funding & Cap'!$B$6/12,0)) -> 2670841 | U131: =IF(MONTH(A131)=IF('Funding & Cap'!$N$4="IPO in 2028",'Funding & Cap'!$N$8,2),'Funding & Cap'!$G$10,0) -> 0 | V131: =0 -> 0 | W131: =IF(MONTH(A131)=12,MIN(AE130,'Funding & Cap'!$G$9),0) -> 0 | X131: =ROUND(X119*IFERROR((SUM(E131:G131)+AI131)/(SUM(E119:G119)+AI119),1),0) -> 41927644 | Y131: =ROUND(Y119*IFERROR((SUM(H131:I131)+AJ131)/(SUM(H119:I119)+AJ119),1),0) -> 18751238 | Z131: =ROUND(Z119*IFERROR(SUM(E131:G131)/SUM(E119:G119),1),0) -> 11753340 | AA131: =ROUND(AA119*IFERROR((SUM(H131:K131)+AJ131+0.25*SUM(L131:M131))/(SUM(H119:K119)+AJ119+0.25*SUM(L119:M119)),1),0) -> 14358097 | AB131: =ROUND(AB119*IFERROR(SUM(L131:O131)/SUM(L119:O119),1),0) -> 23105331 | AC131: =ROUND(AC119*IFERROR(SUM(F131:G131)/SUM(F119:G119),1),0) -> 12791187 | AD131: =MIN(AE131,SUMIFS($W$2:$W$181,$A$2:$A$181,">"&A131,$A$2:$A$181,"<="&EDATE(A131,12))+IF(AND(DATE(2033,12,1)>A131,DATE(2033,12,1)<=EDATE(A131,12)),'Funding & Cap'!$B$200,0)) -> 15000000 | AE131: =SUM($V$2:V131)-SUM($W$2:W131) -> 82000000 | AF131: =AF130+AG131+U131 -> 310990901 | AG131: =SUM(E131:G131)+AI131-SUM(H131:S131)-AJ131+P131+Q131-(X131-X130)-(Y131-Y130)-(Z131-Z130)+(AA131-AA130)+(AB131-AB130)+(AC131-AC130)-T131+V131-W131 -> -3329266 | AH131: ='Revenue & Demand'!I61 -> 5383 | AI131: ='Revenue & Demand'!K61 -> 8074500 | AJ131: ='Manufacturing & Production'!J335 -> 2497717 | AK131: =A131 -> 47027 | AL131: =IF(B131<=2025,C131,"") | AM131: =IF(OR(B131>=2026,AND(B131=2025,MONTH(A131)=12)),C131,"") -> 10705
A132: =EDATE(A120,12) -> 47058 | B132: =YEAR(A132) -> 2028 | C132: ='Revenue & Demand'!C62 -> 10869 | D132: ='Revenue & Demand'!D62 -> 110 | E132: ='Revenue & Demand'!F62 -> 16303500 | F132: ='Revenue & Demand'!G62 -> 3814469 | G132: ='Revenue & Demand'!H62 -> 205882 | H132: ='Manufacturing & Production'!F336 -> 3006357 | I132: ='Manufacturing & Production'!G336 -> 1304280 | J132: ='Workforce & Expenses'!M388 -> 1687963 | K132: ='Manufacturing & Production'!K336 -> 16471 | L132: ='Clinical Trials & R&D'!F336 -> 4694060 | M132: ='Clinical Trials & R&D'!I336 -> 4858444 | N132: ='Workforce & Expenses'!P388 -> 6524521 | O132: ='Workforce & Expenses'!S388 -> 4280904 | P132: =ROUND(P120*(1+MIN(0.2,MAX(0,IFERROR(SUM($P$86:$P$97)/SUM($P$74:$P$85)-1,0)))),0) -> 1587082 | Q132: =ROUND(Q120*IFERROR(SUM($T$86:$T$97)/SUM($T$74:$T$85),1),0) -> 1451851 | R132: =ROUND(AE132*IFERROR(SUM($R$86:$R$97)/AVERAGE($AE$85,$AE$97),0)/12,0) -> 580833 | S132: =0 -> 0 | T132: =MAX(0,ROUND(T120*IFERROR(SUM($T$86:$T$97)/SUM($T$74:$T$85),1)+('Funding & Cap'!$G$10-'Funding & Cap'!$G$5)*'Funding & Cap'!$B$6/12,0)) -> 2700516 | U132: =IF(MONTH(A132)=IF('Funding & Cap'!$N$4="IPO in 2028",'Funding & Cap'!$N$8,2),'Funding & Cap'!$G$10,0) -> 0 | V132: =0 -> 0 | W132: =IF(MONTH(A132)=12,MIN(AE131,'Funding & Cap'!$G$9),0) -> 0 | X132: =ROUND(X120*IFERROR((SUM(E132:G132)+AI132)/(SUM(E120:G120)+AI120),1),0) -> 43447938 | Y132: =ROUND(Y120*IFERROR((SUM(H132:I132)+AJ132)/(SUM(H120:I120)+AJ120),1),0) -> 19596681 | Z132: =ROUND(Z120*IFERROR(SUM(E132:G132)/SUM(E120:G120),1),0) -> 12130727 | AA132: =ROUND(AA120*IFERROR((SUM(H132:K132)+AJ132+0.25*SUM(L132:M132))/(SUM(H120:K120)+AJ120+0.25*SUM(L120:M120)),1),0) -> 14587877 | AB132: =ROUND(AB120*IFERROR(SUM(L132:O132)/SUM(L120:O120),1),0) -> 23180985 | AC132: =ROUND(AC120*IFERROR(SUM(F132:G132)/SUM(F120:G120),1),0) -> 12851905 | AD132: =MIN(AE132,SUMIFS($W$2:$W$181,$A$2:$A$181,">"&A132,$A$2:$A$181,"<="&EDATE(A132,12))+IF(AND(DATE(2033,12,1)>A132,DATE(2033,12,1)<=EDATE(A132,12)),'Funding & Cap'!$B$200,0)) -> 15000000 | AE132: =SUM($V$2:V132)-SUM($W$2:W132) -> 82000000 | AF132: =AF131+AG132+U132 -> 304975294 | AG132: =SUM(E132:G132)+AI132-SUM(H132:S132)-AJ132+P132+Q132-(X132-X131)-(Y132-Y131)-(Z132-Z131)+(AA132-AA131)+(AB132-AB131)+(AC132-AC131)-T132+V132-W132 -> -6015607 | AH132: ='Revenue & Demand'!I62 -> 5491 | AI132: ='Revenue & Demand'!K62 -> 8236500 | AJ132: ='Manufacturing & Production'!J336 -> 2544637 | AK132: =A132 -> 47058 | AL132: =IF(B132<=2025,C132,"") | AM132: =IF(OR(B132>=2026,AND(B132=2025,MONTH(A132)=12)),C132,"") -> 10869
A133: =EDATE(A121,12) -> 47088 | B133: =YEAR(A133) -> 2028 | C133: ='Revenue & Demand'!C63 -> 11035 | D133: ='Revenue & Demand'!D63 -> 112 | E133: ='Revenue & Demand'!F63 -> 16552500 | F133: ='Revenue & Demand'!G63 -> 3938718 | G133: ='Revenue & Demand'!H63 -> 1492649 | H133: ='Manufacturing & Production'!F337 -> 3031797 | I133: ='Manufacturing & Production'!G337 -> 1324200 | J133: ='Workforce & Expenses'!M389 -> 1707059 | K133: ='Manufacturing & Production'!K337 -> 119412 | L133: ='Clinical Trials & R&D'!F337 -> 4694060 | M133: ='Clinical Trials & R&D'!I337 -> 4877010 | N133: ='Workforce & Expenses'!P389 -> 6554586 | O133: ='Workforce & Expenses'!S389 -> 4299629 | P133: =ROUND(P121*(1+MIN(0.2,MAX(0,IFERROR(SUM($P$86:$P$97)/SUM($P$74:$P$85)-1,0)))),0) -> 1613093 | Q133: =ROUND(Q121*IFERROR(SUM($T$86:$T$97)/SUM($T$74:$T$85),1),0) -> 1451861 | R133: =ROUND(AE133*IFERROR(SUM($R$86:$R$97)/AVERAGE($AE$85,$AE$97),0)/12,0) -> 474583 | S133: =ROUND(0.25*MAX(0,SUM(E122:G133)+SUM(AI122:AI133)-SUM(H122:R133)-SUM(AJ122:AJ133)),0) -> 0 | T133: =MAX(0,ROUND(T121*IFERROR(SUM($T$86:$T$97)/SUM($T$74:$T$85),1)+('Funding & Cap'!$G$10-'Funding & Cap'!$G$5)*'Funding & Cap'!$B$6/12,0)) -> 2730192 | U133: =IF(MONTH(A133)=IF('Funding & Cap'!$N$4="IPO in 2028",'Funding & Cap'!$N$8,2),'Funding & Cap'!$G$10,0) -> 0 | V133: =0 -> 0 | W133: =IF(MONTH(A133)=12,MIN(AE132,'Funding & Cap'!$G$9),0) -> 15000000 | X133: =ROUND(X121*IFERROR((SUM(E133:G133)+AI133)/(SUM(E121:G121)+AI121),1),0) -> 41339674 | Y133: =ROUND(Y121*IFERROR((SUM(H133:I133)+AJ133)/(SUM(H121:I121)+AJ121),1),0) -> 20397333 | Z133: =ROUND(Z121*IFERROR(SUM(E133:G133)/SUM(E121:G121),1),0) -> 11696683 | AA133: =ROUND(AA121*IFERROR((SUM(H133:K133)+AJ133+0.25*SUM(L133:M133))/(SUM(H121:K121)+AJ121+0.25*SUM(L121:M121)),1),0) -> 14620660 | AB133: =ROUND(AB121*IFERROR(SUM(L133:O133)/SUM(L121:O121),1),0) -> 23284199 | AC133: =ROUND(AC121*IFERROR(SUM(F133:G133)/SUM(F121:G121),1),0) -> 10755310 | AD133: =MIN(AE133,SUMIFS($W$2:$W$181,$A$2:$A$181,">"&A133,$A$2:$A$181,"<="&EDATE(A133,12))+IF(AND(DATE(2033,12,1)>A133,DATE(2033,12,1)<=EDATE(A133,12)),'Funding & Cap'!$B$200,0)) -> 15000000 | AE133: =SUM($V$2:V133)-SUM($W$2:W133) -> 67000000 | AF133: =AF132+AG133+U133 -> 287736765 | AG133: =SUM(E133:G133)+AI133-SUM(H133:S133)-AJ133+P133+Q133-(X133-X132)-(Y133-Y132)-(Z133-Z132)+(AA133-AA132)+(AB133-AB132)+(AC133-AC132)-T133+V133-W133 -> -17238529 | AH133: ='Revenue & Demand'!I63 -> 5601 | AI133: ='Revenue & Demand'!K63 -> 8401500 | AJ133: ='Manufacturing & Production'!J337 -> 2592426 | AK133: =A133 -> 47088 | AL133: =IF(B133<=2025,C133,"") | AM133: =IF(OR(B133>=2026,AND(B133=2025,MONTH(A133)=12)),C133,"") -> 11035
A134: =EDATE(A122,12) -> 47119 | B134: =YEAR(A134) -> 2029 | C134: ='Revenue & Demand'!C64 -> 11164 | D134: ='Revenue & Demand'!D64 -> 103 | E134: ='Revenue & Demand'!F64 -> 16746000 | F134: ='Revenue & Demand'!G64 -> 4943948 | G134: ='Revenue & Demand'!H64 -> 205882 | H134: ='Manufacturing & Production'!F338 -> 3145730 | I134: ='Manufacturing & Production'!G338 -> 1339680 | J134: ='Workforce & Expenses'!M390 -> 1669760 | K134: ='Manufacturing & Production'!K338 -> 16471 | L134: ='Clinical Trials & R&D'!F338 -> 4834880 | M134: ='Clinical Trials & R&D'!I338 -> 5178876 | N134: ='Workforce & Expenses'!P390 -> 8104856 | O134: ='Workforce & Expenses'!S390 -> 4566975 | P134: =ROUND(P122*(1+MIN(0.2,MAX(0,IFERROR(SUM($P$86:$P$97)/SUM($P$74:$P$85)-1,0)))),0) -> 1593346 | Q134: =ROUND(Q122*IFERROR(SUM($T$86:$T$97)/SUM($T$74:$T$85),1),0) -> 1935801 | R134: =ROUND(AE134*IFERROR(SUM($R$86:$R$97)/AVERAGE($AE$85,$AE$97),0)/12,0) -> 474583 | S134: =0 -> 0 | T134: =MAX(0,ROUND(T122*IFERROR(SUM($T$86:$T$97)/SUM($T$74:$T$85),1)+('Funding & Cap'!$H$10-'Funding & Cap'!$H$5)*'Funding & Cap'!$B$6/12,0)) -> 3147319 | U134: =IF(MONTH(A134)=IF('Funding & Cap'!$N$4="IPO in 2029",'Funding & Cap'!$N$8,2),'Funding & Cap'!$H$10,0) -> 0 | V134: =0 -> 0 | W134: =IF(MONTH(A134)=12,MIN(AE133,'Funding & Cap'!$H$9),0) -> 0 | X134: =ROUND(X122*IFERROR((SUM(E134:G134)+AI134)/(SUM(E122:G122)+AI122),1),0) -> 38173374 | Y134: =ROUND(Y122*IFERROR((SUM(H134:I134)+AJ134)/(SUM(H122:I122)+AJ122),1),0) -> 17223040 | Z134: =ROUND(Z122*IFERROR(SUM(E134:G134)/SUM(E122:G122),1),0) -> 11412486 | AA134: =ROUND(AA122*IFERROR((SUM(H134:K134)+AJ134+0.25*SUM(L134:M134))/(SUM(H122:K122)+AJ122+0.25*SUM(L122:M122)),1),0) -> 12154015 | AB134: =ROUND(AB122*IFERROR(SUM(L134:O134)/SUM(L122:O122),1),0) -> 20225644 | AC134: =ROUND(AC122*IFERROR(SUM(F134:G134)/SUM(F122:G122),1),0) -> 15222137 | AD134: =MIN(AE134,SUMIFS($W$2:$W$181,$A$2:$A$181,">"&A134,$A$2:$A$181,"<="&EDATE(A134,12))+IF(AND(DATE(2033,12,1)>A134,DATE(2033,12,1)<=EDATE(A134,12)),'Funding & Cap'!$B$200,0)) -> 15000000 | AE134: =SUM($V$2:V134)-SUM($W$2:W134) -> 67000000 | AF134: =AF133+AG134+U134 -> 288569067 | AG134: =SUM(E134:G134)+AI134-SUM(H134:S134)-AJ134+P134+Q134-(X134-X133)-(Y134-Y133)-(Z134-Z133)+(AA134-AA133)+(AB134-AB133)+(AC134-AC133)-T134+V134-W134 -> 832302 | AH134: ='Revenue & Demand'!I64 -> 5713 | AI134: ='Revenue & Demand'!K64 -> 8569500 | AJ134: ='Manufacturing & Production'!J338 -> 2720315 | AK134: =A134 -> 47119 | AL134: =IF(B134<=2025,C134,"") | AM134: =IF(OR(B134>=2026,AND(B134=2025,MONTH(A134)=12)),C134,"") -> 11164
A135: =EDATE(A123,12) -> 47150 | B135: =YEAR(A135) -> 2029 | C135: ='Revenue & Demand'!C65 -> 11295 | D135: ='Revenue & Demand'!D65 -> 105 | E135: ='Revenue & Demand'!F65 -> 16942500 | F135: ='Revenue & Demand'!G65 -> 5003054 | G135: ='Revenue & Demand'!H65 -> 205882 | H135: ='Manufacturing & Production'!F339 -> 3197692 | I135: ='Manufacturing & Production'!G339 -> 1355400 | J135: ='Workforce & Expenses'!M391 -> 1703707 | K135: ='Manufacturing & Production'!K339 -> 16471 | L135: ='Clinical Trials & R&D'!F339 -> 4856552 | M135: ='Clinical Trials & R&D'!I339 -> 5197999 | N135: ='Workforce & Expenses'!P391 -> 8120514 | O135: ='Workforce & Expenses'!S391 -> 4570417 | P135: =ROUND(P123*(1+MIN(0.2,MAX(0,IFERROR(SUM($P$86:$P$97)/SUM($P$74:$P$85)-1,0)))),0) -> 1625669 | Q135: =ROUND(Q123*IFERROR(SUM($T$86:$T$97)/SUM($T$74:$T$85),1),0) -> 1935801 | R135: =ROUND(AE135*IFERROR(SUM($R$86:$R$97)/AVERAGE($AE$85,$AE$97),0)/12,0) -> 474583 | S135: =0 -> 0 | T135: =MAX(0,ROUND(T123*IFERROR(SUM($T$86:$T$97)/SUM($T$74:$T$85),1)+('Funding & Cap'!$H$10-'Funding & Cap'!$H$5)*'Funding & Cap'!$B$6/12,0)) -> 3244575 | U135: =IF(MONTH(A135)=IF('Funding & Cap'!$N$4="IPO in 2029",'Funding & Cap'!$N$8,2),'Funding & Cap'!$H$10,0) -> 0 | V135: =0 -> 0 | W135: =IF(MONTH(A135)=12,MIN(AE134,'Funding & Cap'!$H$9),0) -> 0 | X135: =ROUND(X123*IFERROR((SUM(E135:G135)+AI135)/(SUM(E123:G123)+AI123),1),0) -> 40657014 | Y135: =ROUND(Y123*IFERROR((SUM(H135:I135)+AJ135)/(SUM(H123:I123)+AJ123),1),0) -> 18775822 | Z135: =ROUND(Z123*IFERROR(SUM(E135:G135)/SUM(E123:G123),1),0) -> 12005215 | AA135: =ROUND(AA123*IFERROR((SUM(H135:K135)+AJ135+0.25*SUM(L135:M135))/(SUM(H123:K123)+AJ123+0.25*SUM(L123:M123)),1),0) -> 12766748 | AB135: =ROUND(AB123*IFERROR(SUM(L135:O135)/SUM(L123:O123),1),0) -> 20936528 | AC135: =ROUND(AC123*IFERROR(SUM(F135:G135)/SUM(F123:G123),1),0) -> 15421411 | AD135: =MIN(AE135,SUMIFS($W$2:$W$181,$A$2:$A$181,">"&A135,$A$2:$A$181,"<="&EDATE(A135,12))+IF(AND(DATE(2033,12,1)>A135,DATE(2033,12,1)<=EDATE(A135,12)),'Funding & Cap'!$B$200,0)) -> 15000000 | AE135: =SUM($V$2:V135)-SUM($W$2:W135) -> 67000000 | AF135: =AF134+AG135+U135 -> 280845506 | AG135: =SUM(E135:G135)+AI135-SUM(H135:S135)-AJ135+P135+Q135-(X135-X134)-(Y135-Y134)-(Z135-Z134)+(AA135-AA134)+(AB135-AB134)+(AC135-AC134)-T135+V135-W135 -> -7723561 | AH135: ='Revenue & Demand'!I65 -> 5827 | AI135: ='Revenue & Demand'!K65 -> 8740500 | AJ135: ='Manufacturing & Production'!J339 -> 2771327 | AK135: =A135 -> 47150 | AL135: =IF(B135<=2025,C135,"") | AM135: =IF(OR(B135>=2026,AND(B135=2025,MONTH(A135)=12)),C135,"") -> 11295
A136: =EDATE(A124,12) -> 47178 | B136: =YEAR(A136) -> 2029 | C136: ='Revenue & Demand'!C66 -> 11427 | D136: ='Revenue & Demand'!D66 -> 108 | E136: ='Revenue & Demand'!F66 -> 17140500 | F136: ='Revenue & Demand'!G66 -> 4817872 | G136: ='Revenue & Demand'!H66 -> 1286765 | H136: ='Manufacturing & Production'!F340 -> 3220931 | I136: ='Manufacturing & Production'!G340 -> 1371240 | J136: ='Workforce & Expenses'!M392 -> 1733211 | K136: ='Manufacturing & Production'!K340 -> 102941 | L136: ='Clinical Trials & R&D'!F340 -> 4856552 | M136: ='Clinical Trials & R&D'!I340 -> 5217121 | N136: ='Workforce & Expenses'!P392 -> 8151650 | O136: ='Workforce & Expenses'!S392 -> 4589704 | P136: =ROUND(P124*(1+MIN(0.2,MAX(0,IFERROR(SUM($P$86:$P$97)/SUM($P$74:$P$85)-1,0)))),0) -> 1658036 | Q136: =ROUND(Q124*IFERROR(SUM($T$86:$T$97)/SUM($T$74:$T$85),1),0) -> 1935801 | R136: =ROUND(AE136*IFERROR(SUM($R$86:$R$97)/AVERAGE($AE$85,$AE$97),0)/12,0) -> 474583 | S136: =0 -> 0 | T136: =MAX(0,ROUND(T124*IFERROR(SUM($T$86:$T$97)/SUM($T$74:$T$85),1)+('Funding & Cap'!$H$10-'Funding & Cap'!$H$5)*'Funding & Cap'!$B$6/12,0)) -> 8176884 | U136: =IF(MONTH(A136)=IF('Funding & Cap'!$N$4="IPO in 2029",'Funding & Cap'!$N$8,2),'Funding & Cap'!$H$10,0) -> 0 | V136: =0 -> 0 | W136: =IF(MONTH(A136)=12,MIN(AE135,'Funding & Cap'!$H$9),0) -> 0 | X136: =ROUND(X124*IFERROR((SUM(E136:G136)+AI136)/(SUM(E124:G124)+AI124),1),0) -> 37988188 | Y136: =ROUND(Y124*IFERROR((SUM(H136:I136)+AJ136)/(SUM(H124:I124)+AJ124),1),0) -> 19733492 | Z136: =ROUND(Z124*IFERROR(SUM(E136:G136)/SUM(E124:G124),1),0) -> 11212730 | AA136: =ROUND(AA124*IFERROR((SUM(H136:K136)+AJ136+0.25*SUM(L136:M136))/(SUM(H124:K124)+AJ124+0.25*SUM(L124:M124)),1),0) -> 13268029 | AB136: =ROUND(AB124*IFERROR(SUM(L136:O136)/SUM(L124:O124),1),0) -> 21810961 | AC136: =ROUND(AC124*IFERROR(SUM(F136:G136)/SUM(F124:G124),1),0) -> 12128367 | AD136: =MIN(AE136,SUMIFS($W$2:$W$181,$A$2:$A$181,">"&A136,$A$2:$A$181,"<="&EDATE(A136,12))+IF(AND(DATE(2033,12,1)>A136,DATE(2033,12,1)<=EDATE(A136,12)),'Funding & Cap'!$B$200,0)) -> 15000000 | AE136: =SUM($V$2:V136)-SUM($W$2:W136) -> 67000000 | AF136: =AF135+AG136+U136 -> 272874456 | AG136: =SUM(E136:G136)+AI136-SUM(H136:S136)-AJ136+P136+Q136-(X136-X135)-(Y136-Y135)-(Z136-Z135)+(AA136-AA135)+(AB136-AB135)+(AC136-AC135)-T136+V136-W136 -> -7971050 | AH136: ='Revenue & Demand'!I66 -> 5944 | AI136: ='Revenue & Demand'!K66 -> 8916000 | AJ136: ='Manufacturing & Production'!J340 -> 2823681 | AK136: =A136 -> 47178 | AL136: =IF(B136<=2025,C136,"") | AM136: =IF(OR(B136>=2026,AND(B136=2025,MONTH(A136)=12)),C136,"") -> 11427
A137: =EDATE(A125,12) -> 47209 | B137: =YEAR(A137) -> 2029 | C137: ='Revenue & Demand'!C67 -> 11561 | D137: ='Revenue & Demand'!D67 -> 109 | E137: ='Revenue & Demand'!F67 -> 17341500 | F137: ='Revenue & Demand'!G67 -> 4810903 | G137: ='Revenue & Demand'!H67 -> 205882 | H137: ='Manufacturing & Production'!F341 -> 3256073 | I137: ='Manufacturing & Production'!G341 -> 1387320 | J137: ='Workforce & Expenses'!M393 -> 1743045 | K137: ='Manufacturing & Production'!K341 -> 16471 | L137: ='Clinical Trials & R&D'!F341 -> 4878224 | M137: ='Clinical Trials & R&D'!I341 -> 5236244 | N137: ='Workforce & Expenses'!P393 -> 8182607 | O137: ='Workforce & Expenses'!S393 -> 4592654 | P137: =ROUND(P125*(1+MIN(0.2,MAX(0,IFERROR(SUM($P$86:$P$97)/SUM($P$74:$P$85)-1,0)))),0) -> 1690444 | Q137: =ROUND(Q125*IFERROR(SUM($T$86:$T$97)/SUM($T$74:$T$85),1),0) -> 1935801 | R137: =ROUND(AE137*IFERROR(SUM($R$86:$R$97)/AVERAGE($AE$85,$AE$97),0)/12,0) -> 474583 | S137: =0 -> 0 | T137: =MAX(0,ROUND(T125*IFERROR(SUM($T$86:$T$97)/SUM($T$74:$T$85),1)+('Funding & Cap'!$H$10-'Funding & Cap'!$H$5)*'Funding & Cap'!$B$6/12,0)) -> 3263887 | U137: =IF(MONTH(A137)=IF('Funding & Cap'!$N$4="IPO in 2029",'Funding & Cap'!$N$8,2),'Funding & Cap'!$H$10,0) -> 0 | V137: =0 -> 0 | W137: =IF(MONTH(A137)=12,MIN(AE136,'Funding & Cap'!$H$9),0) -> 0 | X137: =ROUND(X125*IFERROR((SUM(E137:G137)+AI137)/(SUM(E125:G125)+AI125),1),0) -> 44835437 | Y137: =ROUND(Y125*IFERROR((SUM(H137:I137)+AJ137)/(SUM(H125:I125)+AJ125),1),0) -> 20697532 | Z137: =ROUND(Z125*IFERROR(SUM(E137:G137)/SUM(E125:G125),1),0) -> 12924648 | AA137: =ROUND(AA125*IFERROR((SUM(H137:K137)+AJ137+0.25*SUM(L137:M137))/(SUM(H125:K125)+AJ125+0.25*SUM(L125:M125)),1),0) -> 14217310 | AB137: =ROUND(AB125*IFERROR(SUM(L137:O137)/SUM(L125:O125),1),0) -> 22822222 | AC137: =ROUND(AC125*IFERROR(SUM(F137:G137)/SUM(F125:G125),1),0) -> 15522500 | AD137: =MIN(AE137,SUMIFS($W$2:$W$181,$A$2:$A$181,">"&A137,$A$2:$A$181,"<="&EDATE(A137,12))+IF(AND(DATE(2033,12,1)>A137,DATE(2033,12,1)<=EDATE(A137,12)),'Funding & Cap'!$B$200,0)) -> 15000000 | AE137: =SUM($V$2:V137)-SUM($W$2:W137) -> 67000000 | AF137: =AF136+AG137+U137 -> 264250672 | AG137: =SUM(E137:G137)+AI137-SUM(H137:S137)-AJ137+P137+Q137-(X137-X136)-(Y137-Y136)-(Z137-Z136)+(AA137-AA136)+(AB137-AB136)+(AC137-AC136)-T137+V137-W137 -> -8623784 | AH137: ='Revenue & Demand'!I67 -> 6063 | AI137: ='Revenue & Demand'!K67 -> 9094500 | AJ137: ='Manufacturing & Production'!J341 -> 2876929 | AK137: =A137 -> 47209 | AL137: =IF(B137<=2025,C137,"") | AM137: =IF(OR(B137>=2026,AND(B137=2025,MONTH(A137)=12)),C137,"") -> 11561
A138: =EDATE(A126,12) -> 47239 | B138: =YEAR(A138) -> 2029 | C138: ='Revenue & Demand'!C68 -> 11697 | D138: ='Revenue & Demand'!D68 -> 112 | E138: ='Revenue & Demand'!F68 -> 17545500 | F138: ='Revenue & Demand'!G68 -> 4607914 | G138: ='Revenue & Demand'!H68 -> 205882 | H138: ='Manufacturing & Production'!F342 -> 3296744 | I138: ='Manufacturing & Production'!G342 -> 1403640 | J138: ='Workforce & Expenses'!M394 -> 1772549 | K138: ='Manufacturing & Production'!K342 -> 16471 | L138: ='Clinical Trials & R&D'!F342 -> 4878224 | M138: ='Clinical Trials & R&D'!I342 -> 5255367 | N138: ='Workforce & Expenses'!P394 -> 8198265 | O138: ='Workforce & Expenses'!S394 -> 4611941 | P138: =ROUND(P126*(1+MIN(0.2,MAX(0,IFERROR(SUM($P$86:$P$97)/SUM($P$74:$P$85)-1,0)))),0) -> 1722893 | Q138: =ROUND(Q126*IFERROR(SUM($T$86:$T$97)/SUM($T$74:$T$85),1),0) -> 1935801 | R138: =ROUND(AE138*IFERROR(SUM($R$86:$R$97)/AVERAGE($AE$85,$AE$97),0)/12,0) -> 474583 | S138: =0 -> 0 | T138: =MAX(0,ROUND(T126*IFERROR(SUM($T$86:$T$97)/SUM($T$74:$T$85),1)+('Funding & Cap'!$H$10-'Funding & Cap'!$H$5)*'Funding & Cap'!$B$6/12,0)) -> 3363280 | U138: =IF(MONTH(A138)=IF('Funding & Cap'!$N$4="IPO in 2029",'Funding & Cap'!$N$8,2),'Funding & Cap'!$H$10,0) -> 0 | V138: =0 -> 0 | W138: =IF(MONTH(A138)=12,MIN(AE137,'Funding & Cap'!$H$9),0) -> 0 | X138: =ROUND(X126*IFERROR((SUM(E138:G138)+AI138)/(SUM(E126:G126)+AI126),1),0) -> 46509835 | Y138: =ROUND(Y126*IFERROR((SUM(H138:I138)+AJ138)/(SUM(H126:I126)+AJ126),1),0) -> 21429079 | Z138: =ROUND(Z126*IFERROR(SUM(E138:G138)/SUM(E126:G126),1),0) -> 13249805 | AA138: =ROUND(AA126*IFERROR((SUM(H138:K138)+AJ138+0.25*SUM(L138:M138))/(SUM(H126:K126)+AJ126+0.25*SUM(L126:M126)),1),0) -> 15072101 | AB138: =ROUND(AB126*IFERROR(SUM(L138:O138)/SUM(L126:O126),1),0) -> 23881064 | AC138: =ROUND(AC126*IFERROR(SUM(F138:G138)/SUM(F126:G126),1),0) -> 15404410 | AD138: =MIN(AE138,SUMIFS($W$2:$W$181,$A$2:$A$181,">"&A138,$A$2:$A$181,"<="&EDATE(A138,12))+IF(AND(DATE(2033,12,1)>A138,DATE(2033,12,1)<=EDATE(A138,12)),'Funding & Cap'!$B$200,0)) -> 15000000 | AE138: =SUM($V$2:V138)-SUM($W$2:W138) -> 67000000 | AF138: =AF137+AG138+U138 -> 258748271 | AG138: =SUM(E138:G138)+AI138-SUM(H138:S138)-AJ138+P138+Q138-(X138-X137)-(Y138-Y137)-(Z138-Z137)+(AA138-AA137)+(AB138-AB137)+(AC138-AC137)-T138+V138-W138 -> -5502401 | AH138: ='Revenue & Demand'!I68 -> 6184 | AI138: ='Revenue & Demand'!K68 -> 9276000 | AJ138: ='Manufacturing & Production'!J342 -> 2931074 | AK138: =A138 -> 47239 | AL138: =IF(B138<=2025,C138,"") | AM138: =IF(OR(B138>=2026,AND(B138=2025,MONTH(A138)=12)),C138,"") -> 11697
A139: =EDATE(A127,12) -> 47270 | B139: =YEAR(A139) -> 2029 | C139: ='Revenue & Demand'!C69 -> 11834 | D139: ='Revenue & Demand'!D69 -> 114 | E139: ='Revenue & Demand'!F69 -> 17751000 | F139: ='Revenue & Demand'!G69 -> 4219485 | G139: ='Revenue & Demand'!H69 -> 1286765 | H139: ='Manufacturing & Production'!F343 -> 3332148 | I139: ='Manufacturing & Production'!G343 -> 1420080 | J139: ='Workforce & Expenses'!M395 -> 1806496 | K139: ='Manufacturing & Production'!K343 -> 102941 | L139: ='Clinical Trials & R&D'!F343 -> 4899897 | M139: ='Clinical Trials & R&D'!I343 -> 5274489 | N139: ='Workforce & Expenses'!P395 -> 8229401 | O139: ='Workforce & Expenses'!S395 -> 4615383 | P139: =ROUND(P127*(1+MIN(0.2,MAX(0,IFERROR(SUM($P$86:$P$97)/SUM($P$74:$P$85)-1,0)))),0) -> 1755382 | Q139: =ROUND(Q127*IFERROR(SUM($T$86:$T$97)/SUM($T$74:$T$85),1),0) -> 1935801 | R139: =ROUND(AE139*IFERROR(SUM($R$86:$R$97)/AVERAGE($AE$85,$AE$97),0)/12,0) -> 474583 | S139: =0 -> 0 | T139: =MAX(0,ROUND(T127*IFERROR(SUM($T$86:$T$97)/SUM($T$74:$T$85),1)+('Funding & Cap'!$H$10-'Funding & Cap'!$H$5)*'Funding & Cap'!$B$6/12,0)) -> 3464097 | U139: =IF(MONTH(A139)=IF('Funding & Cap'!$N$4="IPO in 2029",'Funding & Cap'!$N$8,2),'Funding & Cap'!$H$10,0) -> 0 | V139: =0 -> 0 | W139: =IF(MONTH(A139)=12,MIN(AE138,'Funding & Cap'!$H$9),0) -> 0 | X139: =ROUND(X127*IFERROR((SUM(E139:G139)+AI139)/(SUM(E127:G127)+AI127),1),0) -> 42821035 | Y139: =ROUND(Y127*IFERROR((SUM(H139:I139)+AJ139)/(SUM(H127:I127)+AJ127),1),0) -> 22089499 | Z139: =ROUND(Z127*IFERROR(SUM(E139:G139)/SUM(E127:G127),1),0) -> 12201974 | AA139: =ROUND(AA127*IFERROR((SUM(H139:K139)+AJ139+0.25*SUM(L139:M139))/(SUM(H127:K127)+AJ127+0.25*SUM(L127:M127)),1),0) -> 15543261 | AB139: =ROUND(AB127*IFERROR(SUM(L139:O139)/SUM(L127:O127),1),0) -> 24928814 | AC139: =ROUND(AC127*IFERROR(SUM(F139:G139)/SUM(F127:G127),1),0) -> 11708226 | AD139: =MIN(AE139,SUMIFS($W$2:$W$181,$A$2:$A$181,">"&A139,$A$2:$A$181,"<="&EDATE(A139,12))+IF(AND(DATE(2033,12,1)>A139,DATE(2033,12,1)<=EDATE(A139,12)),'Funding & Cap'!$B$200,0)) -> 15000000 | AE139: =SUM($V$2:V139)-SUM($W$2:W139) -> 67000000 | AF139: =AF138+AG139+U139 -> 256760383 | AG139: =SUM(E139:G139)+AI139-SUM(H139:S139)-AJ139+P139+Q139-(X139-X138)-(Y139-Y138)-(Z139-Z138)+(AA139-AA138)+(AB139-AB138)+(AC139-AC138)-T139+V139-W139 -> -1987888 | AH139: ='Revenue & Demand'!I69 -> 6308 | AI139: ='Revenue & Demand'!K69 -> 9462000 | AJ139: ='Manufacturing & Production'!J343 -> 2986560 | AK139: =A139 -> 47270 | AL139: =IF(B139<=2025,C139,"") | AM139: =IF(OR(B139>=2026,AND(B139=2025,MONTH(A139)=12)),C139,"") -> 11834
